{"1p5":[{"n":2,"t":"code-golf"}],"3d":[{"n":15,"t":"code-golf"},{"n":2,"t":"math"},{"n":2,"t":"graphical-output"},{"n":4,"t":"geometry"},{"n":3,"t":"ascii-art"}],"abstract-algebra":[{"n":43,"t":"code-golf"},{"n":26,"t":"math"},{"n":7,"t":"polynomials"},{"n":3,"t":"matrix"},{"n":3,"t":"linear-algebra"},{"n":5,"t":"geometry"},{"n":4,"t":"permutations"},{"n":5,"t":"number"},{"n":2,"t":"primes"},{"n":3,"t":"sequence"},{"n":6,"t":"number-theory"},{"n":2,"t":"ascii-art"},{"n":2,"t":"string"},{"n":3,"t":"decision-problem"},{"n":3,"t":"restricted-time"},{"n":3,"t":"combinatorics"}],"ai-player":[{"n":6,"t":"code-challenge"},{"n":3,"t":"game"},{"n":2,"t":"javascript"},{"n":2,"t":"sliding-puzzle"}],"algorithm":[{"n":7,"t":"code-golf"},{"n":2,"t":"math"},{"n":2,"t":"code-challenge"}],"alphabet":[{"n":57,"t":"code-golf"},{"n":22,"t":"kolmogorov-complexity"},{"n":23,"t":"string"},{"n":3,"t":"number"},{"n":10,"t":"ascii-art"},{"n":2,"t":"random"},{"n":2,"t":"sorting"},{"n":2,"t":"decision-problem"}],"animation":[{"n":42,"t":"code-golf"},{"n":26,"t":"ascii-art"},{"n":5,"t":"popularity-contest"},{"n":13,"t":"graphical-output"},{"n":2,"t":"math"},{"n":11,"t":"kolmogorov-complexity"},{"n":11,"t":"string"},{"n":6,"t":"random"}],"answer-chaining":[{"n":4,"t":"printable-ascii"},{"n":2,"t":"hello-world"},{"n":9,"t":"restricted-source"},{"n":5,"t":"code-challenge"},{"n":2,"t":"popularity-contest"},{"n":6,"t":"math"},{"n":2,"t":"kolmogorov-complexity"},{"n":3,"t":"number"},{"n":5,"t":"sequence"},{"n":4,"t":"polyglot"},{"n":2,"t":"arithmetic"},{"n":2,"t":"quine"}],"apl":[{"n":10,"t":"code-golf"},{"n":2,"t":"string"},{"n":2,"t":"classification"},{"n":3,"t":"parsing"},{"n":2,"t":"sequence"}],"approximation":[{"n":10,"t":"code-golf"},{"n":7,"t":"math"},{"n":2,"t":"rational-numbers"},{"n":5,"t":"pi"},{"n":3,"t":"code-challenge"},{"n":2,"t":"random"},{"n":2,"t":"number"}],"arithmetic":[{"n":352,"t":"code-golf"},{"n":3,"t":"checksum"},{"n":6,"t":"division"},{"n":136,"t":"math"},{"n":3,"t":"restricted-time"},{"n":4,"t":"factorial"},{"n":9,"t":"ascii-art"},{"n":4,"t":"repeated-transformation"},{"n":8,"t":"code-challenge"},{"n":11,"t":"expression-building"},{"n":6,"t":"restricted-source"},{"n":3,"t":"set-theory"},{"n":6,"t":"date"},{"n":5,"t":"atomic-code-golf"},{"n":41,"t":"number-theory"},{"n":2,"t":"bitwise"},{"n":105,"t":"number"},{"n":10,"t":"base-conversion"},{"n":6,"t":"rational-numbers"},{"n":7,"t":"kolmogorov-complexity"},{"n":4,"t":"complex-numbers"},{"n":22,"t":"string"},{"n":3,"t":"regular-expression"},{"n":2,"t":"code-generation"},{"n":7,"t":"combinatorics"},{"n":47,"t":"sequence"},{"n":28,"t":"array-manipulation"},{"n":3,"t":"pi"},{"n":4,"t":"binary"},{"n":6,"t":"parsing"},{"n":3,"t":"set-partitions"},{"n":2,"t":"balanced-string"},{"n":4,"t":"recursion"},{"n":8,"t":"geometry"},{"n":3,"t":"interpreter"},{"n":7,"t":"game"},{"n":6,"t":"grid"},{"n":5,"t":"statistics"},{"n":8,"t":"primes"},{"n":3,"t":"random"},{"n":3,"t":"subsequence"},{"n":2,"t":"source-layout"},{"n":7,"t":"matrix"},{"n":2,"t":"roman-numerals"},{"n":16,"t":"decision-problem"},{"n":40,"t":"integer"},{"n":3,"t":"fibonacci"},{"n":3,"t":"permutations"},{"n":3,"t":"integer-partitions"},{"n":2,"t":"answer-chaining"},{"n":4,"t":"cops-and-robbers"},{"n":2,"t":"polyglot"}],"array":[{"n":3,"t":"code-golf"}],"array-manipulation":[{"n":416,"t":"code-golf"},{"n":42,"t":"matrix"},{"n":5,"t":"code-challenge"},{"n":3,"t":"restricted-source"},{"n":10,"t":"random"},{"n":42,"t":"math"},{"n":5,"t":"combinatorics"},{"n":2,"t":"function"},{"n":14,"t":"sequence"},{"n":20,"t":"string"},{"n":2,"t":"tips"},{"n":32,"t":"sorting"},{"n":4,"t":"restricted-complexity"},{"n":66,"t":"number"},{"n":5,"t":"game"},{"n":5,"t":"grid"},{"n":8,"t":"counting"},{"n":12,"t":"permutations"},{"n":28,"t":"arithmetic"},{"n":3,"t":"graph-theory"},{"n":38,"t":"decision-problem"},{"n":2,"t":"set-partitions"},{"n":2,"t":"ascii-art"},{"n":6,"t":"geometry"},{"n":6,"t":"subsequence"},{"n":2,"t":"source-layout"},{"n":4,"t":"bitwise"},{"n":7,"t":"optimization"},{"n":30,"t":"integer"},{"n":4,"t":"number-theory"},{"n":2,"t":"polynomials"},{"n":3,"t":"jelly"},{"n":2,"t":"balanced-string"},{"n":4,"t":"data-structures"},{"n":3,"t":"primes"},{"n":3,"t":"logic"},{"n":2,"t":"parsing"},{"n":3,"t":"generation"},{"n":2,"t":"rubiks-cube"},{"n":3,"t":"search"},{"n":3,"t":"statistics"},{"n":3,"t":"binary-matrix"},{"n":2,"t":"maze"},{"n":2,"t":"functional-programming"}],"ascii-art":[{"n":836,"t":"code-golf"},{"n":12,"t":"code-challenge"},{"n":7,"t":"maze"},{"n":9,"t":"path-finding"},{"n":3,"t":"binary-tree"},{"n":124,"t":"kolmogorov-complexity"},{"n":21,"t":"fractal"},{"n":9,"t":"arithmetic"},{"n":2,"t":"division"},{"n":6,"t":"graph-theory"},{"n":18,"t":"graphical-output"},{"n":26,"t":"math"},{"n":30,"t":"random"},{"n":8,"t":"music"},{"n":11,"t":"popularity-contest"},{"n":26,"t":"animation"},{"n":11,"t":"printable-ascii"},{"n":3,"t":"hello-world"},{"n":152,"t":"string"},{"n":26,"t":"number"},{"n":2,"t":"multiple-holes"},{"n":25,"t":"geometry"},{"n":2,"t":"tips"},{"n":4,"t":"image-processing"},{"n":14,"t":"decision-problem"},{"n":2,"t":"dominoes"},{"n":4,"t":"simulation"},{"n":11,"t":"date"},{"n":4,"t":"chemistry"},{"n":9,"t":"counting"},{"n":5,"t":"combinatorics"},{"n":10,"t":"tiling"},{"n":19,"t":"hexagonal-grid"},{"n":4,"t":"sorting"},{"n":2,"t":"packing"},{"n":35,"t":"grid"},{"n":2,"t":"whitespace"},{"n":3,"t":"balanced-string"},{"n":4,"t":"card-games"},{"n":2,"t":"fibonacci"},{"n":5,"t":"board-game"},{"n":2,"t":"array-manipulation"},{"n":2,"t":"compression"},{"n":7,"t":"base-conversion"},{"n":6,"t":"physics"},{"n":2,"t":"chess"},{"n":3,"t":"optimization"},{"n":2,"t":"logic-gates"},{"n":5,"t":"binary"},{"n":12,"t":"parsing"},{"n":9,"t":"sequence"},{"n":3,"t":"number-theory"},{"n":4,"t":"primes"},{"n":2,"t":"puzzle-solver"},{"n":4,"t":"game"},{"n":2,"t":"conversion"},{"n":3,"t":"unicode"},{"n":2,"t":"abstract-algebra"},{"n":10,"t":"alphabet"},{"n":2,"t":"cellular-automata"},{"n":12,"t":"integer"},{"n":4,"t":"classification"},{"n":2,"t":"interactive"},{"n":6,"t":"matrix"},{"n":4,"t":"binary-matrix"},{"n":2,"t":"restricted-source"},{"n":3,"t":"3d"}],"assembly":[{"n":5,"t":"code-golf"},{"n":2,"t":"machine-code"},{"n":2,"t":"x86-family"},{"n":2,"t":"tips"}],"astronomy":[{"n":3,"t":"code-golf"}],"atomic-code-golf":[{"n":6,"t":"logic-gates"},{"n":9,"t":"math"},{"n":3,"t":"number-theory"},{"n":2,"t":"restricted-source"},{"n":5,"t":"arithmetic"},{"n":3,"t":"graph-theory"},{"n":2,"t":"proof-golf"},{"n":3,"t":"code-challenge"},{"n":3,"t":"game"}],"audio":[{"n":14,"t":"code-golf"},{"n":7,"t":"music"},{"n":2,"t":"popularity-contest"},{"n":2,"t":"classification"},{"n":4,"t":"kolmogorov-complexity"}],"balanced-string":[{"n":58,"t":"code-golf"},{"n":33,"t":"string"},{"n":4,"t":"whitespace"},{"n":6,"t":"decision-problem"},{"n":3,"t":"brainfuck"},{"n":2,"t":"restricted-source"},{"n":2,"t":"code-challenge"},{"n":4,"t":"syntax"},{"n":3,"t":"ascii-art"},{"n":2,"t":"arithmetic"},{"n":2,"t":"recursion"},{"n":5,"t":"number"},{"n":3,"t":"sequence"},{"n":3,"t":"parsing"},{"n":2,"t":"combinatorics"},{"n":6,"t":"brain-flak"},{"n":2,"t":"array-manipulation"},{"n":2,"t":"permutations"},{"n":2,"t":"primes"}],"base-conversion":[{"n":116,"t":"code-golf"},{"n":23,"t":"binary"},{"n":37,"t":"number"},{"n":3,"t":"decision-problem"},{"n":5,"t":"palindrome"},{"n":10,"t":"arithmetic"},{"n":12,"t":"number-theory"},{"n":25,"t":"math"},{"n":2,"t":"code-challenge"},{"n":11,"t":"string"},{"n":18,"t":"sequence"},{"n":7,"t":"ascii-art"},{"n":2,"t":"fibonacci"},{"n":4,"t":"primes"},{"n":6,"t":"hexadecimal"},{"n":2,"t":"counting"},{"n":2,"t":"roman-numerals"},{"n":2,"t":"subsequence"},{"n":10,"t":"integer"},{"n":2,"t":"combinatorics"},{"n":2,"t":"restricted-source"},{"n":2,"t":"parsing"},{"n":2,"t":"compression"},{"n":2,"t":"floating-point"}],"basic":[{"n":4,"t":"code-golf"},{"n":4,"t":"tips"}],"befunge":[{"n":2,"t":"code-golf"},{"n":3,"t":"stack"},{"n":2,"t":"code-challenge"}],"binary":[{"n":127,"t":"code-golf"},{"n":3,"t":"palindrome"},{"n":25,"t":"number"},{"n":23,"t":"base-conversion"},{"n":4,"t":"number-theory"},{"n":11,"t":"string"},{"n":2,"t":"conversion"},{"n":2,"t":"counting"},{"n":4,"t":"arithmetic"},{"n":29,"t":"sequence"},{"n":5,"t":"ascii-art"},{"n":2,"t":"game"},{"n":9,"t":"math"},{"n":6,"t":"primes"},{"n":9,"t":"bitwise"},{"n":4,"t":"subsequence"},{"n":2,"t":"permutations"},{"n":2,"t":"logic-gates"},{"n":2,"t":"logic"},{"n":5,"t":"restricted-source"},{"n":12,"t":"decision-problem"},{"n":2,"t":"kolmogorov-complexity"},{"n":11,"t":"integer"},{"n":2,"t":"combinatorics"},{"n":2,"t":"binary-matrix"},{"n":2,"t":"graph-theory"},{"n":2,"t":"encode"}],"binary-matrix":[{"n":5,"t":"code-challenge"},{"n":2,"t":"math"},{"n":26,"t":"code-golf"},{"n":6,"t":"matrix"},{"n":2,"t":"linear-algebra"},{"n":2,"t":"binary"},{"n":4,"t":"ascii-art"},{"n":2,"t":"unicode"},{"n":3,"t":"decision-problem"},{"n":2,"t":"game"},{"n":2,"t":"graph-theory"},{"n":3,"t":"array-manipulation"},{"n":3,"t":"grid"},{"n":2,"t":"string"}],"binary-tree":[{"n":14,"t":"code-golf"},{"n":3,"t":"ascii-art"},{"n":2,"t":"math"},{"n":2,"t":"tree-traversal"},{"n":2,"t":"graph-theory"},{"n":2,"t":"decision-problem"},{"n":2,"t":"sequence"}],"bioinformatics":[{"n":5,"t":"code-golf"},{"n":3,"t":"string"}],"bitwise":[{"n":44,"t":"code-golf"},{"n":3,"t":"sorting"},{"n":7,"t":"math"},{"n":2,"t":"arithmetic"},{"n":2,"t":"restricted-source"},{"n":6,"t":"number"},{"n":6,"t":"integer"},{"n":2,"t":"primes"},{"n":2,"t":"sequence"},{"n":9,"t":"binary"},{"n":4,"t":"array-manipulation"},{"n":5,"t":"string"},{"n":2,"t":"permutations"}],"board-game":[{"n":35,"t":"code-golf"},{"n":13,"t":"game"},{"n":3,"t":"go"},{"n":5,"t":"king-of-the-hill"},{"n":4,"t":"hexagonal-grid"},{"n":3,"t":"string"},{"n":2,"t":"scrabble"},{"n":4,"t":"decision-problem"},{"n":4,"t":"chess"},{"n":4,"t":"tic-tac-toe"},{"n":2,"t":"path-finding"},{"n":5,"t":"ascii-art"},{"n":5,"t":"kolmogorov-complexity"},{"n":5,"t":"grid"}],"boggle":[{"n":6,"t":"code-golf"},{"n":4,"t":"code-challenge"},{"n":3,"t":"string"},{"n":2,"t":"decision-problem"}],"brain-flak":[{"n":11,"t":"code-golf"},{"n":6,"t":"balanced-string"},{"n":2,"t":"stack"},{"n":3,"t":"metagolf"},{"n":2,"t":"test-battery"},{"n":2,"t":"restricted-source"},{"n":4,"t":"string"},{"n":2,"t":"code-challenge"}],"brainfuck":[{"n":24,"t":"code-golf"},{"n":2,"t":"interpreter"},{"n":7,"t":"code-challenge"},{"n":2,"t":"busy-beaver"},{"n":7,"t":"code-generation"},{"n":3,"t":"kolmogorov-complexity"},{"n":4,"t":"metagolf"},{"n":3,"t":"tips"},{"n":3,"t":"balanced-string"},{"n":2,"t":"compiler"},{"n":2,"t":"restricted-source"}],"browser":[{"n":3,"t":"code-golf"}],"busy-beaver":[{"n":14,"t":"code-challenge"},{"n":2,"t":"brainfuck"},{"n":4,"t":"code-golf"},{"n":4,"t":"math"},{"n":4,"t":"number"},{"n":3,"t":"restricted-source"},{"n":2,"t":"quine"}],"c":[{"n":10,"t":"code-golf"},{"n":2,"t":"tips"},{"n":3,"t":"popularity-contest"},{"n":4,"t":"code-challenge"},{"n":5,"t":"c++"},{"n":4,"t":"string"},{"n":3,"t":"parsing"}],"c#":[{"n":4,"t":"code-golf"},{"n":5,"t":"programming-puzzle"}],"c++":[{"n":5,"t":"code-challenge"},{"n":5,"t":"code-golf"},{"n":3,"t":"tips"},{"n":2,"t":"popularity-contest"},{"n":2,"t":"restricted-source"},{"n":5,"t":"c"},{"n":2,"t":"programming-puzzle"},{"n":2,"t":"polyglot"},{"n":2,"t":"king-of-the-hill"}],"calculus":[{"n":15,"t":"code-golf"},{"n":14,"t":"math"},{"n":4,"t":"polynomials"}],"card-games":[{"n":40,"t":"code-golf"},{"n":5,"t":"king-of-the-hill"},{"n":2,"t":"java"},{"n":7,"t":"game"},{"n":5,"t":"combinatorics"},{"n":4,"t":"ascii-art"},{"n":6,"t":"decision-problem"},{"n":2,"t":"string"},{"n":2,"t":"permutations"},{"n":2,"t":"kolmogorov-complexity"},{"n":2,"t":"random"}],"cellular-automata":[{"n":26,"t":"code-golf"},{"n":4,"t":"graphical-output"},{"n":10,"t":"game-of-life"},{"n":2,"t":"sequence"},{"n":4,"t":"code-challenge"},{"n":4,"t":"game"},{"n":2,"t":"grid"},{"n":2,"t":"ascii-art"},{"n":2,"t":"matrix"}],"checksum":[{"n":8,"t":"code-golf"},{"n":3,"t":"arithmetic"},{"n":3,"t":"math"}],"chemistry":[{"n":31,"t":"code-golf"},{"n":3,"t":"math"},{"n":8,"t":"string"},{"n":2,"t":"number"},{"n":4,"t":"ascii-art"},{"n":8,"t":"kolmogorov-complexity"},{"n":2,"t":"parsing"},{"n":2,"t":"combinatorics"}],"chess":[{"n":51,"t":"code-golf"},{"n":3,"t":"code-challenge"},{"n":3,"t":"king-of-the-hill"},{"n":8,"t":"decision-problem"},{"n":4,"t":"board-game"},{"n":2,"t":"ascii-art"},{"n":3,"t":"kolmogorov-complexity"},{"n":2,"t":"string"},{"n":5,"t":"grid"},{"n":2,"t":"graph-theory"},{"n":3,"t":"number"},{"n":2,"t":"path-finding"},{"n":2,"t":"integer"}],"cipher":[{"n":16,"t":"code-golf"},{"n":12,"t":"string"},{"n":3,"t":"encoding"}],"classification":[{"n":35,"t":"code-golf"},{"n":2,"t":"audio"},{"n":8,"t":"test-battery"},{"n":8,"t":"code-challenge"},{"n":10,"t":"string"},{"n":4,"t":"natural-language"},{"n":3,"t":"word"},{"n":5,"t":"decision-problem"},{"n":5,"t":"number"},{"n":3,"t":"random"},{"n":4,"t":"ascii-art"},{"n":2,"t":"parsing"},{"n":2,"t":"apl"},{"n":2,"t":"matrix"}],"clock":[{"n":8,"t":"code-golf"}],"code-bowling":[{"n":3,"t":"hello-world"},{"n":3,"t":"pangram"},{"n":4,"t":"code-challenge"},{"n":2,"t":"cops-and-robbers"},{"n":2,"t":"string"},{"n":4,"t":"restricted-source"},{"n":2,"t":"radiation-hardening"},{"n":2,"t":"pristine-programming"}],"code-challenge":[{"n":39,"t":"math"},{"n":5,"t":"random"},{"n":5,"t":"c++"},{"n":12,"t":"ascii-art"},{"n":4,"t":"maze"},{"n":6,"t":"cryptography"},{"n":23,"t":"quine"},{"n":8,"t":"rosetta-stone"},{"n":3,"t":"fastest-algorithm"},{"n":4,"t":"popularity-contest"},{"n":4,"t":"regular-expression"},{"n":8,"t":"fastest-code"},{"n":47,"t":"restricted-source"},{"n":5,"t":"array-manipulation"},{"n":3,"t":"palindrome"},{"n":6,"t":"error-message"},{"n":16,"t":"kolmogorov-complexity"},{"n":10,"t":"sorting"},{"n":7,"t":"brainfuck"},{"n":2,"t":"word-puzzle"},{"n":18,"t":"game"},{"n":3,"t":"king-of-the-hill"},{"n":10,"t":"self-referential"},{"n":3,"t":"compile-time"},{"n":2,"t":"interpreter"},{"n":24,"t":"polyglot"},{"n":14,"t":"graphical-output"},{"n":14,"t":"busy-beaver"},{"n":32,"t":"source-layout"},{"n":2,"t":"underhanded"},{"n":10,"t":"metagolf"},{"n":4,"t":"boggle"},{"n":14,"t":"primes"},{"n":5,"t":"game-of-life"},{"n":7,"t":"puzzle-solver"},{"n":3,"t":"sliding-puzzle"},{"n":4,"t":"python"},{"n":3,"t":"programming-puzzle"},{"n":4,"t":"c"},{"n":10,"t":"decision-problem"},{"n":8,"t":"radiation-hardening"},{"n":31,"t":"optimization"},{"n":9,"t":"permutations"},{"n":2,"t":"scrabble"},{"n":5,"t":"stack"},{"n":5,"t":"optimized-output"},{"n":2,"t":"befunge"},{"n":23,"t":"test-battery"},{"n":8,"t":"number-theory"},{"n":8,"t":"arithmetic"},{"n":4,"t":"expression-building"},{"n":11,"t":"printable-ascii"},{"n":19,"t":"compression"},{"n":14,"t":"image-processing"},{"n":4,"t":"tetris"},{"n":9,"t":"hello-world"},{"n":3,"t":"obfuscation"},{"n":4,"t":"cellular-automata"},{"n":2,"t":"rubiks-cube"},{"n":4,"t":"javascript"},{"n":2,"t":"logic-gates"},{"n":16,"t":"combinatorics"},{"n":5,"t":"multiple-holes"},{"n":22,"t":"number"},{"n":3,"t":"internet"},{"n":40,"t":"string"},{"n":3,"t":"chess"},{"n":2,"t":"stack-exchange-api"},{"n":9,"t":"natural-language"},{"n":5,"t":"keyboard"},{"n":5,"t":"binary-matrix"},{"n":6,"t":"ai-player"},{"n":2,"t":"word"},{"n":11,"t":"geometry"},{"n":10,"t":"graph-theory"},{"n":9,"t":"path-finding"},{"n":3,"t":"approximation"},{"n":13,"t":"code-generation"},{"n":3,"t":"compiler"},{"n":2,"t":"balanced-string"},{"n":4,"t":"code-bowling"},{"n":2,"t":"rational-numbers"},{"n":11,"t":"cops-and-robbers"},{"n":4,"t":"counting"},{"n":2,"t":"tiling"},{"n":3,"t":"sudoku"},{"n":3,"t":"unicode"},{"n":2,"t":"base-conversion"},{"n":8,"t":"classification"},{"n":2,"t":"probability-theory"},{"n":2,"t":"fibonacci"},{"n":3,"t":"packing"},{"n":5,"t":"answer-chaining"},{"n":9,"t":"grid"},{"n":22,"t":"sequence"},{"n":2,"t":"word-search"},{"n":9,"t":"integer"},{"n":4,"t":"parsing"},{"n":2,"t":"statistics"},{"n":2,"t":"hashing"},{"n":10,"t":"code-golf"},{"n":2,"t":"brain-flak"},{"n":2,"t":"matrix"},{"n":3,"t":"restricted-time"},{"n":3,"t":"atomic-code-golf"},{"n":2,"t":"encode"},{"n":2,"t":"polynomials"},{"n":3,"t":"polyomino"},{"n":2,"t":"pristine-programming"},{"n":2,"t":"neural-networks"},{"n":2,"t":"algorithm"}],"code-generation":[{"n":31,"t":"code-golf"},{"n":7,"t":"brainfuck"},{"n":2,"t":"generation"},{"n":3,"t":"metagolf"},{"n":15,"t":"quine"},{"n":13,"t":"code-challenge"},{"n":2,"t":"arithmetic"},{"n":6,"t":"kolmogorov-complexity"},{"n":3,"t":"restricted-source"},{"n":2,"t":"math"},{"n":2,"t":"number"},{"n":3,"t":"sequence"},{"n":2,"t":"polyglot"},{"n":2,"t":"parsing"},{"n":2,"t":"cops-and-robbers"},{"n":2,"t":"obfuscation"}],"code-golf":[{"n":29,"t":"cryptography"},{"n":554,"t":"sequence"},{"n":298,"t":"number-theory"},{"n":29,"t":"restricted-time"},{"n":352,"t":"arithmetic"},{"n":8,"t":"checksum"},{"n":928,"t":"math"},{"n":208,"t":"geometry"},{"n":8,"t":"clock"},{"n":24,"t":"python"},{"n":127,"t":"tips"},{"n":128,"t":"quine"},{"n":67,"t":"interpreter"},{"n":24,"t":"brainfuck"},{"n":804,"t":"number"},{"n":70,"t":"fibonacci"},{"n":10,"t":"obfuscation"},{"n":124,"t":"restricted-source"},{"n":190,"t":"primes"},{"n":9,"t":"morse"},{"n":5,"t":"c++"},{"n":28,"t":"compression"},{"n":94,"t":"graph-theory"},{"n":69,"t":"path-finding"},{"n":52,"t":"palindrome"},{"n":4,"t":"c#"},{"n":1292,"t":"string"},{"n":61,"t":"subsequence"},{"n":836,"t":"ascii-art"},{"n":38,"t":"music"},{"n":14,"t":"audio"},{"n":4,"t":"lambda-calculus"},{"n":30,"t":"hello-world"},{"n":145,"t":"game"},{"n":40,"t":"puzzle-solver"},{"n":10,"t":"sudoku"},{"n":3,"t":"ruby"},{"n":39,"t":"conversion"},{"n":107,"t":"sorting"},{"n":194,"t":"random"},{"n":13,"t":"javascript"},{"n":38,"t":"regular-expression"},{"n":3,"t":"compiler"},{"n":33,"t":"division"},{"n":35,"t":"pi"},{"n":29,"t":"probability-theory"},{"n":5,"t":"assembly"},{"n":19,"t":"factorial"},{"n":22,"t":"stack"},{"n":2,"t":"befunge"},{"n":16,"t":"cipher"},{"n":127,"t":"binary"},{"n":29,"t":"function"},{"n":15,"t":"roman-numerals"},{"n":43,"t":"abstract-algebra"},{"n":43,"t":"polynomials"},{"n":14,"t":"binary-tree"},{"n":10,"t":"repeated-transformation"},{"n":2,"t":"markov-chain"},{"n":162,"t":"date"},{"n":432,"t":"kolmogorov-complexity"},{"n":50,"t":"fractal"},{"n":11,"t":"tic-tac-toe"},{"n":11,"t":"word"},{"n":6,"t":"word-puzzle"},{"n":6,"t":"optimized-output"},{"n":416,"t":"array-manipulation"},{"n":164,"t":"matrix"},{"n":108,"t":"permutations"},{"n":9,"t":"sliding-puzzle"},{"n":179,"t":"combinatorics"},{"n":52,"t":"rational-numbers"},{"n":6,"t":"haskell"},{"n":180,"t":"graphical-output"},{"n":197,"t":"grid"},{"n":26,"t":"simulation"},{"n":25,"t":"factoring"},{"n":433,"t":"decision-problem"},{"n":57,"t":"alphabet"},{"n":10,"t":"c"},{"n":32,"t":"maze"},{"n":2,"t":"1p5"},{"n":21,"t":"complex-numbers"},{"n":32,"t":"polyglot"},{"n":51,"t":"chess"},{"n":26,"t":"integer-partitions"},{"n":2,"t":"multi-threading"},{"n":40,"t":"card-games"},{"n":22,"t":"set-theory"},{"n":7,"t":"lisp"},{"n":22,"t":"generation"},{"n":43,"t":"hexagonal-grid"},{"n":26,"t":"cellular-automata"},{"n":26,"t":"whitespace"},{"n":58,"t":"balanced-string"},{"n":7,"t":"metagolf"},{"n":21,"t":"trigonometry"},{"n":7,"t":"crossword"},{"n":6,"t":"word-search"},{"n":15,"t":"game-of-life"},{"n":10,"t":"approximation"},{"n":42,"t":"animation"},{"n":34,"t":"printable-ascii"},{"n":116,"t":"base-conversion"},{"n":6,"t":"boggle"},{"n":4,"t":"basic"},{"n":31,"t":"code-generation"},{"n":3,"t":"golfscript"},{"n":5,"t":"rosetta-stone"},{"n":35,"t":"board-game"},{"n":4,"t":"busy-beaver"},{"n":11,"t":"minesweeper"},{"n":3,"t":"java"},{"n":4,"t":"go"},{"n":76,"t":"counting"},{"n":31,"t":"chemistry"},{"n":45,"t":"internet"},{"n":53,"t":"natural-language"},{"n":16,"t":"rubiks-cube"},{"n":17,"t":"self-referential"},{"n":8,"t":"floating-point"},{"n":3,"t":"machine-code"},{"n":3,"t":"x86-family"},{"n":125,"t":"parsing"},{"n":27,"t":"restricted-complexity"},{"n":23,"t":"file-system"},{"n":16,"t":"expression-building"},{"n":82,"t":"source-layout"},{"n":3,"t":"whitespace-language"},{"n":6,"t":"programming-puzzle"},{"n":40,"t":"unicode"},{"n":16,"t":"stack-exchange-api"},{"n":3,"t":"octave"},{"n":2,"t":"concurrency"},{"n":3,"t":"vim"},{"n":15,"t":"hashing"},{"n":13,"t":"new-years"},{"n":271,"t":"integer"},{"n":52,"t":"image-processing"},{"n":10,"t":"apl"},{"n":2,"t":"manufactoria"},{"n":36,"t":"set-partitions"},{"n":3,"t":"browser"},{"n":15,"t":"functional-programming"},{"n":44,"t":"bitwise"},{"n":2,"t":"lua"},{"n":3,"t":"steganography"},{"n":2,"t":"popularity-contest"},{"n":9,"t":"encode"},{"n":7,"t":"electrical-engineering"},{"n":7,"t":"networking"},{"n":5,"t":"pattern-matching"},{"n":7,"t":"knot-theory"},{"n":32,"t":"keyboard"},{"n":15,"t":"calculus"},{"n":3,"t":"sql"},{"n":9,"t":"dominoes"},{"n":15,"t":"3d"},{"n":14,"t":"logic"},{"n":28,"t":"tiling"},{"n":4,"t":"scrabble"},{"n":35,"t":"cops-and-robbers"},{"n":35,"t":"classification"},{"n":9,"t":"stateful"},{"n":2,"t":"pyth"},{"n":24,"t":"recursion"},{"n":13,"t":"typography"},{"n":5,"t":"bioinformatics"},{"n":33,"t":"linear-algebra"},{"n":12,"t":"multiple-holes"},{"n":27,"t":"optimization"},{"n":4,"t":"error-correction"},{"n":3,"t":"coding-theory"},{"n":23,"t":"hexadecimal"},{"n":7,"t":"comment"},{"n":14,"t":"syntax"},{"n":6,"t":"packing"},{"n":11,"t":"logic-gates"},{"n":12,"t":"topology"},{"n":7,"t":"tetris"},{"n":3,"t":"connected-figure"},{"n":18,"t":"data-structures"},{"n":6,"t":"tree-traversal"},{"n":25,"t":"physics"},{"n":3,"t":"fizzbuzz"},{"n":16,"t":"interactive"},{"n":17,"t":"statistics"},{"n":4,"t":"pristine-programming"},{"n":2,"t":"restricted-memory"},{"n":3,"t":"grammars"},{"n":3,"t":"astronomy"},{"n":26,"t":"binary-matrix"},{"n":4,"t":"jelly"},{"n":9,"t":"encryption"},{"n":11,"t":"radiation-hardening"},{"n":4,"t":"json"},{"n":20,"t":"color"},{"n":11,"t":"brain-flak"},{"n":13,"t":"search"},{"n":3,"t":"decode"},{"n":7,"t":"algorithm"},{"n":4,"t":"halting-problem"},{"n":3,"t":"hardware"},{"n":9,"t":"substitution"},{"n":2,"t":"compile-time"},{"n":10,"t":"code-challenge"},{"n":2,"t":"language-design"},{"n":3,"t":"error-message"},{"n":10,"t":"text-processing"},{"n":3,"t":"equation"},{"n":2,"t":"pangram"},{"n":7,"t":"polyomino"},{"n":4,"t":"encoding"},{"n":3,"t":"array"},{"n":2,"t":"fastest-algorithm"}],"code-shuffleboard":[{"n":2,"t":"restricted-source"}],"code-trolling":[{"n":8,"t":"popularity-contest"}],"coding-theory":[{"n":3,"t":"code-golf"}],"color":[{"n":2,"t":"popularity-contest"},{"n":8,"t":"graphical-output"},{"n":5,"t":"image-processing"},{"n":20,"t":"code-golf"},{"n":2,"t":"math"},{"n":4,"t":"string"},{"n":3,"t":"hexadecimal"},{"n":2,"t":"conversion"},{"n":2,"t":"kolmogorov-complexity"}],"combinatorics":[{"n":179,"t":"code-golf"},{"n":51,"t":"math"},{"n":27,"t":"permutations"},{"n":5,"t":"array-manipulation"},{"n":12,"t":"fastest-code"},{"n":45,"t":"sequence"},{"n":16,"t":"code-challenge"},{"n":2,"t":"graphical-output"},{"n":20,"t":"number"},{"n":5,"t":"ascii-art"},{"n":8,"t":"tiling"},{"n":14,"t":"number-theory"},{"n":3,"t":"primes"},{"n":8,"t":"graph-theory"},{"n":7,"t":"arithmetic"},{"n":3,"t":"counting"},{"n":3,"t":"subsequence"},{"n":6,"t":"random"},{"n":8,"t":"integer-partitions"},{"n":13,"t":"set-partitions"},{"n":4,"t":"game"},{"n":5,"t":"card-games"},{"n":8,"t":"decision-problem"},{"n":16,"t":"grid"},{"n":3,"t":"restricted-time"},{"n":2,"t":"balanced-string"},{"n":12,"t":"string"},{"n":4,"t":"probability-theory"},{"n":2,"t":"base-conversion"},{"n":2,"t":"chemistry"},{"n":2,"t":"path-finding"},{"n":3,"t":"dominoes"},{"n":2,"t":"kolmogorov-complexity"},{"n":2,"t":"binary"},{"n":2,"t":"optimization"},{"n":2,"t":"source-layout"},{"n":3,"t":"abstract-algebra"},{"n":4,"t":"integer"},{"n":14,"t":"geometry"},{"n":6,"t":"polyomino"},{"n":2,"t":"topology"},{"n":2,"t":"hexagonal-grid"}],"comment":[{"n":7,"t":"code-golf"},{"n":4,"t":"string"},{"n":2,"t":"parsing"}],"compile-time":[{"n":3,"t":"code-challenge"},{"n":2,"t":"popularity-contest"},{"n":2,"t":"code-golf"}],"compiler":[{"n":3,"t":"code-golf"},{"n":2,"t":"brainfuck"},{"n":3,"t":"code-challenge"}],"complex-numbers":[{"n":21,"t":"code-golf"},{"n":2,"t":"graphical-output"},{"n":9,"t":"math"},{"n":4,"t":"arithmetic"},{"n":3,"t":"matrix"},{"n":2,"t":"linear-algebra"},{"n":2,"t":"number-theory"}],"compression":[{"n":28,"t":"code-golf"},{"n":12,"t":"string"},{"n":19,"t":"code-challenge"},{"n":3,"t":"image-processing"},{"n":2,"t":"encode"},{"n":2,"t":"ascii-art"},{"n":2,"t":"number"},{"n":6,"t":"kolmogorov-complexity"},{"n":2,"t":"tips"},{"n":2,"t":"graphical-output"},{"n":2,"t":"decision-problem"},{"n":2,"t":"base-conversion"},{"n":2,"t":"game"}],"concurrency":[{"n":2,"t":"code-golf"}],"connected-figure":[{"n":3,"t":"code-golf"}],"conversion":[{"n":39,"t":"code-golf"},{"n":10,"t":"string"},{"n":2,"t":"binary"},{"n":3,"t":"hexadecimal"},{"n":3,"t":"integer"},{"n":2,"t":"natural-language"},{"n":2,"t":"whitespace"},{"n":3,"t":"unicode"},{"n":6,"t":"number"},{"n":5,"t":"date"},{"n":2,"t":"ascii-art"},{"n":3,"t":"parsing"},{"n":2,"t":"color"}],"cops-and-robbers":[{"n":35,"t":"code-golf"},{"n":22,"t":"sequence"},{"n":12,"t":"obfuscation"},{"n":11,"t":"code-challenge"},{"n":2,"t":"code-bowling"},{"n":3,"t":"regular-expression"},{"n":3,"t":"printable-ascii"},{"n":7,"t":"source-layout"},{"n":2,"t":"crossword"},{"n":3,"t":"primes"},{"n":2,"t":"king-of-the-hill"},{"n":2,"t":"hexagonal-grid"},{"n":2,"t":"java"},{"n":2,"t":"cryptography"},{"n":2,"t":"hashing"},{"n":3,"t":"hello-world"},{"n":7,"t":"kolmogorov-complexity"},{"n":2,"t":"popularity-contest"},{"n":8,"t":"number"},{"n":4,"t":"polyglot"},{"n":3,"t":"quine"},{"n":6,"t":"permutations"},{"n":4,"t":"string"},{"n":2,"t":"whitespace"},{"n":2,"t":"matrix"},{"n":6,"t":"restricted-source"},{"n":4,"t":"arithmetic"},{"n":3,"t":"decision-problem"},{"n":2,"t":"integer"},{"n":2,"t":"code-generation"}],"counting":[{"n":76,"t":"code-golf"},{"n":14,"t":"number"},{"n":8,"t":"sequence"},{"n":20,"t":"string"},{"n":2,"t":"popularity-contest"},{"n":6,"t":"math"},{"n":9,"t":"ascii-art"},{"n":4,"t":"code-challenge"},{"n":8,"t":"array-manipulation"},{"n":3,"t":"combinatorics"},{"n":2,"t":"binary"},{"n":4,"t":"geometry"},{"n":10,"t":"grid"},{"n":2,"t":"permutations"},{"n":2,"t":"game"},{"n":2,"t":"base-conversion"},{"n":2,"t":"primes"},{"n":2,"t":"date"},{"n":2,"t":"natural-language"},{"n":3,"t":"subsequence"}],"crossword":[{"n":7,"t":"code-golf"},{"n":2,"t":"printable-ascii"},{"n":2,"t":"source-layout"},{"n":2,"t":"cops-and-robbers"},{"n":2,"t":"grid"},{"n":3,"t":"string"}],"cryptography":[{"n":29,"t":"code-golf"},{"n":6,"t":"code-challenge"},{"n":3,"t":"math"},{"n":2,"t":"polynomials"},{"n":9,"t":"string"},{"n":2,"t":"cops-and-robbers"},{"n":2,"t":"hashing"},{"n":2,"t":"random"},{"n":2,"t":"kolmogorov-complexity"}],"data-structures":[{"n":18,"t":"code-golf"},{"n":3,"t":"string"},{"n":4,"t":"array-manipulation"},{"n":2,"t":"generation"},{"n":2,"t":"graph-theory"}],"date":[{"n":162,"t":"code-golf"},{"n":16,"t":"kolmogorov-complexity"},{"n":3,"t":"math"},{"n":6,"t":"arithmetic"},{"n":11,"t":"ascii-art"},{"n":2,"t":"regular-expression"},{"n":23,"t":"string"},{"n":7,"t":"decision-problem"},{"n":3,"t":"interactive"},{"n":2,"t":"natural-language"},{"n":3,"t":"parsing"},{"n":10,"t":"number"},{"n":2,"t":"pi"},{"n":5,"t":"conversion"},{"n":2,"t":"palindrome"},{"n":4,"t":"primes"},{"n":2,"t":"counting"},{"n":3,"t":"sorting"}],"decision-problem":[{"n":433,"t":"code-golf"},{"n":50,"t":"math"},{"n":13,"t":"geometry"},{"n":34,"t":"number-theory"},{"n":79,"t":"string"},{"n":75,"t":"number"},{"n":26,"t":"primes"},{"n":10,"t":"code-challenge"},{"n":8,"t":"palindrome"},{"n":3,"t":"quine"},{"n":6,"t":"balanced-string"},{"n":17,"t":"restricted-source"},{"n":18,"t":"integer"},{"n":3,"t":"sudoku"},{"n":3,"t":"base-conversion"},{"n":6,"t":"regular-expression"},{"n":3,"t":"pattern-matching"},{"n":14,"t":"ascii-art"},{"n":3,"t":"knot-theory"},{"n":16,"t":"graph-theory"},{"n":6,"t":"path-finding"},{"n":8,"t":"chess"},{"n":4,"t":"board-game"},{"n":2,"t":"tic-tac-toe"},{"n":3,"t":"maze"},{"n":3,"t":"syntax"},{"n":23,"t":"grid"},{"n":5,"t":"classification"},{"n":8,"t":"combinatorics"},{"n":7,"t":"date"},{"n":38,"t":"array-manipulation"},{"n":4,"t":"set-partitions"},{"n":3,"t":"simulation"},{"n":7,"t":"subsequence"},{"n":5,"t":"natural-language"},{"n":2,"t":"physics"},{"n":4,"t":"factoring"},{"n":3,"t":"hexagonal-grid"},{"n":19,"t":"sequence"},{"n":6,"t":"card-games"},{"n":4,"t":"permutations"},{"n":14,"t":"game"},{"n":20,"t":"matrix"},{"n":2,"t":"compression"},{"n":16,"t":"arithmetic"},{"n":4,"t":"set-theory"},{"n":4,"t":"parsing"},{"n":4,"t":"division"},{"n":12,"t":"binary"},{"n":4,"t":"tiling"},{"n":2,"t":"linear-algebra"},{"n":2,"t":"tree-traversal"},{"n":2,"t":"unicode"},{"n":2,"t":"internet"},{"n":3,"t":"abstract-algebra"},{"n":2,"t":"rational-numbers"},{"n":2,"t":"python"},{"n":3,"t":"fibonacci"},{"n":2,"t":"topology"},{"n":3,"t":"cops-and-robbers"},{"n":2,"t":"test-battery"},{"n":3,"t":"binary-matrix"},{"n":2,"t":"alphabet"},{"n":2,"t":"interpreter"},{"n":2,"t":"halting-problem"},{"n":4,"t":"source-layout"},{"n":2,"t":"boggle"},{"n":2,"t":"binary-tree"},{"n":3,"t":"polyomino"}],"decode":[{"n":3,"t":"code-golf"}],"division":[{"n":33,"t":"code-golf"},{"n":6,"t":"arithmetic"},{"n":2,"t":"ascii-art"},{"n":9,"t":"math"},{"n":11,"t":"number"},{"n":2,"t":"primes"},{"n":7,"t":"sequence"},{"n":12,"t":"number-theory"},{"n":4,"t":"decision-problem"},{"n":6,"t":"integer"},{"n":2,"t":"fibonacci"}],"dominoes":[{"n":9,"t":"code-golf"},{"n":2,"t":"ascii-art"},{"n":3,"t":"combinatorics"},{"n":2,"t":"tiling"}],"duct-tape-coding":[{"n":3,"t":"popularity-contest"},{"n":2,"t":"restricted-source"}],"electrical-engineering":[{"n":7,"t":"code-golf"},{"n":3,"t":"physics"},{"n":2,"t":"math"}],"encode":[{"n":9,"t":"code-golf"},{"n":4,"t":"string"},{"n":2,"t":"compression"},{"n":2,"t":"code-challenge"},{"n":2,"t":"binary"}],"encoding":[{"n":4,"t":"code-golf"},{"n":4,"t":"string"},{"n":3,"t":"cipher"}],"encryption":[{"n":9,"t":"code-golf"},{"n":4,"t":"string"}],"equation":[{"n":3,"t":"code-golf"},{"n":2,"t":"polynomials"}],"error-correction":[{"n":4,"t":"code-golf"}],"error-message":[{"n":6,"t":"code-challenge"},{"n":3,"t":"quine"},{"n":3,"t":"code-golf"}],"expression-building":[{"n":5,"t":"math"},{"n":4,"t":"code-challenge"},{"n":11,"t":"arithmetic"},{"n":16,"t":"code-golf"},{"n":5,"t":"number"},{"n":2,"t":"restricted-source"},{"n":4,"t":"integer"}],"factorial":[{"n":19,"t":"code-golf"},{"n":4,"t":"arithmetic"},{"n":2,"t":"restricted-time"},{"n":13,"t":"math"},{"n":3,"t":"number-theory"},{"n":2,"t":"sequence"},{"n":2,"t":"string"},{"n":3,"t":"number"},{"n":3,"t":"integer"}],"factoring":[{"n":25,"t":"code-golf"},{"n":8,"t":"number-theory"},{"n":15,"t":"primes"},{"n":7,"t":"math"},{"n":7,"t":"number"},{"n":4,"t":"decision-problem"},{"n":2,"t":"permutations"},{"n":3,"t":"sequence"},{"n":4,"t":"integer"}],"fastest-algorithm":[{"n":3,"t":"code-challenge"},{"n":5,"t":"math"},{"n":2,"t":"code-golf"}],"fastest-code":[{"n":8,"t":"code-challenge"},{"n":17,"t":"math"},{"n":3,"t":"optimization"},{"n":7,"t":"primes"},{"n":8,"t":"sequence"},{"n":12,"t":"combinatorics"},{"n":4,"t":"number-theory"},{"n":2,"t":"puzzle-solver"},{"n":2,"t":"grid"},{"n":2,"t":"permutations"},{"n":4,"t":"number"},{"n":2,"t":"geometry"},{"n":3,"t":"integer"},{"n":5,"t":"string"},{"n":2,"t":"matrix"}],"fewest-operations":[{"n":2,"t":"number-theory"},{"n":4,"t":"golf-cpu"},{"n":2,"t":"math"},{"n":2,"t":"optimization"}],"fibonacci":[{"n":70,"t":"code-golf"},{"n":17,"t":"number"},{"n":33,"t":"sequence"},{"n":18,"t":"math"},{"n":3,"t":"primes"},{"n":2,"t":"integer-partitions"},{"n":2,"t":"string"},{"n":3,"t":"restricted-source"},{"n":2,"t":"quine"},{"n":2,"t":"code-challenge"},{"n":2,"t":"ascii-art"},{"n":2,"t":"random"},{"n":3,"t":"kolmogorov-complexity"},{"n":2,"t":"base-conversion"},{"n":2,"t":"subsequence"},{"n":6,"t":"number-theory"},{"n":3,"t":"arithmetic"},{"n":2,"t":"division"},{"n":3,"t":"decision-problem"}],"file-system":[{"n":23,"t":"code-golf"},{"n":7,"t":"string"},{"n":3,"t":"random"}],"fizzbuzz":[{"n":3,"t":"code-golf"}],"floating-point":[{"n":8,"t":"code-golf"},{"n":3,"t":"math"},{"n":2,"t":"base-conversion"}],"fractal":[{"n":50,"t":"code-golf"},{"n":21,"t":"ascii-art"},{"n":5,"t":"kolmogorov-complexity"},{"n":19,"t":"graphical-output"},{"n":7,"t":"math"},{"n":2,"t":"random"},{"n":2,"t":"popularity-contest"},{"n":4,"t":"image-processing"},{"n":3,"t":"string"},{"n":3,"t":"number"},{"n":3,"t":"sequence"},{"n":2,"t":"geometry"},{"n":3,"t":"recursion"}],"function":[{"n":29,"t":"code-golf"},{"n":9,"t":"math"},{"n":2,"t":"number"},{"n":2,"t":"popularity-contest"},{"n":2,"t":"array-manipulation"},{"n":2,"t":"recursion"},{"n":5,"t":"functional-programming"},{"n":2,"t":"sequence"}],"functional-programming":[{"n":15,"t":"code-golf"},{"n":2,"t":"haskell"},{"n":5,"t":"function"},{"n":2,"t":"tips"},{"n":3,"t":"math"},{"n":2,"t":"integer"},{"n":2,"t":"array-manipulation"}],"game":[{"n":145,"t":"code-golf"},{"n":3,"t":"puzzle-solver"},{"n":3,"t":"sudoku"},{"n":18,"t":"code-challenge"},{"n":23,"t":"king-of-the-hill"},{"n":2,"t":"popularity-contest"},{"n":4,"t":"graph-theory"},{"n":13,"t":"board-game"},{"n":3,"t":"go"},{"n":10,"t":"number"},{"n":4,"t":"graphical-output"},{"n":4,"t":"cellular-automata"},{"n":4,"t":"game-of-life"},{"n":2,"t":"tetris"},{"n":5,"t":"minesweeper"},{"n":3,"t":"sliding-puzzle"},{"n":2,"t":"hexagonal-grid"},{"n":8,"t":"javascript"},{"n":3,"t":"ai-player"},{"n":2,"t":"maze"},{"n":19,"t":"grid"},{"n":2,"t":"optimization"},{"n":14,"t":"string"},{"n":5,"t":"array-manipulation"},{"n":5,"t":"path-finding"},{"n":2,"t":"probability-theory"},{"n":3,"t":"tic-tac-toe"},{"n":4,"t":"combinatorics"},{"n":7,"t":"card-games"},{"n":2,"t":"geometry"},{"n":4,"t":"kolmogorov-complexity"},{"n":14,"t":"random"},{"n":3,"t":"stack"},{"n":2,"t":"permutations"},{"n":7,"t":"arithmetic"},{"n":4,"t":"sequence"},{"n":2,"t":"binary"},{"n":2,"t":"counting"},{"n":14,"t":"decision-problem"},{"n":4,"t":"ascii-art"},{"n":6,"t":"math"},{"n":2,"t":"integer"},{"n":2,"t":"compression"},{"n":5,"t":"python"},{"n":2,"t":"binary-matrix"},{"n":3,"t":"atomic-code-golf"}],"game-of-life":[{"n":15,"t":"code-golf"},{"n":5,"t":"graphical-output"},{"n":10,"t":"cellular-automata"},{"n":5,"t":"code-challenge"},{"n":4,"t":"game"},{"n":2,"t":"image-processing"},{"n":2,"t":"parsing"},{"n":5,"t":"grid"},{"n":2,"t":"king-of-the-hill"}],"generation":[{"n":22,"t":"code-golf"},{"n":2,"t":"code-generation"},{"n":5,"t":"random"},{"n":2,"t":"natural-language"},{"n":2,"t":"number"},{"n":2,"t":"grid"},{"n":3,"t":"popularity-contest"},{"n":3,"t":"array-manipulation"},{"n":2,"t":"integer"},{"n":2,"t":"data-structures"},{"n":4,"t":"string"},{"n":2,"t":"parsing"},{"n":2,"t":"matrix"}],"geometry":[{"n":208,"t":"code-golf"},{"n":67,"t":"math"},{"n":13,"t":"decision-problem"},{"n":10,"t":"trigonometry"},{"n":34,"t":"graphical-output"},{"n":3,"t":"popularity-contest"},{"n":25,"t":"ascii-art"},{"n":14,"t":"kolmogorov-complexity"},{"n":11,"t":"sequence"},{"n":11,"t":"code-challenge"},{"n":5,"t":"tiling"},{"n":4,"t":"path-finding"},{"n":4,"t":"image-processing"},{"n":28,"t":"grid"},{"n":3,"t":"packing"},{"n":4,"t":"counting"},{"n":6,"t":"random"},{"n":2,"t":"game"},{"n":6,"t":"integer"},{"n":2,"t":"fastest-code"},{"n":8,"t":"arithmetic"},{"n":4,"t":"set-partitions"},{"n":6,"t":"array-manipulation"},{"n":3,"t":"permutations"},{"n":5,"t":"abstract-algebra"},{"n":8,"t":"number"},{"n":11,"t":"string"},{"n":2,"t":"number-theory"},{"n":3,"t":"graph-theory"},{"n":4,"t":"3d"},{"n":2,"t":"fractal"},{"n":4,"t":"hexagonal-grid"},{"n":14,"t":"combinatorics"},{"n":3,"t":"polyomino"}],"go":[{"n":4,"t":"code-golf"},{"n":3,"t":"game"},{"n":3,"t":"board-game"}],"golf-cpu":[{"n":2,"t":"number-theory"},{"n":4,"t":"fewest-operations"}],"golfing-language":[{"n":2,"t":"tips"}],"golfscript":[{"n":3,"t":"code-golf"},{"n":5,"t":"tips"}],"grammars":[{"n":3,"t":"code-golf"}],"graph-theory":[{"n":94,"t":"code-golf"},{"n":9,"t":"path-finding"},{"n":6,"t":"ascii-art"},{"n":3,"t":"graphical-output"},{"n":4,"t":"game"},{"n":10,"t":"code-challenge"},{"n":6,"t":"optimization"},{"n":10,"t":"grid"},{"n":16,"t":"decision-problem"},{"n":2,"t":"popularity-contest"},{"n":6,"t":"maze"},{"n":8,"t":"combinatorics"},{"n":3,"t":"array-manipulation"},{"n":10,"t":"math"},{"n":5,"t":"sequence"},{"n":3,"t":"atomic-code-golf"},{"n":3,"t":"geometry"},{"n":2,"t":"chess"},{"n":2,"t":"binary-tree"},{"n":2,"t":"data-structures"},{"n":2,"t":"matrix"},{"n":2,"t":"binary"},{"n":2,"t":"binary-matrix"},{"n":2,"t":"random"},{"n":2,"t":"integer"},{"n":2,"t":"string"}],"graphical-output":[{"n":180,"t":"code-golf"},{"n":18,"t":"ascii-art"},{"n":3,"t":"graph-theory"},{"n":19,"t":"fractal"},{"n":2,"t":"complex-numbers"},{"n":4,"t":"cellular-automata"},{"n":5,"t":"game-of-life"},{"n":14,"t":"code-challenge"},{"n":36,"t":"popularity-contest"},{"n":3,"t":"string"},{"n":34,"t":"geometry"},{"n":4,"t":"game"},{"n":3,"t":"hello-world"},{"n":27,"t":"kolmogorov-complexity"},{"n":13,"t":"animation"},{"n":8,"t":"color"},{"n":2,"t":"quine"},{"n":44,"t":"image-processing"},{"n":15,"t":"math"},{"n":2,"t":"combinatorics"},{"n":4,"t":"trigonometry"},{"n":4,"t":"tiling"},{"n":8,"t":"random"},{"n":2,"t":"3d"},{"n":6,"t":"number"},{"n":4,"t":"path-finding"},{"n":3,"t":"sequence"},{"n":3,"t":"grid"},{"n":2,"t":"hexagonal-grid"},{"n":3,"t":"primes"},{"n":2,"t":"compression"},{"n":2,"t":"typography"},{"n":2,"t":"knot-theory"},{"n":3,"t":"recursion"},{"n":3,"t":"integer"}],"grid":[{"n":197,"t":"code-golf"},{"n":4,"t":"simulation"},{"n":8,"t":"number"},{"n":2,"t":"generation"},{"n":19,"t":"game"},{"n":10,"t":"graph-theory"},{"n":4,"t":"minesweeper"},{"n":5,"t":"random"},{"n":5,"t":"array-manipulation"},{"n":4,"t":"hexagonal-grid"},{"n":28,"t":"geometry"},{"n":8,"t":"king-of-the-hill"},{"n":20,"t":"path-finding"},{"n":8,"t":"puzzle-solver"},{"n":29,"t":"string"},{"n":2,"t":"fastest-code"},{"n":3,"t":"permutations"},{"n":9,"t":"code-challenge"},{"n":23,"t":"decision-problem"},{"n":8,"t":"maze"},{"n":35,"t":"ascii-art"},{"n":6,"t":"javascript"},{"n":7,"t":"tiling"},{"n":10,"t":"counting"},{"n":16,"t":"combinatorics"},{"n":6,"t":"sequence"},{"n":2,"t":"crossword"},{"n":3,"t":"graphical-output"},{"n":4,"t":"optimization"},{"n":3,"t":"printable-ascii"},{"n":6,"t":"set-partitions"},{"n":6,"t":"arithmetic"},{"n":9,"t":"math"},{"n":5,"t":"kolmogorov-complexity"},{"n":5,"t":"board-game"},{"n":2,"t":"restricted-time"},{"n":2,"t":"word-search"},{"n":2,"t":"primes"},{"n":2,"t":"cellular-automata"},{"n":5,"t":"game-of-life"},{"n":5,"t":"chess"},{"n":2,"t":"integer"},{"n":3,"t":"binary-matrix"},{"n":2,"t":"sudoku"},{"n":2,"t":"polyomino"}],"halting-problem":[{"n":4,"t":"code-golf"},{"n":3,"t":"interpreter"},{"n":2,"t":"decision-problem"}],"hardware":[{"n":3,"t":"code-golf"},{"n":2,"t":"keyboard"}],"hashing":[{"n":15,"t":"code-golf"},{"n":2,"t":"restricted-source"},{"n":2,"t":"cryptography"},{"n":2,"t":"cops-and-robbers"},{"n":2,"t":"code-challenge"},{"n":2,"t":"string"}],"haskell":[{"n":6,"t":"code-golf"},{"n":4,"t":"tips"},{"n":2,"t":"functional-programming"},{"n":2,"t":"string"}],"hello-world":[{"n":30,"t":"code-golf"},{"n":5,"t":"obfuscation"},{"n":14,"t":"restricted-source"},{"n":3,"t":"ascii-art"},{"n":4,"t":"kolmogorov-complexity"},{"n":4,"t":"printable-ascii"},{"n":3,"t":"code-bowling"},{"n":11,"t":"popularity-contest"},{"n":3,"t":"polyglot"},{"n":9,"t":"code-challenge"},{"n":6,"t":"source-layout"},{"n":2,"t":"radiation-hardening"},{"n":3,"t":"graphical-output"},{"n":7,"t":"string"},{"n":2,"t":"answer-chaining"},{"n":3,"t":"cops-and-robbers"},{"n":4,"t":"quine"}],"hexadecimal":[{"n":23,"t":"code-golf"},{"n":3,"t":"conversion"},{"n":2,"t":"integer"},{"n":3,"t":"number"},{"n":6,"t":"base-conversion"},{"n":3,"t":"math"},{"n":7,"t":"string"},{"n":3,"t":"kolmogorov-complexity"},{"n":3,"t":"color"}],"hexagonal-grid":[{"n":43,"t":"code-golf"},{"n":2,"t":"game"},{"n":4,"t":"board-game"},{"n":19,"t":"ascii-art"},{"n":4,"t":"grid"},{"n":5,"t":"kolmogorov-complexity"},{"n":3,"t":"tiling"},{"n":3,"t":"path-finding"},{"n":2,"t":"king-of-the-hill"},{"n":2,"t":"cops-and-robbers"},{"n":2,"t":"java"},{"n":2,"t":"graphical-output"},{"n":2,"t":"string"},{"n":3,"t":"decision-problem"},{"n":4,"t":"geometry"},{"n":3,"t":"sequence"},{"n":2,"t":"combinatorics"}],"image-processing":[{"n":14,"t":"code-challenge"},{"n":3,"t":"compression"},{"n":52,"t":"code-golf"},{"n":20,"t":"popularity-contest"},{"n":4,"t":"ascii-art"},{"n":44,"t":"graphical-output"},{"n":5,"t":"color"},{"n":2,"t":"game-of-life"},{"n":4,"t":"geometry"},{"n":2,"t":"kolmogorov-complexity"},{"n":4,"t":"fractal"},{"n":2,"t":"path-finding"},{"n":4,"t":"test-battery"}],"integer":[{"n":271,"t":"code-golf"},{"n":4,"t":"restricted-source"},{"n":18,"t":"decision-problem"},{"n":2,"t":"palindrome"},{"n":3,"t":"conversion"},{"n":2,"t":"hexadecimal"},{"n":9,"t":"code-challenge"},{"n":6,"t":"geometry"},{"n":3,"t":"fastest-code"},{"n":6,"t":"bitwise"},{"n":91,"t":"number"},{"n":30,"t":"array-manipulation"},{"n":7,"t":"sorting"},{"n":10,"t":"matrix"},{"n":58,"t":"math"},{"n":63,"t":"sequence"},{"n":4,"t":"polynomials"},{"n":18,"t":"string"},{"n":40,"t":"arithmetic"},{"n":8,"t":"kolmogorov-complexity"},{"n":6,"t":"division"},{"n":5,"t":"source-layout"},{"n":4,"t":"permutations"},{"n":22,"t":"number-theory"},{"n":12,"t":"ascii-art"},{"n":11,"t":"binary"},{"n":14,"t":"primes"},{"n":10,"t":"base-conversion"},{"n":2,"t":"natural-language"},{"n":4,"t":"factoring"},{"n":2,"t":"generation"},{"n":4,"t":"expression-building"},{"n":4,"t":"random"},{"n":2,"t":"grid"},{"n":3,"t":"factorial"},{"n":2,"t":"game"},{"n":2,"t":"integer-partitions"},{"n":3,"t":"parsing"},{"n":3,"t":"subsequence"},{"n":2,"t":"substitution"},{"n":2,"t":"probability-theory"},{"n":2,"t":"statistics"},{"n":2,"t":"functional-programming"},{"n":4,"t":"combinatorics"},{"n":3,"t":"graphical-output"},{"n":2,"t":"graph-theory"},{"n":2,"t":"chess"},{"n":3,"t":"rational-numbers"},{"n":2,"t":"cops-and-robbers"},{"n":2,"t":"linear-algebra"}],"integer-partitions":[{"n":26,"t":"code-golf"},{"n":2,"t":"fibonacci"},{"n":10,"t":"number-theory"},{"n":5,"t":"number"},{"n":8,"t":"combinatorics"},{"n":2,"t":"random"},{"n":3,"t":"sequence"},{"n":12,"t":"math"},{"n":3,"t":"arithmetic"},{"n":2,"t":"permutations"},{"n":2,"t":"integer"}],"interactive":[{"n":16,"t":"code-golf"},{"n":3,"t":"date"},{"n":2,"t":"string"},{"n":2,"t":"ascii-art"}],"internet":[{"n":45,"t":"code-golf"},{"n":2,"t":"random"},{"n":3,"t":"code-challenge"},{"n":2,"t":"quine"},{"n":9,"t":"parsing"},{"n":10,"t":"stack-exchange-api"},{"n":3,"t":"string"},{"n":2,"t":"search"},{"n":2,"t":"decision-problem"}],"interpreter":[{"n":67,"t":"code-golf"},{"n":2,"t":"brainfuck"},{"n":2,"t":"regular-expression"},{"n":9,"t":"stack"},{"n":2,"t":"code-challenge"},{"n":2,"t":"quine"},{"n":5,"t":"math"},{"n":4,"t":"popularity-contest"},{"n":4,"t":"parsing"},{"n":6,"t":"string"},{"n":3,"t":"lisp"},{"n":3,"t":"arithmetic"},{"n":2,"t":"recursion"},{"n":3,"t":"halting-problem"},{"n":2,"t":"decision-problem"},{"n":2,"t":"language-design"}],"java":[{"n":3,"t":"code-golf"},{"n":2,"t":"tips"},{"n":21,"t":"king-of-the-hill"},{"n":2,"t":"card-games"},{"n":2,"t":"cops-and-robbers"},{"n":2,"t":"hexagonal-grid"}],"javascript":[{"n":13,"t":"code-golf"},{"n":2,"t":"popularity-contest"},{"n":6,"t":"tips"},{"n":4,"t":"code-challenge"},{"n":5,"t":"restricted-source"},{"n":8,"t":"game"},{"n":2,"t":"ai-player"},{"n":2,"t":"sliding-puzzle"},{"n":17,"t":"king-of-the-hill"},{"n":6,"t":"grid"},{"n":2,"t":"kolmogorov-complexity"}],"jelly":[{"n":4,"t":"code-golf"},{"n":3,"t":"array-manipulation"}],"json":[{"n":4,"t":"code-golf"}],"keyboard":[{"n":5,"t":"code-challenge"},{"n":32,"t":"code-golf"},{"n":13,"t":"string"},{"n":2,"t":"hardware"}],"king-of-the-hill":[{"n":3,"t":"code-challenge"},{"n":23,"t":"game"},{"n":5,"t":"board-game"},{"n":2,"t":"tic-tac-toe"},{"n":21,"t":"java"},{"n":3,"t":"chess"},{"n":3,"t":"path-finding"},{"n":8,"t":"grid"},{"n":17,"t":"javascript"},{"n":5,"t":"card-games"},{"n":2,"t":"cops-and-robbers"},{"n":2,"t":"hexagonal-grid"},{"n":2,"t":"c++"},{"n":2,"t":"game-of-life"},{"n":2,"t":"random"},{"n":13,"t":"python"}],"knot-theory":[{"n":7,"t":"code-golf"},{"n":3,"t":"decision-problem"},{"n":2,"t":"graphical-output"}],"kolmogorov-complexity":[{"n":2,"t":"popularity-contest"},{"n":432,"t":"code-golf"},{"n":124,"t":"ascii-art"},{"n":5,"t":"fractal"},{"n":3,"t":"restricted-time"},{"n":4,"t":"pi"},{"n":16,"t":"code-challenge"},{"n":22,"t":"alphabet"},{"n":2,"t":"subsequence"},{"n":4,"t":"hello-world"},{"n":3,"t":"brainfuck"},{"n":6,"t":"metagolf"},{"n":6,"t":"primes"},{"n":11,"t":"math"},{"n":24,"t":"number"},{"n":98,"t":"string"},{"n":27,"t":"graphical-output"},{"n":14,"t":"geometry"},{"n":29,"t":"restricted-source"},{"n":16,"t":"date"},{"n":11,"t":"animation"},{"n":2,"t":"tiling"},{"n":8,"t":"chemistry"},{"n":7,"t":"arithmetic"},{"n":2,"t":"image-processing"},{"n":2,"t":"new-years"},{"n":4,"t":"audio"},{"n":3,"t":"morse"},{"n":4,"t":"source-layout"},{"n":6,"t":"code-generation"},{"n":2,"t":"answer-chaining"},{"n":13,"t":"sequence"},{"n":5,"t":"hexagonal-grid"},{"n":5,"t":"board-game"},{"n":4,"t":"game"},{"n":2,"t":"scrabble"},{"n":3,"t":"chess"},{"n":2,"t":"javascript"},{"n":3,"t":"fibonacci"},{"n":5,"t":"unicode"},{"n":2,"t":"tips"},{"n":6,"t":"compression"},{"n":7,"t":"cops-and-robbers"},{"n":5,"t":"grid"},{"n":4,"t":"music"},{"n":5,"t":"natural-language"},{"n":2,"t":"card-games"},{"n":3,"t":"number-theory"},{"n":2,"t":"cryptography"},{"n":8,"t":"integer"},{"n":2,"t":"binary"},{"n":3,"t":"polyglot"},{"n":3,"t":"hexadecimal"},{"n":2,"t":"radiation-hardening"},{"n":5,"t":"random"},{"n":2,"t":"combinatorics"},{"n":3,"t":"obfuscation"},{"n":2,"t":"color"},{"n":3,"t":"matrix"}],"lambda-calculus":[{"n":4,"t":"code-golf"}],"language-design":[{"n":4,"t":"popularity-contest"},{"n":2,"t":"code-golf"},{"n":2,"t":"interpreter"}],"linear-algebra":[{"n":33,"t":"code-golf"},{"n":23,"t":"math"},{"n":26,"t":"matrix"},{"n":2,"t":"complex-numbers"},{"n":3,"t":"abstract-algebra"},{"n":3,"t":"polynomials"},{"n":2,"t":"binary-matrix"},{"n":2,"t":"decision-problem"},{"n":2,"t":"integer"}],"lisp":[{"n":7,"t":"code-golf"},{"n":2,"t":"tips"},{"n":3,"t":"interpreter"}],"logic":[{"n":14,"t":"code-golf"},{"n":2,"t":"natural-language"},{"n":6,"t":"math"},{"n":2,"t":"binary"},{"n":3,"t":"logic-gates"},{"n":3,"t":"array-manipulation"},{"n":3,"t":"proof-golf"},{"n":2,"t":"string"}],"logic-gates":[{"n":6,"t":"atomic-code-golf"},{"n":2,"t":"code-challenge"},{"n":2,"t":"optimization"},{"n":11,"t":"code-golf"},{"n":2,"t":"ascii-art"},{"n":2,"t":"binary"},{"n":3,"t":"logic"}],"lua":[{"n":2,"t":"code-golf"}],"machine-code":[{"n":3,"t":"code-golf"},{"n":3,"t":"x86-family"},{"n":2,"t":"assembly"}],"manufactoria":[{"n":2,"t":"code-golf"}],"markov-chain":[{"n":2,"t":"code-golf"}],"math":[{"n":39,"t":"code-challenge"},{"n":8,"t":"random"},{"n":928,"t":"code-golf"},{"n":67,"t":"geometry"},{"n":116,"t":"number-theory"},{"n":192,"t":"number"},{"n":136,"t":"arithmetic"},{"n":13,"t":"factorial"},{"n":9,"t":"restricted-time"},{"n":9,"t":"function"},{"n":3,"t":"roman-numerals"},{"n":26,"t":"abstract-algebra"},{"n":35,"t":"polynomials"},{"n":17,"t":"fastest-code"},{"n":3,"t":"cryptography"},{"n":51,"t":"combinatorics"},{"n":17,"t":"permutations"},{"n":29,"t":"rational-numbers"},{"n":5,"t":"repeated-transformation"},{"n":65,"t":"primes"},{"n":18,"t":"fibonacci"},{"n":50,"t":"decision-problem"},{"n":26,"t":"ascii-art"},{"n":8,"t":"set-theory"},{"n":5,"t":"fastest-algorithm"},{"n":13,"t":"trigonometry"},{"n":17,"t":"restricted-source"},{"n":11,"t":"pi"},{"n":7,"t":"approximation"},{"n":5,"t":"interpreter"},{"n":2,"t":"rosetta-stone"},{"n":143,"t":"sequence"},{"n":42,"t":"array-manipulation"},{"n":11,"t":"kolmogorov-complexity"},{"n":7,"t":"fractal"},{"n":4,"t":"busy-beaver"},{"n":9,"t":"division"},{"n":48,"t":"matrix"},{"n":5,"t":"expression-building"},{"n":9,"t":"complex-numbers"},{"n":11,"t":"optimization"},{"n":2,"t":"binary-tree"},{"n":4,"t":"multiple-holes"},{"n":11,"t":"popularity-contest"},{"n":3,"t":"puzzle-solver"},{"n":15,"t":"graphical-output"},{"n":2,"t":"animation"},{"n":5,"t":"underhanded"},{"n":14,"t":"calculus"},{"n":2,"t":"quine"},{"n":9,"t":"atomic-code-golf"},{"n":3,"t":"date"},{"n":28,"t":"string"},{"n":3,"t":"chemistry"},{"n":7,"t":"factoring"},{"n":6,"t":"counting"},{"n":7,"t":"bitwise"},{"n":2,"t":"3d"},{"n":25,"t":"base-conversion"},{"n":4,"t":"probability-theory"},{"n":23,"t":"linear-algebra"},{"n":6,"t":"answer-chaining"},{"n":2,"t":"code-generation"},{"n":2,"t":"binary-matrix"},{"n":10,"t":"graph-theory"},{"n":12,"t":"integer-partitions"},{"n":3,"t":"recursion"},{"n":2,"t":"fewest-operations"},{"n":6,"t":"polyglot"},{"n":5,"t":"sorting"},{"n":9,"t":"grid"},{"n":9,"t":"statistics"},{"n":8,"t":"parsing"},{"n":3,"t":"optimized-output"},{"n":6,"t":"logic"},{"n":4,"t":"physics"},{"n":9,"t":"binary"},{"n":2,"t":"stack"},{"n":3,"t":"hexadecimal"},{"n":8,"t":"topology"},{"n":3,"t":"subsequence"},{"n":4,"t":"set-partitions"},{"n":58,"t":"integer"},{"n":3,"t":"checksum"},{"n":3,"t":"metagolf"},{"n":6,"t":"game"},{"n":2,"t":"color"},{"n":3,"t":"source-layout"},{"n":3,"t":"palindrome"},{"n":2,"t":"natural-language"},{"n":2,"t":"algorithm"},{"n":2,"t":"proof-golf"},{"n":3,"t":"functional-programming"},{"n":2,"t":"electrical-engineering"},{"n":3,"t":"floating-point"}],"matrix":[{"n":164,"t":"code-golf"},{"n":42,"t":"array-manipulation"},{"n":48,"t":"math"},{"n":26,"t":"linear-algebra"},{"n":3,"t":"complex-numbers"},{"n":3,"t":"abstract-algebra"},{"n":2,"t":"polynomials"},{"n":6,"t":"binary-matrix"},{"n":7,"t":"arithmetic"},{"n":20,"t":"decision-problem"},{"n":3,"t":"subsequence"},{"n":4,"t":"sorting"},{"n":10,"t":"integer"},{"n":18,"t":"number"},{"n":2,"t":"fastest-code"},{"n":2,"t":"regular-expression"},{"n":2,"t":"cops-and-robbers"},{"n":2,"t":"parsing"},{"n":2,"t":"code-challenge"},{"n":3,"t":"source-layout"},{"n":6,"t":"string"},{"n":6,"t":"ascii-art"},{"n":2,"t":"graph-theory"},{"n":2,"t":"optimization"},{"n":2,"t":"tiling"},{"n":3,"t":"kolmogorov-complexity"},{"n":2,"t":"classification"},{"n":2,"t":"cellular-automata"},{"n":2,"t":"generation"}],"maze":[{"n":4,"t":"code-challenge"},{"n":7,"t":"ascii-art"},{"n":32,"t":"code-golf"},{"n":12,"t":"path-finding"},{"n":2,"t":"game"},{"n":3,"t":"decision-problem"},{"n":6,"t":"graph-theory"},{"n":8,"t":"grid"},{"n":2,"t":"optimization"},{"n":2,"t":"array-manipulation"}],"metagolf":[{"n":7,"t":"code-golf"},{"n":2,"t":"popularity-contest"},{"n":10,"t":"code-challenge"},{"n":6,"t":"kolmogorov-complexity"},{"n":4,"t":"brainfuck"},{"n":3,"t":"code-generation"},{"n":2,"t":"regular-expression"},{"n":5,"t":"stack"},{"n":2,"t":"restricted-source"},{"n":3,"t":"number"},{"n":3,"t":"math"},{"n":5,"t":"test-battery"},{"n":3,"t":"brain-flak"}],"minesweeper":[{"n":11,"t":"code-golf"},{"n":5,"t":"game"},{"n":4,"t":"grid"},{"n":2,"t":"random"}],"morse":[{"n":9,"t":"code-golf"},{"n":3,"t":"kolmogorov-complexity"}],"multi-threading":[{"n":2,"t":"code-golf"}],"multiple-holes":[{"n":5,"t":"code-challenge"},{"n":4,"t":"math"},{"n":2,"t":"ascii-art"},{"n":5,"t":"string"},{"n":12,"t":"code-golf"},{"n":5,"t":"number"},{"n":2,"t":"sequence"},{"n":4,"t":"restricted-source"},{"n":3,"t":"source-layout"}],"music":[{"n":38,"t":"code-golf"},{"n":7,"t":"audio"},{"n":8,"t":"ascii-art"},{"n":5,"t":"popularity-contest"},{"n":4,"t":"kolmogorov-complexity"}],"natural-language":[{"n":53,"t":"code-golf"},{"n":2,"t":"generation"},{"n":9,"t":"code-challenge"},{"n":30,"t":"string"},{"n":4,"t":"parsing"},{"n":2,"t":"logic"},{"n":4,"t":"classification"},{"n":3,"t":"popularity-contest"},{"n":2,"t":"conversion"},{"n":2,"t":"date"},{"n":5,"t":"decision-problem"},{"n":3,"t":"number"},{"n":5,"t":"kolmogorov-complexity"},{"n":2,"t":"counting"},{"n":2,"t":"polyglot"},{"n":3,"t":"sorting"},{"n":2,"t":"integer"},{"n":2,"t":"math"},{"n":2,"t":"test-battery"}],"networking":[{"n":7,"t":"code-golf"},{"n":2,"t":"string"}],"neural-networks":[{"n":2,"t":"code-challenge"},{"n":2,"t":"optimization"}],"new-years":[{"n":13,"t":"code-golf"},{"n":4,"t":"restricted-source"},{"n":2,"t":"kolmogorov-complexity"},{"n":2,"t":"number"},{"n":2,"t":"quine"}],"number":[{"n":804,"t":"code-golf"},{"n":184,"t":"sequence"},{"n":17,"t":"fibonacci"},{"n":192,"t":"math"},{"n":81,"t":"number-theory"},{"n":25,"t":"binary"},{"n":48,"t":"primes"},{"n":75,"t":"decision-problem"},{"n":62,"t":"string"},{"n":14,"t":"counting"},{"n":14,"t":"random"},{"n":10,"t":"game"},{"n":26,"t":"ascii-art"},{"n":24,"t":"kolmogorov-complexity"},{"n":37,"t":"base-conversion"},{"n":2,"t":"function"},{"n":14,"t":"sorting"},{"n":5,"t":"stack"},{"n":2,"t":"generation"},{"n":8,"t":"grid"},{"n":22,"t":"code-challenge"},{"n":12,"t":"restricted-source"},{"n":4,"t":"busy-beaver"},{"n":3,"t":"popularity-contest"},{"n":20,"t":"combinatorics"},{"n":13,"t":"rational-numbers"},{"n":11,"t":"division"},{"n":2,"t":"tips"},{"n":2,"t":"chemistry"},{"n":105,"t":"arithmetic"},{"n":6,"t":"graphical-output"},{"n":3,"t":"roman-numerals"},{"n":66,"t":"array-manipulation"},{"n":2,"t":"new-years"},{"n":5,"t":"multiple-holes"},{"n":5,"t":"integer-partitions"},{"n":11,"t":"permutations"},{"n":2,"t":"restricted-complexity"},{"n":5,"t":"set-partitions"},{"n":5,"t":"probability-theory"},{"n":5,"t":"expression-building"},{"n":3,"t":"answer-chaining"},{"n":3,"t":"metagolf"},{"n":4,"t":"fastest-code"},{"n":6,"t":"bitwise"},{"n":3,"t":"restricted-time"},{"n":9,"t":"palindrome"},{"n":5,"t":"balanced-string"},{"n":2,"t":"compression"},{"n":2,"t":"code-generation"},{"n":91,"t":"integer"},{"n":4,"t":"printable-ascii"},{"n":7,"t":"parsing"},{"n":6,"t":"conversion"},{"n":10,"t":"date"},{"n":3,"t":"polyglot"},{"n":3,"t":"fractal"},{"n":3,"t":"hexadecimal"},{"n":5,"t":"abstract-algebra"},{"n":7,"t":"factoring"},{"n":3,"t":"pi"},{"n":6,"t":"optimization"},{"n":6,"t":"subsequence"},{"n":8,"t":"geometry"},{"n":3,"t":"natural-language"},{"n":5,"t":"classification"},{"n":8,"t":"cops-and-robbers"},{"n":3,"t":"chess"},{"n":7,"t":"source-layout"},{"n":5,"t":"polynomials"},{"n":2,"t":"approximation"},{"n":3,"t":"alphabet"},{"n":18,"t":"matrix"},{"n":3,"t":"set-theory"},{"n":3,"t":"recursion"},{"n":3,"t":"factorial"}],"number-theory":[{"n":298,"t":"code-golf"},{"n":81,"t":"sequence"},{"n":4,"t":"restricted-time"},{"n":116,"t":"math"},{"n":81,"t":"number"},{"n":3,"t":"factorial"},{"n":60,"t":"primes"},{"n":8,"t":"factoring"},{"n":34,"t":"decision-problem"},{"n":4,"t":"binary"},{"n":8,"t":"code-challenge"},{"n":3,"t":"atomic-code-golf"},{"n":41,"t":"arithmetic"},{"n":4,"t":"fastest-code"},{"n":12,"t":"base-conversion"},{"n":14,"t":"combinatorics"},{"n":10,"t":"integer-partitions"},{"n":2,"t":"restricted-complexity"},{"n":2,"t":"fewest-operations"},{"n":2,"t":"golf-cpu"},{"n":2,"t":"path-finding"},{"n":3,"t":"permutations"},{"n":4,"t":"set-partitions"},{"n":12,"t":"division"},{"n":2,"t":"parsing"},{"n":3,"t":"ascii-art"},{"n":2,"t":"string"},{"n":2,"t":"complex-numbers"},{"n":2,"t":"geometry"},{"n":6,"t":"abstract-algebra"},{"n":4,"t":"array-manipulation"},{"n":6,"t":"polynomials"},{"n":6,"t":"fibonacci"},{"n":3,"t":"kolmogorov-complexity"},{"n":2,"t":"subsequence"},{"n":22,"t":"integer"},{"n":3,"t":"palindrome"},{"n":2,"t":"source-layout"},{"n":3,"t":"rational-numbers"}],"obfuscation":[{"n":6,"t":"popularity-contest"},{"n":10,"t":"code-golf"},{"n":2,"t":"restricted-source"},{"n":5,"t":"hello-world"},{"n":3,"t":"code-challenge"},{"n":12,"t":"cops-and-robbers"},{"n":3,"t":"kolmogorov-complexity"},{"n":2,"t":"code-generation"}],"octave":[{"n":3,"t":"code-golf"},{"n":3,"t":"tips"}],"optimization":[{"n":3,"t":"fastest-code"},{"n":31,"t":"code-challenge"},{"n":3,"t":"stack"},{"n":2,"t":"puzzle-solver"},{"n":11,"t":"math"},{"n":2,"t":"logic-gates"},{"n":2,"t":"game"},{"n":6,"t":"graph-theory"},{"n":27,"t":"code-golf"},{"n":2,"t":"test-battery"},{"n":4,"t":"grid"},{"n":2,"t":"maze"},{"n":3,"t":"ascii-art"},{"n":2,"t":"fewest-operations"},{"n":2,"t":"path-finding"},{"n":6,"t":"number"},{"n":7,"t":"array-manipulation"},{"n":2,"t":"sequence"},{"n":2,"t":"combinatorics"},{"n":3,"t":"sorting"},{"n":2,"t":"matrix"},{"n":2,"t":"neural-networks"}],"optimized-output":[{"n":6,"t":"code-golf"},{"n":5,"t":"code-challenge"},{"n":3,"t":"math"},{"n":4,"t":"string"}],"packing":[{"n":3,"t":"code-challenge"},{"n":6,"t":"code-golf"},{"n":2,"t":"ascii-art"},{"n":3,"t":"geometry"}],"palindrome":[{"n":52,"t":"code-golf"},{"n":18,"t":"string"},{"n":3,"t":"binary"},{"n":3,"t":"code-challenge"},{"n":8,"t":"decision-problem"},{"n":5,"t":"base-conversion"},{"n":7,"t":"restricted-source"},{"n":2,"t":"integer"},{"n":7,"t":"sequence"},{"n":3,"t":"polyglot"},{"n":9,"t":"number"},{"n":2,"t":"date"},{"n":3,"t":"permutations"},{"n":3,"t":"math"},{"n":3,"t":"number-theory"},{"n":2,"t":"primes"}],"pangram":[{"n":3,"t":"code-bowling"},{"n":3,"t":"restricted-source"},{"n":3,"t":"string"},{"n":2,"t":"code-golf"}],"parsing":[{"n":125,"t":"code-golf"},{"n":58,"t":"string"},{"n":3,"t":"popularity-contest"},{"n":3,"t":"syntax"},{"n":4,"t":"interpreter"},{"n":4,"t":"natural-language"},{"n":4,"t":"regular-expression"},{"n":9,"t":"internet"},{"n":6,"t":"arithmetic"},{"n":4,"t":"rational-numbers"},{"n":3,"t":"date"},{"n":4,"t":"unicode"},{"n":8,"t":"math"},{"n":7,"t":"number"},{"n":3,"t":"balanced-string"},{"n":12,"t":"ascii-art"},{"n":2,"t":"chemistry"},{"n":2,"t":"number-theory"},{"n":2,"t":"game-of-life"},{"n":2,"t":"comment"},{"n":4,"t":"code-challenge"},{"n":3,"t":"c"},{"n":3,"t":"conversion"},{"n":4,"t":"decision-problem"},{"n":2,"t":"array-manipulation"},{"n":2,"t":"code-generation"},{"n":2,"t":"base-conversion"},{"n":2,"t":"generation"},{"n":2,"t":"classification"},{"n":2,"t":"matrix"},{"n":3,"t":"integer"},{"n":3,"t":"apl"}],"path-finding":[{"n":69,"t":"code-golf"},{"n":9,"t":"graph-theory"},{"n":9,"t":"ascii-art"},{"n":12,"t":"maze"},{"n":9,"t":"code-challenge"},{"n":6,"t":"decision-problem"},{"n":4,"t":"geometry"},{"n":4,"t":"graphical-output"},{"n":2,"t":"image-processing"},{"n":3,"t":"king-of-the-hill"},{"n":20,"t":"grid"},{"n":5,"t":"game"},{"n":3,"t":"puzzle-solver"},{"n":2,"t":"board-game"},{"n":3,"t":"hexagonal-grid"},{"n":2,"t":"sequence"},{"n":2,"t":"number-theory"},{"n":2,"t":"permutations"},{"n":3,"t":"string"},{"n":2,"t":"optimization"},{"n":2,"t":"chess"},{"n":2,"t":"combinatorics"}],"pattern-matching":[{"n":5,"t":"code-golf"},{"n":3,"t":"string"},{"n":3,"t":"decision-problem"}],"permutations":[{"n":108,"t":"code-golf"},{"n":21,"t":"string"},{"n":17,"t":"math"},{"n":27,"t":"combinatorics"},{"n":9,"t":"code-challenge"},{"n":7,"t":"sorting"},{"n":2,"t":"puzzle-solver"},{"n":7,"t":"random"},{"n":12,"t":"array-manipulation"},{"n":5,"t":"source-layout"},{"n":11,"t":"number"},{"n":11,"t":"sequence"},{"n":2,"t":"fastest-code"},{"n":3,"t":"grid"},{"n":3,"t":"number-theory"},{"n":2,"t":"path-finding"},{"n":2,"t":"game"},{"n":2,"t":"restricted-time"},{"n":2,"t":"counting"},{"n":3,"t":"geometry"},{"n":4,"t":"abstract-algebra"},{"n":2,"t":"restricted-complexity"},{"n":4,"t":"decision-problem"},{"n":2,"t":"card-games"},{"n":2,"t":"binary"},{"n":2,"t":"bitwise"},{"n":3,"t":"palindrome"},{"n":3,"t":"arithmetic"},{"n":4,"t":"integer"},{"n":2,"t":"primes"},{"n":2,"t":"factoring"},{"n":2,"t":"integer-partitions"},{"n":6,"t":"quine"},{"n":6,"t":"cops-and-robbers"},{"n":2,"t":"balanced-string"}],"physics":[{"n":25,"t":"code-golf"},{"n":6,"t":"ascii-art"},{"n":3,"t":"electrical-engineering"},{"n":2,"t":"random"},{"n":4,"t":"math"},{"n":3,"t":"string"},{"n":2,"t":"decision-problem"}],"pi":[{"n":35,"t":"code-golf"},{"n":2,"t":"restricted-time"},{"n":4,"t":"kolmogorov-complexity"},{"n":11,"t":"math"},{"n":5,"t":"approximation"},{"n":3,"t":"popularity-contest"},{"n":2,"t":"underhanded"},{"n":3,"t":"random"},{"n":3,"t":"arithmetic"},{"n":2,"t":"string"},{"n":3,"t":"number"},{"n":2,"t":"date"},{"n":3,"t":"sequence"}],"polyglot":[{"n":32,"t":"code-golf"},{"n":13,"t":"quine"},{"n":24,"t":"code-challenge"},{"n":3,"t":"hello-world"},{"n":5,"t":"popularity-contest"},{"n":2,"t":"restricted-source"},{"n":2,"t":"c++"},{"n":8,"t":"sequence"},{"n":3,"t":"palindrome"},{"n":6,"t":"math"},{"n":7,"t":"string"},{"n":3,"t":"number"},{"n":9,"t":"rosetta-stone"},{"n":2,"t":"code-generation"},{"n":4,"t":"cops-and-robbers"},{"n":3,"t":"kolmogorov-complexity"},{"n":2,"t":"natural-language"},{"n":4,"t":"answer-chaining"},{"n":2,"t":"arithmetic"}],"polynomials":[{"n":43,"t":"code-golf"},{"n":35,"t":"math"},{"n":7,"t":"abstract-algebra"},{"n":2,"t":"cryptography"},{"n":2,"t":"rational-numbers"},{"n":4,"t":"calculus"},{"n":2,"t":"matrix"},{"n":3,"t":"linear-algebra"},{"n":5,"t":"sequence"},{"n":4,"t":"integer"},{"n":2,"t":"array-manipulation"},{"n":6,"t":"number-theory"},{"n":5,"t":"number"},{"n":2,"t":"equation"},{"n":2,"t":"code-challenge"}],"polyomino":[{"n":7,"t":"code-golf"},{"n":6,"t":"combinatorics"},{"n":3,"t":"code-challenge"},{"n":3,"t":"sequence"},{"n":3,"t":"geometry"},{"n":2,"t":"grid"},{"n":3,"t":"decision-problem"},{"n":2,"t":"tiling"}],"popularity-contest":[{"n":6,"t":"obfuscation"},{"n":2,"t":"kolmogorov-complexity"},{"n":10,"t":"restricted-source"},{"n":2,"t":"c++"},{"n":4,"t":"code-challenge"},{"n":2,"t":"javascript"},{"n":2,"t":"metagolf"},{"n":11,"t":"ascii-art"},{"n":2,"t":"source-layout"},{"n":2,"t":"radiation-hardening"},{"n":36,"t":"graphical-output"},{"n":3,"t":"c"},{"n":5,"t":"music"},{"n":2,"t":"game"},{"n":32,"t":"underhanded"},{"n":2,"t":"regular-expression"},{"n":2,"t":"compile-time"},{"n":11,"t":"hello-world"},{"n":2,"t":"audio"},{"n":8,"t":"code-trolling"},{"n":2,"t":"function"},{"n":11,"t":"math"},{"n":3,"t":"geometry"},{"n":6,"t":"quine"},{"n":4,"t":"interpreter"},{"n":2,"t":"stack"},{"n":20,"t":"image-processing"},{"n":2,"t":"counting"},{"n":5,"t":"animation"},{"n":2,"t":"programming-puzzle"},{"n":3,"t":"parsing"},{"n":5,"t":"polyglot"},{"n":2,"t":"color"},{"n":2,"t":"python"},{"n":3,"t":"number"},{"n":2,"t":"sequence"},{"n":3,"t":"pi"},{"n":2,"t":"code-golf"},{"n":3,"t":"generation"},{"n":3,"t":"duct-tape-coding"},{"n":2,"t":"sorting"},{"n":2,"t":"random"},{"n":4,"t":"string"},{"n":2,"t":"graph-theory"},{"n":2,"t":"fractal"},{"n":4,"t":"language-design"},{"n":2,"t":"answer-chaining"},{"n":3,"t":"natural-language"},{"n":2,"t":"cops-and-robbers"}],"primes":[{"n":190,"t":"code-golf"},{"n":65,"t":"math"},{"n":3,"t":"fibonacci"},{"n":60,"t":"number-theory"},{"n":15,"t":"factoring"},{"n":48,"t":"number"},{"n":26,"t":"decision-problem"},{"n":6,"t":"kolmogorov-complexity"},{"n":14,"t":"code-challenge"},{"n":7,"t":"fastest-code"},{"n":7,"t":"string"},{"n":7,"t":"restricted-source"},{"n":3,"t":"combinatorics"},{"n":3,"t":"cops-and-robbers"},{"n":50,"t":"sequence"},{"n":2,"t":"division"},{"n":6,"t":"binary"},{"n":8,"t":"arithmetic"},{"n":4,"t":"base-conversion"},{"n":2,"t":"bitwise"},{"n":2,"t":"abstract-algebra"},{"n":4,"t":"ascii-art"},{"n":3,"t":"graphical-output"},{"n":2,"t":"grid"},{"n":2,"t":"set-partitions"},{"n":3,"t":"array-manipulation"},{"n":4,"t":"date"},{"n":2,"t":"counting"},{"n":4,"t":"source-layout"},{"n":2,"t":"permutations"},{"n":14,"t":"integer"},{"n":2,"t":"palindrome"},{"n":2,"t":"balanced-string"}],"printable-ascii":[{"n":34,"t":"code-golf"},{"n":11,"t":"ascii-art"},{"n":4,"t":"hello-world"},{"n":11,"t":"code-challenge"},{"n":10,"t":"string"},{"n":11,"t":"restricted-source"},{"n":13,"t":"source-layout"},{"n":3,"t":"cops-and-robbers"},{"n":2,"t":"crossword"},{"n":4,"t":"answer-chaining"},{"n":3,"t":"grid"},{"n":4,"t":"number"}],"pristine-programming":[{"n":4,"t":"code-golf"},{"n":4,"t":"restricted-source"},{"n":2,"t":"code-bowling"},{"n":2,"t":"code-challenge"}],"probability-theory":[{"n":29,"t":"code-golf"},{"n":6,"t":"random"},{"n":2,"t":"code-challenge"},{"n":4,"t":"math"},{"n":2,"t":"rational-numbers"},{"n":5,"t":"number"},{"n":2,"t":"game"},{"n":4,"t":"combinatorics"},{"n":2,"t":"integer"},{"n":2,"t":"statistics"}],"programming-puzzle":[{"n":3,"t":"code-challenge"},{"n":2,"t":"c++"},{"n":5,"t":"c#"},{"n":6,"t":"code-golf"},{"n":2,"t":"popularity-contest"},{"n":2,"t":"restricted-source"}],"proof-golf":[{"n":2,"t":"atomic-code-golf"},{"n":3,"t":"logic"},{"n":2,"t":"math"}],"puzzle-solver":[{"n":40,"t":"code-golf"},{"n":3,"t":"game"},{"n":3,"t":"sudoku"},{"n":7,"t":"code-challenge"},{"n":2,"t":"sliding-puzzle"},{"n":2,"t":"optimization"},{"n":3,"t":"rubiks-cube"},{"n":3,"t":"math"},{"n":3,"t":"test-battery"},{"n":2,"t":"permutations"},{"n":8,"t":"grid"},{"n":2,"t":"fastest-code"},{"n":3,"t":"path-finding"},{"n":2,"t":"ascii-art"}],"pyth":[{"n":2,"t":"code-golf"},{"n":2,"t":"tips"}],"python":[{"n":24,"t":"code-golf"},{"n":18,"t":"tips"},{"n":4,"t":"code-challenge"},{"n":2,"t":"popularity-contest"},{"n":2,"t":"string"},{"n":2,"t":"decision-problem"},{"n":13,"t":"king-of-the-hill"},{"n":5,"t":"game"},{"n":2,"t":"test-battery"},{"n":2,"t":"restricted-source"}],"quine":[{"n":128,"t":"code-golf"},{"n":23,"t":"code-challenge"},{"n":2,"t":"rosetta-stone"},{"n":13,"t":"polyglot"},{"n":2,"t":"interpreter"},{"n":17,"t":"source-layout"},{"n":3,"t":"decision-problem"},{"n":6,"t":"popularity-contest"},{"n":15,"t":"code-generation"},{"n":2,"t":"graphical-output"},{"n":2,"t":"internet"},{"n":2,"t":"self-referential"},{"n":2,"t":"fibonacci"},{"n":2,"t":"math"},{"n":3,"t":"error-message"},{"n":2,"t":"whitespace"},{"n":10,"t":"restricted-source"},{"n":2,"t":"busy-beaver"},{"n":4,"t":"radiation-hardening"},{"n":10,"t":"string"},{"n":4,"t":"hello-world"},{"n":4,"t":"sequence"},{"n":2,"t":"regular-expression"},{"n":2,"t":"random"},{"n":3,"t":"cops-and-robbers"},{"n":6,"t":"permutations"},{"n":2,"t":"stateful"},{"n":2,"t":"new-years"},{"n":2,"t":"tips"},{"n":2,"t":"answer-chaining"}],"radiation-hardening":[{"n":2,"t":"popularity-contest"},{"n":8,"t":"source-layout"},{"n":8,"t":"code-challenge"},{"n":2,"t":"hello-world"},{"n":4,"t":"quine"},{"n":11,"t":"code-golf"},{"n":2,"t":"kolmogorov-complexity"},{"n":2,"t":"code-bowling"},{"n":2,"t":"self-referential"}],"random":[{"n":5,"t":"code-challenge"},{"n":8,"t":"math"},{"n":194,"t":"code-golf"},{"n":6,"t":"probability-theory"},{"n":10,"t":"array-manipulation"},{"n":30,"t":"ascii-art"},{"n":44,"t":"string"},{"n":14,"t":"number"},{"n":2,"t":"internet"},{"n":5,"t":"generation"},{"n":2,"t":"popularity-contest"},{"n":8,"t":"graphical-output"},{"n":2,"t":"fractal"},{"n":5,"t":"grid"},{"n":7,"t":"permutations"},{"n":6,"t":"combinatorics"},{"n":2,"t":"integer-partitions"},{"n":3,"t":"pi"},{"n":2,"t":"approximation"},{"n":6,"t":"geometry"},{"n":2,"t":"fibonacci"},{"n":3,"t":"simulation"},{"n":14,"t":"game"},{"n":2,"t":"physics"},{"n":3,"t":"arithmetic"},{"n":3,"t":"file-system"},{"n":3,"t":"classification"},{"n":2,"t":"cryptography"},{"n":2,"t":"minesweeper"},{"n":2,"t":"quine"},{"n":4,"t":"sequence"},{"n":5,"t":"kolmogorov-complexity"},{"n":6,"t":"animation"},{"n":4,"t":"integer"},{"n":2,"t":"king-of-the-hill"},{"n":2,"t":"alphabet"},{"n":2,"t":"card-games"},{"n":2,"t":"graph-theory"}],"rational-numbers":[{"n":52,"t":"code-golf"},{"n":29,"t":"math"},{"n":2,"t":"polynomials"},{"n":2,"t":"approximation"},{"n":13,"t":"number"},{"n":2,"t":"code-challenge"},{"n":6,"t":"arithmetic"},{"n":2,"t":"probability-theory"},{"n":4,"t":"parsing"},{"n":4,"t":"sequence"},{"n":2,"t":"decision-problem"},{"n":3,"t":"number-theory"},{"n":3,"t":"integer"}],"recursion":[{"n":24,"t":"code-golf"},{"n":2,"t":"function"},{"n":4,"t":"arithmetic"},{"n":2,"t":"balanced-string"},{"n":3,"t":"math"},{"n":2,"t":"interpreter"},{"n":3,"t":"graphical-output"},{"n":3,"t":"fractal"},{"n":4,"t":"sequence"},{"n":3,"t":"number"}],"regular-expression":[{"n":38,"t":"code-golf"},{"n":2,"t":"interpreter"},{"n":4,"t":"code-challenge"},{"n":2,"t":"popularity-contest"},{"n":2,"t":"metagolf"},{"n":7,"t":"string"},{"n":6,"t":"decision-problem"},{"n":3,"t":"cops-and-robbers"},{"n":3,"t":"arithmetic"},{"n":2,"t":"date"},{"n":4,"t":"parsing"},{"n":2,"t":"quine"},{"n":2,"t":"matrix"}],"repeated-transformation":[{"n":10,"t":"code-golf"},{"n":5,"t":"math"},{"n":4,"t":"arithmetic"}],"restricted-complexity":[{"n":27,"t":"code-golf"},{"n":4,"t":"string"},{"n":4,"t":"array-manipulation"},{"n":3,"t":"sorting"},{"n":2,"t":"number"},{"n":2,"t":"number-theory"},{"n":2,"t":"permutations"}],"restricted-memory":[{"n":2,"t":"code-golf"}],"restricted-source":[{"n":124,"t":"code-golf"},{"n":2,"t":"obfuscation"},{"n":10,"t":"popularity-contest"},{"n":2,"t":"c++"},{"n":14,"t":"hello-world"},{"n":47,"t":"code-challenge"},{"n":3,"t":"array-manipulation"},{"n":7,"t":"sequence"},{"n":17,"t":"math"},{"n":31,"t":"string"},{"n":4,"t":"new-years"},{"n":17,"t":"decision-problem"},{"n":4,"t":"integer"},{"n":5,"t":"javascript"},{"n":12,"t":"number"},{"n":3,"t":"busy-beaver"},{"n":3,"t":"fibonacci"},{"n":29,"t":"kolmogorov-complexity"},{"n":7,"t":"primes"},{"n":6,"t":"arithmetic"},{"n":2,"t":"hashing"},{"n":2,"t":"duct-tape-coding"},{"n":7,"t":"palindrome"},{"n":2,"t":"balanced-string"},{"n":2,"t":"atomic-code-golf"},{"n":13,"t":"source-layout"},{"n":11,"t":"printable-ascii"},{"n":2,"t":"polyglot"},{"n":3,"t":"pangram"},{"n":9,"t":"answer-chaining"},{"n":10,"t":"quine"},{"n":2,"t":"brainfuck"},{"n":2,"t":"metagolf"},{"n":3,"t":"code-generation"},{"n":2,"t":"bitwise"},{"n":4,"t":"multiple-holes"},{"n":4,"t":"pristine-programming"},{"n":2,"t":"code-shuffleboard"},{"n":2,"t":"expression-building"},{"n":2,"t":"programming-puzzle"},{"n":5,"t":"binary"},{"n":2,"t":"base-conversion"},{"n":2,"t":"brain-flak"},{"n":6,"t":"cops-and-robbers"},{"n":4,"t":"code-bowling"},{"n":4,"t":"self-referential"},{"n":2,"t":"python"},{"n":2,"t":"ascii-art"},{"n":2,"t":"tips"}],"restricted-time":[{"n":29,"t":"code-golf"},{"n":4,"t":"sequence"},{"n":4,"t":"number-theory"},{"n":2,"t":"pi"},{"n":3,"t":"arithmetic"},{"n":2,"t":"factorial"},{"n":9,"t":"math"},{"n":3,"t":"kolmogorov-complexity"},{"n":3,"t":"number"},{"n":3,"t":"string"},{"n":3,"t":"combinatorics"},{"n":2,"t":"permutations"},{"n":2,"t":"grid"},{"n":3,"t":"abstract-algebra"},{"n":3,"t":"code-challenge"}],"roman-numerals":[{"n":15,"t":"code-golf"},{"n":3,"t":"math"},{"n":3,"t":"number"},{"n":2,"t":"base-conversion"},{"n":2,"t":"arithmetic"}],"rosetta-stone":[{"n":8,"t":"code-challenge"},{"n":2,"t":"quine"},{"n":5,"t":"code-golf"},{"n":2,"t":"math"},{"n":2,"t":"source-layout"},{"n":9,"t":"polyglot"},{"n":2,"t":"sequence"}],"rubiks-cube":[{"n":16,"t":"code-golf"},{"n":3,"t":"puzzle-solver"},{"n":2,"t":"code-challenge"},{"n":3,"t":"string"},{"n":2,"t":"array-manipulation"}],"ruby":[{"n":3,"t":"code-golf"},{"n":2,"t":"tips"}],"scrabble":[{"n":2,"t":"code-challenge"},{"n":4,"t":"code-golf"},{"n":3,"t":"string"},{"n":2,"t":"board-game"},{"n":2,"t":"kolmogorov-complexity"}],"search":[{"n":13,"t":"code-golf"},{"n":2,"t":"internet"},{"n":4,"t":"string"},{"n":3,"t":"array-manipulation"}],"self-referential":[{"n":10,"t":"code-challenge"},{"n":17,"t":"code-golf"},{"n":3,"t":"string"},{"n":2,"t":"quine"},{"n":3,"t":"source-layout"},{"n":4,"t":"restricted-source"},{"n":2,"t":"radiation-hardening"}],"sequence":[{"n":554,"t":"code-golf"},{"n":81,"t":"number-theory"},{"n":4,"t":"restricted-time"},{"n":184,"t":"number"},{"n":33,"t":"fibonacci"},{"n":7,"t":"restricted-source"},{"n":143,"t":"math"},{"n":8,"t":"counting"},{"n":8,"t":"fastest-code"},{"n":2,"t":"cellular-automata"},{"n":45,"t":"combinatorics"},{"n":5,"t":"sorting"},{"n":4,"t":"stack"},{"n":2,"t":"popularity-contest"},{"n":11,"t":"geometry"},{"n":14,"t":"array-manipulation"},{"n":22,"t":"cops-and-robbers"},{"n":50,"t":"primes"},{"n":2,"t":"multiple-holes"},{"n":21,"t":"subsequence"},{"n":47,"t":"arithmetic"},{"n":11,"t":"permutations"},{"n":3,"t":"graphical-output"},{"n":29,"t":"binary"},{"n":22,"t":"code-challenge"},{"n":5,"t":"answer-chaining"},{"n":13,"t":"kolmogorov-complexity"},{"n":18,"t":"base-conversion"},{"n":6,"t":"grid"},{"n":3,"t":"integer-partitions"},{"n":7,"t":"palindrome"},{"n":8,"t":"polyglot"},{"n":2,"t":"path-finding"},{"n":5,"t":"graph-theory"},{"n":7,"t":"division"},{"n":4,"t":"game"},{"n":3,"t":"set-partitions"},{"n":3,"t":"balanced-string"},{"n":20,"t":"string"},{"n":9,"t":"ascii-art"},{"n":3,"t":"fractal"},{"n":2,"t":"bitwise"},{"n":3,"t":"abstract-algebra"},{"n":4,"t":"quine"},{"n":3,"t":"code-generation"},{"n":19,"t":"decision-problem"},{"n":4,"t":"rational-numbers"},{"n":5,"t":"polynomials"},{"n":63,"t":"integer"},{"n":3,"t":"pi"},{"n":4,"t":"recursion"},{"n":4,"t":"random"},{"n":2,"t":"tiling"},{"n":3,"t":"factoring"},{"n":2,"t":"factorial"},{"n":2,"t":"optimization"},{"n":2,"t":"rosetta-stone"},{"n":2,"t":"function"},{"n":3,"t":"polyomino"},{"n":3,"t":"hexagonal-grid"},{"n":2,"t":"apl"},{"n":2,"t":"binary-tree"}],"set-partitions":[{"n":36,"t":"code-golf"},{"n":5,"t":"number"},{"n":13,"t":"combinatorics"},{"n":3,"t":"arithmetic"},{"n":2,"t":"array-manipulation"},{"n":4,"t":"decision-problem"},{"n":4,"t":"geometry"},{"n":6,"t":"grid"},{"n":2,"t":"string"},{"n":3,"t":"sequence"},{"n":4,"t":"number-theory"},{"n":2,"t":"subsequence"},{"n":4,"t":"math"},{"n":2,"t":"primes"}],"set-theory":[{"n":22,"t":"code-golf"},{"n":8,"t":"math"},{"n":3,"t":"arithmetic"},{"n":4,"t":"decision-problem"},{"n":3,"t":"number"}],"simulation":[{"n":26,"t":"code-golf"},{"n":4,"t":"grid"},{"n":4,"t":"ascii-art"},{"n":3,"t":"random"},{"n":3,"t":"decision-problem"}],"sliding-puzzle":[{"n":9,"t":"code-golf"},{"n":3,"t":"code-challenge"},{"n":2,"t":"puzzle-solver"},{"n":3,"t":"game"},{"n":2,"t":"javascript"},{"n":2,"t":"ai-player"}],"sorting":[{"n":107,"t":"code-golf"},{"n":10,"t":"code-challenge"},{"n":7,"t":"permutations"},{"n":14,"t":"number"},{"n":5,"t":"sequence"},{"n":4,"t":"stack"},{"n":3,"t":"bitwise"},{"n":2,"t":"popularity-contest"},{"n":32,"t":"array-manipulation"},{"n":3,"t":"restricted-complexity"},{"n":4,"t":"ascii-art"},{"n":27,"t":"string"},{"n":2,"t":"word"},{"n":5,"t":"math"},{"n":4,"t":"matrix"},{"n":7,"t":"integer"},{"n":3,"t":"date"},{"n":3,"t":"natural-language"},{"n":3,"t":"optimization"},{"n":2,"t":"alphabet"}],"source-layout":[{"n":2,"t":"popularity-contest"},{"n":8,"t":"radiation-hardening"},{"n":32,"t":"code-challenge"},{"n":17,"t":"quine"},{"n":6,"t":"hello-world"},{"n":82,"t":"code-golf"},{"n":13,"t":"restricted-source"},{"n":13,"t":"printable-ascii"},{"n":7,"t":"cops-and-robbers"},{"n":2,"t":"tetris"},{"n":2,"t":"crossword"},{"n":2,"t":"rosetta-stone"},{"n":5,"t":"whitespace"},{"n":18,"t":"string"},{"n":5,"t":"permutations"},{"n":4,"t":"kolmogorov-complexity"},{"n":2,"t":"array-manipulation"},{"n":2,"t":"arithmetic"},{"n":7,"t":"number"},{"n":4,"t":"primes"},{"n":5,"t":"integer"},{"n":3,"t":"math"},{"n":2,"t":"number-theory"},{"n":2,"t":"combinatorics"},{"n":3,"t":"matrix"},{"n":4,"t":"decision-problem"},{"n":3,"t":"multiple-holes"},{"n":3,"t":"self-referential"}],"sql":[{"n":3,"t":"code-golf"},{"n":3,"t":"tips"}],"stack":[{"n":22,"t":"code-golf"},{"n":9,"t":"interpreter"},{"n":3,"t":"befunge"},{"n":5,"t":"code-challenge"},{"n":3,"t":"optimization"},{"n":5,"t":"number"},{"n":4,"t":"sequence"},{"n":4,"t":"sorting"},{"n":2,"t":"popularity-contest"},{"n":5,"t":"metagolf"},{"n":3,"t":"game"},{"n":2,"t":"math"},{"n":2,"t":"brain-flak"}],"stack-exchange-api":[{"n":16,"t":"code-golf"},{"n":2,"t":"code-challenge"},{"n":10,"t":"internet"}],"stateful":[{"n":9,"t":"code-golf"},{"n":2,"t":"quine"}],"statistics":[{"n":17,"t":"code-golf"},{"n":9,"t":"math"},{"n":5,"t":"arithmetic"},{"n":2,"t":"code-challenge"},{"n":2,"t":"integer"},{"n":2,"t":"probability-theory"},{"n":3,"t":"array-manipulation"}],"steganography":[{"n":3,"t":"code-golf"}],"string":[{"n":1292,"t":"code-golf"},{"n":18,"t":"palindrome"},{"n":22,"t":"subsequence"},{"n":21,"t":"permutations"},{"n":20,"t":"whitespace"},{"n":33,"t":"balanced-string"},{"n":44,"t":"random"},{"n":79,"t":"decision-problem"},{"n":3,"t":"graphical-output"},{"n":62,"t":"number"},{"n":152,"t":"ascii-art"},{"n":31,"t":"restricted-source"},{"n":23,"t":"alphabet"},{"n":12,"t":"compression"},{"n":3,"t":"self-referential"},{"n":58,"t":"parsing"},{"n":4,"t":"restricted-complexity"},{"n":98,"t":"kolmogorov-complexity"},{"n":7,"t":"hello-world"},{"n":2,"t":"fibonacci"},{"n":20,"t":"counting"},{"n":40,"t":"code-challenge"},{"n":5,"t":"multiple-holes"},{"n":4,"t":"c"},{"n":7,"t":"primes"},{"n":10,"t":"printable-ascii"},{"n":9,"t":"cryptography"},{"n":2,"t":"networking"},{"n":30,"t":"natural-language"},{"n":7,"t":"regular-expression"},{"n":3,"t":"pattern-matching"},{"n":11,"t":"binary"},{"n":28,"t":"math"},{"n":8,"t":"chemistry"},{"n":3,"t":"board-game"},{"n":3,"t":"scrabble"},{"n":6,"t":"interpreter"},{"n":20,"t":"array-manipulation"},{"n":3,"t":"boggle"},{"n":4,"t":"word-search"},{"n":4,"t":"popularity-contest"},{"n":5,"t":"typography"},{"n":22,"t":"arithmetic"},{"n":18,"t":"unicode"},{"n":11,"t":"base-conversion"},{"n":10,"t":"classification"},{"n":18,"t":"source-layout"},{"n":14,"t":"game"},{"n":10,"t":"conversion"},{"n":23,"t":"date"},{"n":8,"t":"syntax"},{"n":29,"t":"grid"},{"n":4,"t":"comment"},{"n":3,"t":"fractal"},{"n":27,"t":"sorting"},{"n":4,"t":"encode"},{"n":5,"t":"fastest-code"},{"n":3,"t":"data-structures"},{"n":4,"t":"word"},{"n":3,"t":"path-finding"},{"n":7,"t":"polyglot"},{"n":7,"t":"file-system"},{"n":2,"t":"chess"},{"n":2,"t":"set-partitions"},{"n":3,"t":"restricted-time"},{"n":13,"t":"keyboard"},{"n":10,"t":"quine"},{"n":3,"t":"physics"},{"n":20,"t":"sequence"},{"n":2,"t":"hexagonal-grid"},{"n":12,"t":"cipher"},{"n":2,"t":"pi"},{"n":4,"t":"optimized-output"},{"n":2,"t":"number-theory"},{"n":11,"t":"geometry"},{"n":4,"t":"encryption"},{"n":2,"t":"card-games"},{"n":3,"t":"crossword"},{"n":5,"t":"bitwise"},{"n":3,"t":"rubiks-cube"},{"n":3,"t":"bioinformatics"},{"n":18,"t":"integer"},{"n":12,"t":"combinatorics"},{"n":3,"t":"internet"},{"n":4,"t":"color"},{"n":2,"t":"python"},{"n":11,"t":"animation"},{"n":7,"t":"hexadecimal"},{"n":4,"t":"cops-and-robbers"},{"n":2,"t":"tiling"},{"n":2,"t":"abstract-algebra"},{"n":2,"t":"logic"},{"n":2,"t":"factorial"},{"n":6,"t":"substitution"},{"n":4,"t":"generation"},{"n":2,"t":"code-bowling"},{"n":3,"t":"pangram"},{"n":4,"t":"brain-flak"},{"n":2,"t":"hashing"},{"n":2,"t":"interactive"},{"n":4,"t":"search"},{"n":2,"t":"haskell"},{"n":2,"t":"apl"},{"n":6,"t":"matrix"},{"n":4,"t":"text-processing"},{"n":2,"t":"graph-theory"},{"n":4,"t":"encoding"},{"n":2,"t":"binary-matrix"}],"subsequence":[{"n":61,"t":"code-golf"},{"n":22,"t":"string"},{"n":2,"t":"kolmogorov-complexity"},{"n":3,"t":"combinatorics"},{"n":21,"t":"sequence"},{"n":6,"t":"array-manipulation"},{"n":7,"t":"decision-problem"},{"n":2,"t":"set-partitions"},{"n":6,"t":"number"},{"n":3,"t":"arithmetic"},{"n":2,"t":"fibonacci"},{"n":3,"t":"math"},{"n":2,"t":"base-conversion"},{"n":4,"t":"binary"},{"n":3,"t":"matrix"},{"n":2,"t":"number-theory"},{"n":3,"t":"integer"},{"n":3,"t":"counting"}],"substitution":[{"n":9,"t":"code-golf"},{"n":6,"t":"string"},{"n":2,"t":"integer"}],"sudoku":[{"n":10,"t":"code-golf"},{"n":3,"t":"game"},{"n":3,"t":"puzzle-solver"},{"n":3,"t":"decision-problem"},{"n":3,"t":"code-challenge"},{"n":2,"t":"grid"}],"syntax":[{"n":3,"t":"parsing"},{"n":14,"t":"code-golf"},{"n":8,"t":"string"},{"n":3,"t":"decision-problem"},{"n":4,"t":"balanced-string"}],"test-battery":[{"n":23,"t":"code-challenge"},{"n":3,"t":"puzzle-solver"},{"n":8,"t":"classification"},{"n":2,"t":"optimization"},{"n":4,"t":"image-processing"},{"n":5,"t":"metagolf"},{"n":2,"t":"brain-flak"},{"n":2,"t":"decision-problem"},{"n":2,"t":"natural-language"},{"n":2,"t":"python"}],"tetris":[{"n":4,"t":"code-challenge"},{"n":2,"t":"game"},{"n":2,"t":"source-layout"},{"n":7,"t":"code-golf"}],"text-processing":[{"n":10,"t":"code-golf"},{"n":4,"t":"string"}],"tic-tac-toe":[{"n":11,"t":"code-golf"},{"n":2,"t":"king-of-the-hill"},{"n":2,"t":"decision-problem"},{"n":4,"t":"board-game"},{"n":3,"t":"game"}],"tiling":[{"n":28,"t":"code-golf"},{"n":4,"t":"graphical-output"},{"n":2,"t":"kolmogorov-complexity"},{"n":5,"t":"geometry"},{"n":10,"t":"ascii-art"},{"n":8,"t":"combinatorics"},{"n":2,"t":"code-challenge"},{"n":7,"t":"grid"},{"n":3,"t":"hexagonal-grid"},{"n":4,"t":"decision-problem"},{"n":2,"t":"sequence"},{"n":2,"t":"string"},{"n":2,"t":"matrix"},{"n":2,"t":"dominoes"},{"n":2,"t":"polyomino"}],"tips":[{"n":127,"t":"code-golf"},{"n":18,"t":"python"},{"n":3,"t":"c++"},{"n":2,"t":"ruby"},{"n":4,"t":"haskell"},{"n":2,"t":"c"},{"n":6,"t":"javascript"},{"n":2,"t":"lisp"},{"n":4,"t":"basic"},{"n":5,"t":"golfscript"},{"n":2,"t":"java"},{"n":3,"t":"brainfuck"},{"n":3,"t":"octave"},{"n":2,"t":"ascii-art"},{"n":2,"t":"number"},{"n":3,"t":"sql"},{"n":2,"t":"array-manipulation"},{"n":2,"t":"pyth"},{"n":2,"t":"kolmogorov-complexity"},{"n":2,"t":"compression"},{"n":2,"t":"quine"},{"n":2,"t":"golfing-language"},{"n":2,"t":"functional-programming"},{"n":2,"t":"assembly"},{"n":2,"t":"restricted-source"}],"topology":[{"n":12,"t":"code-golf"},{"n":8,"t":"math"},{"n":2,"t":"decision-problem"},{"n":2,"t":"combinatorics"}],"tree-traversal":[{"n":6,"t":"code-golf"},{"n":2,"t":"binary-tree"},{"n":2,"t":"decision-problem"}],"trigonometry":[{"n":21,"t":"code-golf"},{"n":13,"t":"math"},{"n":10,"t":"geometry"},{"n":4,"t":"graphical-output"}],"typography":[{"n":13,"t":"code-golf"},{"n":5,"t":"string"},{"n":2,"t":"graphical-output"}],"underhanded":[{"n":2,"t":"code-challenge"},{"n":32,"t":"popularity-contest"},{"n":5,"t":"math"},{"n":2,"t":"pi"}],"unicode":[{"n":40,"t":"code-golf"},{"n":3,"t":"code-challenge"},{"n":18,"t":"string"},{"n":5,"t":"kolmogorov-complexity"},{"n":3,"t":"conversion"},{"n":4,"t":"parsing"},{"n":3,"t":"ascii-art"},{"n":2,"t":"decision-problem"},{"n":2,"t":"binary-matrix"}],"vim":[{"n":3,"t":"code-golf"}],"whitespace":[{"n":26,"t":"code-golf"},{"n":20,"t":"string"},{"n":4,"t":"balanced-string"},{"n":2,"t":"quine"},{"n":5,"t":"source-layout"},{"n":2,"t":"ascii-art"},{"n":2,"t":"conversion"},{"n":2,"t":"cops-and-robbers"}],"whitespace-language":[{"n":3,"t":"code-golf"}],"word":[{"n":11,"t":"code-golf"},{"n":2,"t":"code-challenge"},{"n":3,"t":"classification"},{"n":4,"t":"string"},{"n":2,"t":"sorting"}],"word-puzzle":[{"n":6,"t":"code-golf"},{"n":2,"t":"code-challenge"}],"word-search":[{"n":6,"t":"code-golf"},{"n":4,"t":"string"},{"n":2,"t":"code-challenge"},{"n":2,"t":"grid"}],"x86-family":[{"n":3,"t":"code-golf"},{"n":3,"t":"machine-code"},{"n":2,"t":"assembly"}]}