{"access-control":[{"n":2,"t":"postgresql"},{"n":3,"t":"permissions"},{"n":2,"t":"sql-server"}],"active-directory":[{"n":2,"t":"sql-server"},{"n":2,"t":"sql-server-2008"},{"n":2,"t":"permissions"}],"ado.net":[{"n":5,"t":"sql-server"},{"n":2,"t":"configuration"},{"n":2,"t":"mysql"},{"n":2,"t":"innodb"},{"n":2,"t":"deadlock"},{"n":2,"t":"t-sql"},{"n":2,"t":"transaction"}],"aggregate":[{"n":2,"t":"database-design"},{"n":2,"t":"oracle"},{"n":2,"t":"null"},{"n":10,"t":"postgresql"},{"n":6,"t":"sql-server"},{"n":2,"t":"sql-server-2008"},{"n":2,"t":"sql-server-2005"},{"n":2,"t":"performance"},{"n":2,"t":"sql-standard"},{"n":2,"t":"window-functions"},{"n":2,"t":"group-by"},{"n":2,"t":"join"},{"n":3,"t":"array"},{"n":2,"t":"sql-server-2017"}],"alias":[{"n":2,"t":"sql-server"},{"n":2,"t":"subquery"}],"alter-database":[{"n":2,"t":"sql-server"}],"alter-table":[{"n":13,"t":"sql-server"},{"n":2,"t":"constraint"},{"n":8,"t":"mysql"},{"n":3,"t":"index"},{"n":2,"t":"innodb"},{"n":3,"t":"sql-server-2008-r2"},{"n":4,"t":"locking"},{"n":5,"t":"ddl"},{"n":2,"t":"sql-server-2008"},{"n":8,"t":"postgresql"},{"n":2,"t":"oracle"},{"n":3,"t":"database-design"},{"n":2,"t":"transaction-log"},{"n":3,"t":"null"},{"n":2,"t":"sql-server-2017"}],"amazon-ec2":[{"n":2,"t":"amazon-rds"},{"n":2,"t":"postgresql"}],"amazon-rds":[{"n":7,"t":"mysql"},{"n":2,"t":"amazon-ec2"},{"n":11,"t":"postgresql"},{"n":3,"t":"aws"},{"n":2,"t":"optimization"},{"n":2,"t":"postgresql-9.3"},{"n":2,"t":"sql-server"}],"application-design":[{"n":2,"t":"performance"}],"architecture":[{"n":3,"t":"database-design"},{"n":3,"t":"sql-server"},{"n":2,"t":"storage"},{"n":2,"t":"postgresql"}],"archive":[{"n":2,"t":"sql-server"}],"array":[{"n":10,"t":"postgresql"},{"n":3,"t":"postgresql-9.3"},{"n":3,"t":"json"},{"n":3,"t":"aggregate"},{"n":3,"t":"postgresql-9.4"}],"audit":[{"n":4,"t":"database-design"},{"n":2,"t":"delete"},{"n":3,"t":"mysql"},{"n":5,"t":"sql-server"},{"n":2,"t":"sql-server-2012"}],"authentication":[{"n":3,"t":"mysql"},{"n":2,"t":"postgresql"},{"n":6,"t":"sql-server"},{"n":2,"t":"kerberos"},{"n":2,"t":"logins"},{"n":2,"t":"sql-server-2012"},{"n":2,"t":"sql-server-2016"}],"auto-increment":[{"n":3,"t":"postgresql"},{"n":6,"t":"mysql"},{"n":3,"t":"sql-server"},{"n":3,"t":"identity"},{"n":2,"t":"select"},{"n":3,"t":"primary-key"},{"n":2,"t":"insert"}],"availability-groups":[{"n":20,"t":"sql-server"},{"n":5,"t":"sql-server-2012"},{"n":4,"t":"sql-server-2014"},{"n":2,"t":"upgrade"},{"n":2,"t":"sql-server-2016"},{"n":2,"t":"sql-server-2017"}],"aws":[{"n":3,"t":"postgresql"},{"n":3,"t":"amazon-rds"}],"azure-sql-database":[{"n":11,"t":"sql-server"},{"n":3,"t":"execution-plan"},{"n":2,"t":"index"},{"n":2,"t":"performance"},{"n":2,"t":"query-performance"}],"azure-vm":[{"n":2,"t":"sql-server"}],"backup":[{"n":29,"t":"mysql"},{"n":2,"t":"performance"},{"n":5,"t":"innodb"},{"n":27,"t":"mysqldump"},{"n":3,"t":"migration"},{"n":11,"t":"sql-server-2008"},{"n":4,"t":"maintenance"},{"n":2,"t":"trigger"},{"n":2,"t":"oracle"},{"n":51,"t":"sql-server"},{"n":22,"t":"restore"},{"n":2,"t":"permissions"},{"n":11,"t":"postgresql"},{"n":5,"t":"sql-server-2005"},{"n":5,"t":"export"},{"n":2,"t":"stored-procedures"},{"n":6,"t":"sql-server-2008-r2"},{"n":2,"t":"pg-dump"},{"n":2,"t":"replication"},{"n":5,"t":"transaction-log"},{"n":8,"t":"sql-server-2012"},{"n":3,"t":"postgresql-9.1"},{"n":3,"t":"security"},{"n":3,"t":"mongodb"},{"n":4,"t":"sql-server-2014"},{"n":2,"t":"best-practices"},{"n":2,"t":"ola-hallengren"},{"n":2,"t":"sql-server-2017"}],"batch-mode":[{"n":3,"t":"sql-server"},{"n":2,"t":"sql-server-2014"},{"n":3,"t":"columnstore"}],"bcp":[{"n":2,"t":"sql-server"}],"benchmark":[{"n":3,"t":"postgresql"}],"best-practices":[{"n":22,"t":"sql-server"},{"n":2,"t":"index"},{"n":2,"t":"constraint"},{"n":3,"t":"sql-server-2008"},{"n":2,"t":"oracle"},{"n":11,"t":"database-design"},{"n":2,"t":"sql-server-2005"},{"n":2,"t":"stored-procedures"},{"n":3,"t":"maintenance"},{"n":2,"t":"naming-convention"},{"n":3,"t":"performance"},{"n":5,"t":"postgresql"},{"n":2,"t":"schema"},{"n":3,"t":"permissions"},{"n":2,"t":"deployment"},{"n":3,"t":"foreign-key"},{"n":2,"t":"t-sql"},{"n":2,"t":"backup"},{"n":2,"t":"security"}],"binlog":[{"n":3,"t":"mysql"}],"blob":[{"n":2,"t":"datafile"},{"n":4,"t":"sql-server"},{"n":2,"t":"performance"}],"blocking":[{"n":4,"t":"sql-server"},{"n":3,"t":"locking"}],"bookmark-lookup":[{"n":3,"t":"sql-server"},{"n":2,"t":"execution-plan"}],"buffer-pool":[{"n":2,"t":"sql-server"},{"n":2,"t":"performance"},{"n":2,"t":"mysql"},{"n":2,"t":"innodb"}],"bulk":[{"n":2,"t":"mysql"},{"n":3,"t":"import"},{"n":2,"t":"postgresql"}],"bulk-insert":[{"n":6,"t":"sql-server"},{"n":2,"t":"insert"},{"n":2,"t":"sql-server-2014"}],"business-intelligence":[{"n":2,"t":"data-warehouse"},{"n":2,"t":"ssas"}],"bytea":[{"n":2,"t":"postgresql"}],"c#":[{"n":4,"t":"sql-server"},{"n":2,"t":"sql-server-2008"},{"n":2,"t":"sql-clr"}],"cache":[{"n":2,"t":"postgresql"},{"n":3,"t":"memory"},{"n":2,"t":"mysql"},{"n":5,"t":"performance"},{"n":4,"t":"sql-server"}],"cardinality-estimates":[{"n":19,"t":"sql-server"},{"n":4,"t":"sql-server-2012"},{"n":6,"t":"execution-plan"},{"n":2,"t":"type-conversion"},{"n":5,"t":"optimization"},{"n":6,"t":"query-performance"},{"n":5,"t":"performance"},{"n":7,"t":"sql-server-2014"},{"n":4,"t":"sql-server-2016"},{"n":2,"t":"statistics"},{"n":3,"t":"sql-server-2017"}],"cassandra":[{"n":2,"t":"mongodb"},{"n":2,"t":"nosql"}],"cast":[{"n":5,"t":"postgresql"},{"n":3,"t":"datatypes"}],"catalogs":[{"n":5,"t":"postgresql"}],"centos-7":[{"n":2,"t":"postgresql"}],"certificate":[{"n":2,"t":"sql-server"}],"change-data-capture":[{"n":2,"t":"sql-server"}],"change-tracking":[{"n":2,"t":"sql-server-2012"}],"character-set":[{"n":3,"t":"mysql"},{"n":2,"t":"sql-server"},{"n":2,"t":"encoding"}],"check-constraints":[{"n":2,"t":"postgresql"},{"n":2,"t":"sql-server"}],"clustered-index":[{"n":22,"t":"sql-server"},{"n":2,"t":"data-pages"},{"n":2,"t":"sql-server-2005"},{"n":6,"t":"index"},{"n":2,"t":"primary-key"},{"n":3,"t":"performance"},{"n":4,"t":"index-tuning"},{"n":3,"t":"materialized-view"},{"n":2,"t":"database-internals"},{"n":2,"t":"postgresql"}],"clustering":[{"n":3,"t":"sql-server"}],"collation":[{"n":2,"t":"performance"},{"n":17,"t":"sql-server"},{"n":4,"t":"sql-server-2008"},{"n":2,"t":"sql-server-2005"},{"n":3,"t":"encoding"},{"n":5,"t":"postgresql"},{"n":2,"t":"database-design"},{"n":2,"t":"index"},{"n":2,"t":"mysql"},{"n":2,"t":"utf-8"},{"n":5,"t":"unicode"},{"n":2,"t":"sql-server-2008-r2"},{"n":3,"t":"t-sql"}],"columnstore":[{"n":11,"t":"sql-server"},{"n":2,"t":"index"},{"n":2,"t":"sql-server-2012"},{"n":4,"t":"sql-server-2014"},{"n":3,"t":"batch-mode"},{"n":4,"t":"sql-server-2016"}],"command-line":[{"n":3,"t":"postgresql"},{"n":2,"t":"psql"}],"compatibility-level":[{"n":3,"t":"sql-server"}],"compression":[{"n":7,"t":"sql-server"},{"n":2,"t":"mysql"},{"n":2,"t":"innodb"},{"n":3,"t":"sql-server-2014"}],"computed-column":[{"n":11,"t":"sql-server"},{"n":3,"t":"sql-server-2012"},{"n":3,"t":"index"},{"n":2,"t":"view"},{"n":2,"t":"sql-server-2014"}],"concat":[{"n":2,"t":"sql-server"}],"concurrency":[{"n":2,"t":"index"},{"n":6,"t":"sql-server"},{"n":5,"t":"locking"},{"n":2,"t":"isolation-level"},{"n":8,"t":"postgresql"},{"n":2,"t":"update"}],"condition":[{"n":2,"t":"sql-server"}],"configuration":[{"n":8,"t":"mysql"},{"n":15,"t":"sql-server"},{"n":2,"t":"ado.net"},{"n":2,"t":"sql-server-2005"},{"n":4,"t":"performance"},{"n":2,"t":"ssms"},{"n":2,"t":"innodb"},{"n":6,"t":"postgresql"},{"n":2,"t":"database-design"}],"connections":[{"n":2,"t":"postgresql"},{"n":4,"t":"sql-server"},{"n":2,"t":"sql-server-2012"}],"connectivity":[{"n":6,"t":"sql-server"},{"n":2,"t":"sql-server-2012"},{"n":2,"t":"ssms"},{"n":2,"t":"sql-server-2014"}],"constraint":[{"n":15,"t":"sql-server"},{"n":6,"t":"index"},{"n":2,"t":"best-practices"},{"n":7,"t":"unique-constraint"},{"n":2,"t":"alter-table"},{"n":4,"t":"referential-integrity"},{"n":6,"t":"mysql"},{"n":13,"t":"postgresql"},{"n":2,"t":"null"},{"n":2,"t":"innodb"},{"n":9,"t":"foreign-key"},{"n":9,"t":"database-design"},{"n":2,"t":"primary-key"},{"n":3,"t":"ddl"},{"n":2,"t":"sql-server-2014"}],"corruption":[{"n":3,"t":"sql-server-2008"},{"n":2,"t":"postgresql"},{"n":5,"t":"sql-server"},{"n":2,"t":"dbcc-checkdb"}],"couchdb":[{"n":3,"t":"nosql"},{"n":2,"t":"mongodb"}],"count":[{"n":6,"t":"postgresql"},{"n":3,"t":"index"},{"n":2,"t":"null"},{"n":9,"t":"mysql"},{"n":3,"t":"performance"},{"n":2,"t":"optimization"},{"n":3,"t":"select"},{"n":2,"t":"group-by"}],"crash":[{"n":2,"t":"mysql"},{"n":2,"t":"innodb"},{"n":2,"t":"mysql-5.5"},{"n":2,"t":"sql-server"}],"cross-apply":[{"n":2,"t":"sql-server"}],"csv":[{"n":2,"t":"postgresql"},{"n":2,"t":"mysql"}],"cte":[{"n":11,"t":"sql-server"},{"n":3,"t":"t-sql"},{"n":2,"t":"optimization"},{"n":6,"t":"postgresql"},{"n":6,"t":"recursive"},{"n":2,"t":"performance"},{"n":2,"t":"query-performance"}],"cursors":[{"n":2,"t":"sql-server"}],"data-integrity":[{"n":2,"t":"database-design"},{"n":3,"t":"postgresql"},{"n":2,"t":"mysql"}],"data-pages":[{"n":5,"t":"sql-server"},{"n":2,"t":"clustered-index"},{"n":2,"t":"database-internals"},{"n":2,"t":"index"}],"data-synchronization":[{"n":2,"t":"sql-server"}],"data-warehouse":[{"n":3,"t":"database-design"},{"n":2,"t":"business-intelligence"},{"n":2,"t":"postgresql"},{"n":3,"t":"etl"},{"n":5,"t":"sql-server"},{"n":2,"t":"sql-server-2012"}],"database-design":[{"n":6,"t":"erd"},{"n":8,"t":"relational-theory"},{"n":22,"t":"performance"},{"n":3,"t":"data-warehouse"},{"n":2,"t":"delete"},{"n":4,"t":"audit"},{"n":34,"t":"mysql"},{"n":2,"t":"aggregate"},{"n":7,"t":"oracle"},{"n":4,"t":"security"},{"n":12,"t":"datatypes"},{"n":14,"t":"normalization"},{"n":43,"t":"sql-server"},{"n":16,"t":"sql-server-2008"},{"n":3,"t":"metadata"},{"n":11,"t":"database-recommendation"},{"n":38,"t":"postgresql"},{"n":12,"t":"schema"},{"n":2,"t":"tools"},{"n":11,"t":"best-practices"},{"n":2,"t":"join"},{"n":5,"t":"null"},{"n":10,"t":"primary-key"},{"n":2,"t":"naming-convention"},{"n":3,"t":"database-theory"},{"n":3,"t":"architecture"},{"n":4,"t":"sql-server-2008-r2"},{"n":2,"t":"surrogate-key"},{"n":6,"t":"partitioning"},{"n":2,"t":"default-value"},{"n":19,"t":"foreign-key"},{"n":2,"t":"nosql"},{"n":2,"t":"xml"},{"n":5,"t":"eav"},{"n":2,"t":"innodb"},{"n":7,"t":"sql-server-2012"},{"n":11,"t":"index"},{"n":7,"t":"subtypes"},{"n":3,"t":"mysql-5.5"},{"n":4,"t":"referential-integrity"},{"n":5,"t":"query-performance"},{"n":2,"t":"database-internals"},{"n":2,"t":"data-integrity"},{"n":3,"t":"postgresql-9.1"},{"n":3,"t":"alter-table"},{"n":4,"t":"index-tuning"},{"n":2,"t":"rdbms"},{"n":9,"t":"constraint"},{"n":3,"t":"unique-constraint"},{"n":2,"t":"collation"},{"n":2,"t":"identity"},{"n":3,"t":"t-sql"},{"n":2,"t":"database-diagrams"},{"n":2,"t":"postgresql-performance"},{"n":2,"t":"many-to-many"},{"n":2,"t":"nonclustered-index"},{"n":2,"t":"configuration"},{"n":2,"t":"uniqueidentifier"},{"n":2,"t":"permissions"},{"n":2,"t":"denormalization"},{"n":2,"t":"relations"},{"n":3,"t":"varchar"},{"n":2,"t":"datetime"},{"n":2,"t":"sql-server-2016"},{"n":2,"t":"sql-server-2014"}],"database-diagrams":[{"n":2,"t":"database-design"}],"database-internals":[{"n":4,"t":"sql-server-2008"},{"n":2,"t":"data-pages"},{"n":32,"t":"sql-server"},{"n":2,"t":"database-design"},{"n":2,"t":"statistics"},{"n":4,"t":"sql-server-2012"},{"n":3,"t":"execution-plan"},{"n":2,"t":"clustered-index"},{"n":3,"t":"sql-server-2008-r2"},{"n":2,"t":"sql-server-2014"},{"n":2,"t":"index-tuning"},{"n":5,"t":"performance"},{"n":2,"t":"optimization"},{"n":2,"t":"postgresql"},{"n":2,"t":"metadata"},{"n":2,"t":"sql-server-2016"},{"n":3,"t":"query-performance"},{"n":3,"t":"sql-server-2017"}],"database-link":[{"n":2,"t":"oracle"}],"database-mail":[{"n":4,"t":"sql-server"}],"database-recommendation":[{"n":3,"t":"nosql"},{"n":3,"t":"mysql"},{"n":2,"t":"feature-comparison"},{"n":11,"t":"database-design"},{"n":3,"t":"performance"},{"n":2,"t":"sql-server"}],"database-size":[{"n":3,"t":"mysql"},{"n":3,"t":"postgresql"},{"n":2,"t":"sql-server"}],"database-theory":[{"n":3,"t":"database-design"},{"n":2,"t":"sql-server"},{"n":2,"t":"terminology"}],"database-tuning":[{"n":4,"t":"sql-server"},{"n":2,"t":"insert"},{"n":4,"t":"performance"},{"n":2,"t":"mysql"}],"datafile":[{"n":2,"t":"blob"}],"datatypes":[{"n":18,"t":"postgresql"},{"n":11,"t":"mysql"},{"n":12,"t":"database-design"},{"n":5,"t":"performance"},{"n":3,"t":"varchar"},{"n":2,"t":"oracle"},{"n":6,"t":"sql-server-2008"},{"n":4,"t":"type-conversion"},{"n":2,"t":"stored-procedures"},{"n":2,"t":"parameter"},{"n":16,"t":"sql-server"},{"n":4,"t":"t-sql"},{"n":2,"t":"xml"},{"n":3,"t":"cast"},{"n":2,"t":"uniqueidentifier"},{"n":3,"t":"unicode"}],"date":[{"n":3,"t":"sql-server"},{"n":2,"t":"sql-server-2012"},{"n":2,"t":"timestamp"}],"date-format":[{"n":2,"t":"postgresql"},{"n":3,"t":"sql-server"}],"datetime":[{"n":6,"t":"sql-server"},{"n":2,"t":"sql-server-2008"},{"n":3,"t":"t-sql"},{"n":2,"t":"mysql"},{"n":2,"t":"sql-server-2012"},{"n":2,"t":"timezone"},{"n":2,"t":"database-design"},{"n":2,"t":"postgresql"}],"datetime2":[{"n":2,"t":"sql-server"}],"dbcc":[{"n":2,"t":"sql-server-2005"},{"n":2,"t":"sql-server"},{"n":2,"t":"shrink"}],"dbcc-checkdb":[{"n":8,"t":"sql-server"},{"n":2,"t":"corruption"}],"ddl":[{"n":2,"t":"rollback"},{"n":9,"t":"sql-server"},{"n":3,"t":"sql-server-2008"},{"n":2,"t":"transaction"},{"n":3,"t":"oracle"},{"n":6,"t":"postgresql"},{"n":2,"t":"functions"},{"n":4,"t":"mysql"},{"n":5,"t":"alter-table"},{"n":3,"t":"constraint"},{"n":2,"t":"referential-integrity"},{"n":2,"t":"t-sql"}],"deadlock":[{"n":22,"t":"sql-server"},{"n":6,"t":"sql-server-2008"},{"n":6,"t":"mysql"},{"n":4,"t":"innodb"},{"n":2,"t":"ado.net"},{"n":3,"t":"sql-server-2008-r2"},{"n":2,"t":"merge"},{"n":2,"t":"sql-server-2012"},{"n":2,"t":"locking"}],"debian":[{"n":2,"t":"mysql"}],"decimal":[{"n":2,"t":"sql-server"}],"default-value":[{"n":4,"t":"postgresql"},{"n":2,"t":"sql-server"},{"n":2,"t":"sql-server-2008"},{"n":2,"t":"database-design"}],"delete":[{"n":2,"t":"database-design"},{"n":2,"t":"audit"},{"n":2,"t":"oracle"},{"n":8,"t":"sql-server"},{"n":6,"t":"performance"},{"n":7,"t":"postgresql"},{"n":2,"t":"trigger"},{"n":2,"t":"sql-server-2008-r2"},{"n":2,"t":"vacuum"},{"n":4,"t":"mysql"},{"n":3,"t":"innodb"},{"n":2,"t":"sql-server-2012"},{"n":2,"t":"truncate"}],"denormalization":[{"n":2,"t":"database-design"}],"deployment":[{"n":2,"t":"best-practices"},{"n":2,"t":"ssdt"}],"disk-space":[{"n":7,"t":"postgresql"},{"n":2,"t":"truncate"},{"n":3,"t":"sql-server-2008"},{"n":2,"t":"mysql"},{"n":2,"t":"innodb"},{"n":3,"t":"maintenance"},{"n":7,"t":"sql-server"},{"n":3,"t":"performance"},{"n":2,"t":"postgresql-performance"},{"n":2,"t":"sql-server-2008-r2"}],"disk-structures":[{"n":2,"t":"sql-server"}],"distributed-availability-groups":[{"n":2,"t":"sql-server"},{"n":2,"t":"sql-server-2017"}],"dmv":[{"n":13,"t":"sql-server"},{"n":3,"t":"index"},{"n":2,"t":"sql-server-2005"},{"n":2,"t":"sql-server-2008-r2"},{"n":3,"t":"sql-server-2012"},{"n":2,"t":"stored-procedures"}],"docker":[{"n":2,"t":"mongodb"}],"document-oriented":[{"n":2,"t":"nosql"},{"n":2,"t":"mongodb"}],"documentation":[{"n":3,"t":"sql-server"}],"dump":[{"n":2,"t":"mysql"},{"n":3,"t":"postgresql"}],"duplication":[{"n":3,"t":"postgresql"},{"n":2,"t":"insert"},{"n":2,"t":"mysql"}],"dynamic-ports":[{"n":2,"t":"sql-server"}],"dynamic-sql":[{"n":2,"t":"scripting"},{"n":7,"t":"sql-server"},{"n":2,"t":"sql-injection"},{"n":2,"t":"t-sql"}],"eav":[{"n":5,"t":"database-design"},{"n":2,"t":"schema"},{"n":2,"t":"mysql"}],"encoding":[{"n":7,"t":"sql-server"},{"n":3,"t":"collation"},{"n":2,"t":"postgresql"},{"n":3,"t":"unicode"},{"n":2,"t":"character-set"}],"encryption":[{"n":7,"t":"sql-server"},{"n":2,"t":"transparent-data-encryption"},{"n":2,"t":"sql-server-2008-r2"},{"n":2,"t":"ssl"}],"erd":[{"n":6,"t":"database-design"}],"error-handling":[{"n":3,"t":"postgresql"},{"n":3,"t":"plpgsql"},{"n":2,"t":"sql-server"}],"errors":[{"n":9,"t":"sql-server"},{"n":2,"t":"sql-server-2008-r2"},{"n":5,"t":"mysql"},{"n":2,"t":"t-sql"},{"n":2,"t":"sql-server-2012"}],"etl":[{"n":2,"t":"postgresql"},{"n":3,"t":"data-warehouse"},{"n":4,"t":"sql-server"},{"n":2,"t":"sql-server-2005"}],"except":[{"n":7,"t":"sql-server"},{"n":2,"t":"sql-server-2008"},{"n":4,"t":"sql-server-2008-r2"},{"n":2,"t":"performance"},{"n":2,"t":"query-performance"}],"exclusion-constraint":[{"n":3,"t":"postgresql"}],"execution-plan":[{"n":74,"t":"sql-server"},{"n":5,"t":"sql-server-2008-r2"},{"n":22,"t":"performance"},{"n":10,"t":"optimization"},{"n":19,"t":"query-performance"},{"n":9,"t":"sql-server-2008"},{"n":14,"t":"sql-server-2012"},{"n":2,"t":"t-sql"},{"n":3,"t":"xml"},{"n":3,"t":"database-internals"},{"n":2,"t":"type-conversion"},{"n":6,"t":"cardinality-estimates"},{"n":2,"t":"warning"},{"n":5,"t":"postgresql"},{"n":2,"t":"ssms"},{"n":3,"t":"azure-sql-database"},{"n":5,"t":"index"},{"n":2,"t":"bookmark-lookup"},{"n":2,"t":"memory-grant"},{"n":4,"t":"statistics"},{"n":3,"t":"plan-cache"},{"n":2,"t":"postgresql-9.4"},{"n":4,"t":"sql-server-2014"},{"n":5,"t":"sql-server-2016"},{"n":3,"t":"query-store"},{"n":2,"t":"join"},{"n":2,"t":"postgresql-10"},{"n":3,"t":"sql-server-2017"}],"exists":[{"n":4,"t":"sql-server"},{"n":2,"t":"performance"}],"explain":[{"n":3,"t":"postgresql"},{"n":3,"t":"mysql"},{"n":2,"t":"index"},{"n":3,"t":"optimization"}],"export":[{"n":4,"t":"oracle"},{"n":5,"t":"mysql"},{"n":4,"t":"mysqldump"},{"n":5,"t":"sql-server"},{"n":5,"t":"backup"},{"n":2,"t":"import"},{"n":2,"t":"postgresql"}],"extended-events":[{"n":9,"t":"sql-server"},{"n":2,"t":"profiler"},{"n":3,"t":"sql-server-2016"}],"failover":[{"n":2,"t":"postgresql"},{"n":2,"t":"sql-server"}],"feature-comparison":[{"n":2,"t":"database-recommendation"},{"n":2,"t":"sql-server"}],"filegroups":[{"n":5,"t":"sql-server"}],"filestream":[{"n":3,"t":"sql-server"}],"filtered-index":[{"n":3,"t":"index"},{"n":5,"t":"sql-server"},{"n":2,"t":"sql-server-2008-r2"},{"n":2,"t":"performance"},{"n":2,"t":"query-performance"}],"foreign-key":[{"n":3,"t":"join"},{"n":19,"t":"database-design"},{"n":8,"t":"mysql"},{"n":3,"t":"innodb"},{"n":3,"t":"best-practices"},{"n":9,"t":"constraint"},{"n":5,"t":"referential-integrity"},{"n":12,"t":"postgresql"},{"n":11,"t":"sql-server"},{"n":2,"t":"normalization"},{"n":2,"t":"relational-theory"},{"n":4,"t":"primary-key"},{"n":2,"t":"index"},{"n":3,"t":"sql-server-2014"},{"n":2,"t":"sql-server-2016"}],"fragmentation":[{"n":2,"t":"sql-server-2008"},{"n":3,"t":"index"},{"n":6,"t":"sql-server"}],"full-text-search":[{"n":4,"t":"mysql"},{"n":6,"t":"postgresql"},{"n":2,"t":"performance"},{"n":3,"t":"pattern-matching"},{"n":4,"t":"sql-server"},{"n":2,"t":"sql-server-2008-r2"},{"n":4,"t":"index"}],"functions":[{"n":23,"t":"sql-server"},{"n":18,"t":"postgresql"},{"n":2,"t":"ddl"},{"n":2,"t":"oracle"},{"n":2,"t":"stored-procedures"},{"n":3,"t":"sql-server-2008-r2"},{"n":4,"t":"t-sql"},{"n":4,"t":"performance"},{"n":6,"t":"plpgsql"},{"n":2,"t":"sql-server-2012"},{"n":2,"t":"join"},{"n":2,"t":"sql-server-2014"},{"n":3,"t":"query-performance"},{"n":3,"t":"sql-server-2019"}],"gaps-and-islands":[{"n":3,"t":"postgresql"},{"n":3,"t":"window-functions"},{"n":2,"t":"group-by"},{"n":4,"t":"sql-server"},{"n":3,"t":"sql-server-2008-r2"}],"google-app-engine":[{"n":2,"t":"performance"}],"greatest-n-per-group":[{"n":2,"t":"oracle"},{"n":4,"t":"postgresql"},{"n":3,"t":"performance"},{"n":2,"t":"query-performance"},{"n":2,"t":"index"},{"n":4,"t":"sql-server"}],"group-by":[{"n":6,"t":"sql-server"},{"n":2,"t":"sql-server-2008"},{"n":8,"t":"postgresql"},{"n":2,"t":"performance"},{"n":2,"t":"index"},{"n":2,"t":"gaps-and-islands"},{"n":2,"t":"window-functions"},{"n":2,"t":"join"},{"n":2,"t":"count"},{"n":2,"t":"mysql"},{"n":2,"t":"aggregate"}],"hardware":[{"n":8,"t":"sql-server"},{"n":3,"t":"sql-server-2008-r2"},{"n":5,"t":"performance"}],"hashing":[{"n":2,"t":"sql-server"}],"heap":[{"n":5,"t":"sql-server"}],"hierarchy":[{"n":4,"t":"sql-server"},{"n":2,"t":"sql-server-2008"},{"n":2,"t":"sql-server-2008-r2"}],"high-availability":[{"n":4,"t":"sql-server"},{"n":2,"t":"sql-server-2012"},{"n":2,"t":"postgresql"}],"identity":[{"n":16,"t":"sql-server"},{"n":3,"t":"sql-server-2005"},{"n":3,"t":"auto-increment"},{"n":3,"t":"primary-key"},{"n":2,"t":"database-design"},{"n":2,"t":"insert"},{"n":2,"t":"sql-server-2012"},{"n":2,"t":"sql-server-2008-r2"},{"n":2,"t":"sql-server-2014"}],"import":[{"n":3,"t":"oracle"},{"n":5,"t":"mysql"},{"n":3,"t":"bulk"},{"n":3,"t":"mysqldump"},{"n":3,"t":"sql-server"},{"n":2,"t":"export"}],"index":[{"n":24,"t":"mysql"},{"n":3,"t":"filtered-index"},{"n":2,"t":"rdbms"},{"n":79,"t":"sql-server"},{"n":41,"t":"performance"},{"n":16,"t":"optimization"},{"n":2,"t":"best-practices"},{"n":6,"t":"constraint"},{"n":5,"t":"unique-constraint"},{"n":2,"t":"concurrency"},{"n":4,"t":"sql-server-2005"},{"n":9,"t":"primary-key"},{"n":6,"t":"clustered-index"},{"n":49,"t":"postgresql"},{"n":2,"t":"view"},{"n":3,"t":"oracle"},{"n":3,"t":"count"},{"n":7,"t":"innodb"},{"n":3,"t":"myisam"},{"n":3,"t":"alter-table"},{"n":2,"t":"postgresql-8.4"},{"n":3,"t":"pattern-matching"},{"n":11,"t":"sql-server-2008"},{"n":3,"t":"fragmentation"},{"n":10,"t":"index-tuning"},{"n":4,"t":"order-by"},{"n":12,"t":"sql-server-2012"},{"n":2,"t":"columnstore"},{"n":12,"t":"sql-server-2008-r2"},{"n":4,"t":"statistics"},{"n":4,"t":"maintenance"},{"n":2,"t":"partitioning"},{"n":4,"t":"full-text-search"},{"n":11,"t":"database-design"},{"n":4,"t":"join"},{"n":2,"t":"metadata"},{"n":11,"t":"query-performance"},{"n":2,"t":"sorting"},{"n":3,"t":"dmv"},{"n":3,"t":"nonclustered-index"},{"n":2,"t":"postgresql-9.1"},{"n":4,"t":"postgresql-performance"},{"n":2,"t":"group-by"},{"n":2,"t":"varchar"},{"n":2,"t":"explain"},{"n":5,"t":"execution-plan"},{"n":2,"t":"collation"},{"n":2,"t":"greatest-n-per-group"},{"n":2,"t":"foreign-key"},{"n":3,"t":"locking"},{"n":3,"t":"postgresql-9.3"},{"n":3,"t":"sql-server-2014"},{"n":3,"t":"materialized-view"},{"n":2,"t":"uuid"},{"n":2,"t":"t-sql"},{"n":2,"t":"postgresql-9.4"},{"n":3,"t":"computed-column"},{"n":2,"t":"azure-sql-database"},{"n":2,"t":"update"},{"n":2,"t":"data-pages"},{"n":2,"t":"transaction"},{"n":2,"t":"sql-server-2016"}],"index-maintenance":[{"n":5,"t":"sql-server"}],"index-statistics":[{"n":2,"t":"mysql"},{"n":5,"t":"sql-server"},{"n":2,"t":"sql-server-2008-r2"},{"n":3,"t":"statistics"}],"index-tuning":[{"n":22,"t":"sql-server"},{"n":9,"t":"performance"},{"n":10,"t":"index"},{"n":3,"t":"sql-server-2008"},{"n":6,"t":"postgresql"},{"n":4,"t":"clustered-index"},{"n":2,"t":"materialized-view"},{"n":4,"t":"database-design"},{"n":2,"t":"sql-server-2012"},{"n":2,"t":"sql-server-2008-r2"},{"n":2,"t":"database-internals"},{"n":2,"t":"sql-server-2014"},{"n":4,"t":"query-performance"}],"information-schema":[{"n":3,"t":"mysql"},{"n":3,"t":"postgresql"},{"n":2,"t":"sql-server"},{"n":2,"t":"sql-server-2008-r2"}],"innodb":[{"n":109,"t":"mysql"},{"n":18,"t":"myisam"},{"n":18,"t":"performance"},{"n":5,"t":"backup"},{"n":6,"t":"mysqldump"},{"n":2,"t":"storage-engine"},{"n":3,"t":"logs"},{"n":7,"t":"index"},{"n":4,"t":"deadlock"},{"n":2,"t":"ado.net"},{"n":2,"t":"alter-table"},{"n":14,"t":"mysql-5.5"},{"n":3,"t":"percona-server"},{"n":2,"t":"disk-space"},{"n":3,"t":"foreign-key"},{"n":2,"t":"database-design"},{"n":2,"t":"constraint"},{"n":3,"t":"locking"},{"n":2,"t":"linux"},{"n":3,"t":"memory"},{"n":4,"t":"transaction"},{"n":3,"t":"delete"},{"n":2,"t":"mysql-5.1"},{"n":2,"t":"crash"},{"n":2,"t":"windows"},{"n":2,"t":"configuration"},{"n":2,"t":"isolation-level"},{"n":2,"t":"optimization"},{"n":4,"t":"mysql-5.6"},{"n":2,"t":"buffer-pool"},{"n":2,"t":"compression"},{"n":2,"t":"mysql-5.7"}],"insert":[{"n":13,"t":"sql-server"},{"n":2,"t":"database-tuning"},{"n":6,"t":"postgresql"},{"n":6,"t":"performance"},{"n":2,"t":"duplication"},{"n":2,"t":"mysql"},{"n":2,"t":"sql-server-2005"},{"n":3,"t":"sql-server-2012"},{"n":2,"t":"query-performance"},{"n":2,"t":"auto-increment"},{"n":2,"t":"output-clause"},{"n":2,"t":"identity"},{"n":2,"t":"bulk-insert"},{"n":2,"t":"sql-server-2014"}],"installation":[{"n":2,"t":"mysql"},{"n":2,"t":"windows"},{"n":5,"t":"postgresql"},{"n":2,"t":"oracle"},{"n":2,"t":"ubuntu"},{"n":2,"t":"postgresql-9.3"},{"n":3,"t":"sql-server-2012"},{"n":2,"t":"ssms"},{"n":9,"t":"sql-server"},{"n":2,"t":"sql-server-2008-r2"},{"n":2,"t":"sql-server-2017"}],"instance":[{"n":2,"t":"sql-server"}],"intellisense":[{"n":2,"t":"sql-server"}],"isolation-level":[{"n":5,"t":"sql-server"},{"n":2,"t":"locking"},{"n":2,"t":"concurrency"},{"n":2,"t":"mysql"},{"n":2,"t":"innodb"}],"jdbc":[{"n":2,"t":"mysql"}],"jobs":[{"n":3,"t":"maintenance"},{"n":4,"t":"sql-server"},{"n":3,"t":"t-sql"},{"n":2,"t":"sql-server-2008-r2"}],"join":[{"n":3,"t":"foreign-key"},{"n":2,"t":"oracle"},{"n":3,"t":"syntax"},{"n":9,"t":"mysql"},{"n":2,"t":"database-design"},{"n":2,"t":"naming-convention"},{"n":5,"t":"select"},{"n":21,"t":"sql-server"},{"n":14,"t":"performance"},{"n":20,"t":"postgresql"},{"n":6,"t":"optimization"},{"n":2,"t":"ms-access"},{"n":4,"t":"index"},{"n":6,"t":"query-performance"},{"n":4,"t":"t-sql"},{"n":3,"t":"sql-server-2012"},{"n":2,"t":"group-by"},{"n":2,"t":"update"},{"n":2,"t":"postgresql-9.4"},{"n":2,"t":"functions"},{"n":2,"t":"window-functions"},{"n":2,"t":"postgresql-9.3"},{"n":2,"t":"aggregate"},{"n":2,"t":"sql-server-2014"},{"n":2,"t":"execution-plan"},{"n":2,"t":"postgresql-10"}],"json":[{"n":13,"t":"postgresql"},{"n":3,"t":"postgresql-9.3"},{"n":3,"t":"array"},{"n":2,"t":"row"},{"n":3,"t":"postgresql-9.4"},{"n":3,"t":"mysql"}],"kerberos":[{"n":3,"t":"sql-server"},{"n":2,"t":"authentication"}],"like":[{"n":4,"t":"sql-server"},{"n":2,"t":"sql-server-2016"}],"limits":[{"n":2,"t":"sql-server"}],"linked-server":[{"n":10,"t":"sql-server"},{"n":2,"t":"sql-server-2008-r2"},{"n":2,"t":"sql-server-2008"},{"n":2,"t":"sql-server-2005"},{"n":3,"t":"sql-server-2014"},{"n":2,"t":"sql-server-2012"}],"linux":[{"n":14,"t":"mysql"},{"n":6,"t":"postgresql"},{"n":5,"t":"ubuntu"},{"n":2,"t":"mysqldump"},{"n":2,"t":"innodb"},{"n":4,"t":"sql-server"},{"n":2,"t":"sql-server-2017"}],"listener":[{"n":2,"t":"oracle-11g"}],"locking":[{"n":25,"t":"sql-server"},{"n":2,"t":"nolock"},{"n":8,"t":"mysql"},{"n":3,"t":"sql-server-2008-r2"},{"n":4,"t":"alter-table"},{"n":3,"t":"transaction"},{"n":5,"t":"concurrency"},{"n":2,"t":"isolation-level"},{"n":3,"t":"innodb"},{"n":2,"t":"oracle"},{"n":2,"t":"oracle-11g-r2"},{"n":4,"t":"postgresql"},{"n":2,"t":"sql-server-2008"},{"n":3,"t":"index"},{"n":3,"t":"sql-server-2012"},{"n":2,"t":"deadlock"},{"n":3,"t":"blocking"}],"log":[{"n":2,"t":"postgresql"},{"n":2,"t":"mysql"}],"log-shipping":[{"n":3,"t":"sql-server"}],"logins":[{"n":9,"t":"sql-server"},{"n":2,"t":"sql-server-2012"},{"n":2,"t":"sql-server-2008"},{"n":6,"t":"security"},{"n":3,"t":"permissions"},{"n":2,"t":"authentication"}],"logs":[{"n":5,"t":"mysql"},{"n":3,"t":"innodb"},{"n":3,"t":"sql-server"},{"n":2,"t":"postgresql"}],"mac-os-x":[{"n":5,"t":"postgresql"},{"n":3,"t":"psql"},{"n":2,"t":"mysql"}],"maintenance":[{"n":5,"t":"sql-server-2008"},{"n":4,"t":"backup"},{"n":3,"t":"jobs"},{"n":2,"t":"sql-server-2005"},{"n":3,"t":"best-practices"},{"n":11,"t":"sql-server"},{"n":3,"t":"disk-space"},{"n":3,"t":"performance"},{"n":5,"t":"postgresql"},{"n":4,"t":"index"},{"n":2,"t":"statistics"},{"n":3,"t":"vacuum"}],"maintenance-plans":[{"n":2,"t":"sql-server"}],"management":[{"n":2,"t":"sql-server"}],"many-to-many":[{"n":2,"t":"database-design"}],"mariadb":[{"n":9,"t":"mysql"}],"master-system-database":[{"n":2,"t":"sql-server"}],"materialized-view":[{"n":11,"t":"sql-server"},{"n":2,"t":"sql-server-2008"},{"n":2,"t":"index-tuning"},{"n":3,"t":"clustered-index"},{"n":7,"t":"postgresql"},{"n":3,"t":"view"},{"n":2,"t":"postgresql-9.4"},{"n":3,"t":"index"}],"max":[{"n":2,"t":"sql-server"}],"max-connections":[{"n":2,"t":"mysql"},{"n":2,"t":"postgresql"}],"maxdop":[{"n":2,"t":"sql-server"}],"memory":[{"n":18,"t":"sql-server"},{"n":2,"t":"windows"},{"n":5,"t":"mysql"},{"n":4,"t":"postgresql"},{"n":3,"t":"cache"},{"n":4,"t":"sql-server-2008"},{"n":3,"t":"sql-server-2008-r2"},{"n":2,"t":"ubuntu"},{"n":3,"t":"innodb"},{"n":6,"t":"performance"},{"n":2,"t":"numa"},{"n":2,"t":"sql-server-express"},{"n":2,"t":"sql-server-2012"},{"n":2,"t":"query-performance"},{"n":2,"t":"temporary-tables"},{"n":2,"t":"sql-server-2014"},{"n":2,"t":"mongodb"},{"n":3,"t":"sql-server-2016"},{"n":2,"t":"tempdb"}],"memory-grant":[{"n":2,"t":"sql-server"},{"n":2,"t":"execution-plan"}],"memory-optimized-tables":[{"n":3,"t":"sql-server"},{"n":2,"t":"sql-server-2014"}],"merge":[{"n":7,"t":"sql-server"},{"n":2,"t":"deadlock"},{"n":2,"t":"t-sql"},{"n":2,"t":"sql-server-2014"}],"merge-replication":[{"n":4,"t":"sql-server"},{"n":2,"t":"sql-server-2005"},{"n":2,"t":"replication"}],"metadata":[{"n":10,"t":"sql-server"},{"n":2,"t":"sql-server-2008"},{"n":3,"t":"database-design"},{"n":2,"t":"schema"},{"n":2,"t":"index"},{"n":3,"t":"postgresql"},{"n":2,"t":"database-internals"}],"microsoft-dynamics":[{"n":2,"t":"sql-server"}],"migration":[{"n":5,"t":"mysql"},{"n":3,"t":"backup"},{"n":2,"t":"mysqldump"},{"n":13,"t":"sql-server"},{"n":2,"t":"sql-server-2008"},{"n":3,"t":"restore"},{"n":6,"t":"postgresql"},{"n":2,"t":"tools"},{"n":2,"t":"schema"},{"n":3,"t":"sql-server-2000"},{"n":2,"t":"oracle"},{"n":2,"t":"sql-server-2012"}],"mirroring":[{"n":2,"t":"sql-server-2008"},{"n":6,"t":"sql-server"},{"n":3,"t":"sql-server-2005"}],"mongodb":[{"n":3,"t":"nosql"},{"n":2,"t":"document-oriented"},{"n":2,"t":"couchdb"},{"n":4,"t":"replication"},{"n":2,"t":"cassandra"},{"n":2,"t":"postgresql"},{"n":2,"t":"rdbms"},{"n":3,"t":"backup"},{"n":2,"t":"restore"},{"n":2,"t":"docker"},{"n":2,"t":"mongodb-3.0"},{"n":2,"t":"memory"}],"mongodb-3.0":[{"n":2,"t":"mongodb"}],"monitoring":[{"n":3,"t":"sql-server"},{"n":3,"t":"postgresql"}],"ms-access":[{"n":2,"t":"join"}],"multi-tenant":[{"n":2,"t":"sql-server"}],"my.cnf":[{"n":5,"t":"mysql"}],"myisam":[{"n":26,"t":"mysql"},{"n":18,"t":"innodb"},{"n":2,"t":"storage-engine"},{"n":3,"t":"index"},{"n":3,"t":"mysqldump"},{"n":7,"t":"performance"},{"n":2,"t":"mysql-5.5"},{"n":2,"t":"mysql-5.6"}],"mysql":[{"n":109,"t":"innodb"},{"n":26,"t":"myisam"},{"n":4,"t":"schema"},{"n":9,"t":"mariadb"},{"n":3,"t":"database-recommendation"},{"n":59,"t":"performance"},{"n":29,"t":"backup"},{"n":45,"t":"mysqldump"},{"n":5,"t":"slow-log"},{"n":8,"t":"configuration"},{"n":24,"t":"index"},{"n":4,"t":"null"},{"n":4,"t":"security"},{"n":5,"t":"phpmyadmin"},{"n":5,"t":"migration"},{"n":10,"t":"primary-key"},{"n":34,"t":"database-design"},{"n":12,"t":"stored-procedures"},{"n":6,"t":"trigger"},{"n":11,"t":"datatypes"},{"n":4,"t":"storage-engine"},{"n":4,"t":"varchar"},{"n":4,"t":"tools"},{"n":3,"t":"performance-testing"},{"n":26,"t":"replication"},{"n":3,"t":"authentication"},{"n":3,"t":"audit"},{"n":14,"t":"linux"},{"n":2,"t":"testing"},{"n":3,"t":"query"},{"n":5,"t":"my.cnf"},{"n":2,"t":"max-connections"},{"n":5,"t":"logs"},{"n":12,"t":"mysql-5"},{"n":8,"t":"windows"},{"n":2,"t":"installation"},{"n":9,"t":"join"},{"n":5,"t":"memory"},{"n":2,"t":"prepared-statement"},{"n":19,"t":"postgresql"},{"n":4,"t":"full-text-search"},{"n":8,"t":"locking"},{"n":5,"t":"export"},{"n":39,"t":"mysql-5.5"},{"n":7,"t":"mysql-5.1"},{"n":2,"t":"mysql-5.0"},{"n":9,"t":"sql-server"},{"n":6,"t":"deadlock"},{"n":2,"t":"ado.net"},{"n":14,"t":"select"},{"n":3,"t":"information-schema"},{"n":5,"t":"percona"},{"n":2,"t":"index-statistics"},{"n":6,"t":"mysql-workbench"},{"n":8,"t":"alter-table"},{"n":2,"t":"table"},{"n":2,"t":"dump"},{"n":2,"t":"ndbcluster"},{"n":4,"t":"view"},{"n":2,"t":"database-tuning"},{"n":2,"t":"mac-os-x"},{"n":2,"t":"tuning"},{"n":6,"t":"order-by"},{"n":3,"t":"percona-server"},{"n":2,"t":"disk-space"},{"n":2,"t":"partitioning"},{"n":3,"t":"php"},{"n":10,"t":"optimization"},{"n":3,"t":"temporary-tables"},{"n":2,"t":"uniqueidentifier"},{"n":3,"t":"database-size"},{"n":4,"t":"restore"},{"n":7,"t":"permissions"},{"n":6,"t":"constraint"},{"n":4,"t":"ddl"},{"n":2,"t":"profiler"},{"n":3,"t":"relational-theory"},{"n":3,"t":"spatial"},{"n":3,"t":"normalization"},{"n":8,"t":"transaction"},{"n":9,"t":"count"},{"n":8,"t":"foreign-key"},{"n":7,"t":"amazon-rds"},{"n":5,"t":"import"},{"n":2,"t":"bulk"},{"n":7,"t":"oracle"},{"n":2,"t":"jdbc"},{"n":2,"t":"sorting"},{"n":2,"t":"syntax"},{"n":7,"t":"update"},{"n":3,"t":"character-set"},{"n":6,"t":"auto-increment"},{"n":3,"t":"explain"},{"n":4,"t":"delete"},{"n":2,"t":"users"},{"n":8,"t":"query-performance"},{"n":2,"t":"cache"},{"n":2,"t":"scalability"},{"n":2,"t":"crash"},{"n":2,"t":"sqlite"},{"n":3,"t":"utf-8"},{"n":2,"t":"isolation-level"},{"n":3,"t":"binlog"},{"n":2,"t":"ssl"},{"n":3,"t":"query-cache"},{"n":2,"t":"subtypes"},{"n":2,"t":"insert"},{"n":2,"t":"duplication"},{"n":13,"t":"mysql-5.6"},{"n":2,"t":"datetime"},{"n":5,"t":"errors"},{"n":2,"t":"csv"},{"n":2,"t":"buffer-pool"},{"n":2,"t":"data-integrity"},{"n":2,"t":"collation"},{"n":2,"t":"log"},{"n":2,"t":"group-by"},{"n":2,"t":"compression"},{"n":2,"t":"debian"},{"n":2,"t":"startup"},{"n":2,"t":"rollback"},{"n":6,"t":"mysql-5.7"},{"n":2,"t":"eav"},{"n":3,"t":"json"},{"n":3,"t":"mysql-8.0"}],"mysql-5":[{"n":12,"t":"mysql"},{"n":3,"t":"replication"},{"n":3,"t":"mysql-5.5"},{"n":2,"t":"mysql-5.6"}],"mysql-5.0":[{"n":2,"t":"mysql"}],"mysql-5.1":[{"n":7,"t":"mysql"},{"n":3,"t":"replication"},{"n":2,"t":"mysql-5.5"},{"n":2,"t":"innodb"}],"mysql-5.5":[{"n":39,"t":"mysql"},{"n":5,"t":"replication"},{"n":2,"t":"mysql-5.1"},{"n":2,"t":"performance"},{"n":14,"t":"innodb"},{"n":2,"t":"mysqldump"},{"n":2,"t":"myisam"},{"n":3,"t":"database-design"},{"n":3,"t":"mysql-5"},{"n":2,"t":"crash"},{"n":2,"t":"percona"},{"n":2,"t":"mysql-5.6"}],"mysql-5.6":[{"n":13,"t":"mysql"},{"n":4,"t":"innodb"},{"n":2,"t":"mysql-5.5"},{"n":2,"t":"mysql-5"},{"n":2,"t":"myisam"}],"mysql-5.7":[{"n":6,"t":"mysql"},{"n":2,"t":"innodb"}],"mysql-8.0":[{"n":3,"t":"mysql"}],"mysql-workbench":[{"n":6,"t":"mysql"}],"mysqldump":[{"n":45,"t":"mysql"},{"n":6,"t":"innodb"},{"n":27,"t":"backup"},{"n":2,"t":"migration"},{"n":3,"t":"myisam"},{"n":4,"t":"export"},{"n":2,"t":"stored-procedures"},{"n":3,"t":"restore"},{"n":2,"t":"postgresql"},{"n":2,"t":"linux"},{"n":2,"t":"mysql-5.5"},{"n":3,"t":"import"}],"naming-convention":[{"n":2,"t":"database-design"},{"n":2,"t":"join"},{"n":2,"t":"best-practices"},{"n":2,"t":"postgresql"}],"natural-key":[{"n":2,"t":"surrogate-key"}],"natural-sort":[{"n":2,"t":"sorting"}],"ndbcluster":[{"n":2,"t":"mysql"}],"network":[{"n":2,"t":"sql-server-2008-r2"},{"n":4,"t":"sql-server"}],"nolock":[{"n":3,"t":"sql-server"},{"n":2,"t":"locking"}],"nonclustered-index":[{"n":3,"t":"index"},{"n":6,"t":"sql-server"},{"n":2,"t":"database-design"},{"n":2,"t":"sql-server-2012"}],"normalization":[{"n":14,"t":"database-design"},{"n":3,"t":"mysql"},{"n":4,"t":"relational-theory"},{"n":2,"t":"foreign-key"}],"nosql":[{"n":3,"t":"rdbms"},{"n":3,"t":"database-recommendation"},{"n":2,"t":"document-oriented"},{"n":3,"t":"mongodb"},{"n":3,"t":"couchdb"},{"n":3,"t":"scalability"},{"n":2,"t":"database-design"},{"n":2,"t":"performance"},{"n":2,"t":"cassandra"},{"n":2,"t":"redis"}],"null":[{"n":4,"t":"mysql"},{"n":3,"t":"oracle"},{"n":2,"t":"aggregate"},{"n":2,"t":"count"},{"n":9,"t":"postgresql"},{"n":5,"t":"database-design"},{"n":2,"t":"constraint"},{"n":3,"t":"unique-constraint"},{"n":11,"t":"sql-server"},{"n":3,"t":"sql-server-2008"},{"n":3,"t":"alter-table"},{"n":2,"t":"t-sql"}],"numa":[{"n":2,"t":"memory"}],"ola-hallengren":[{"n":3,"t":"sql-server"},{"n":2,"t":"backup"}],"operator":[{"n":3,"t":"sql-server"}],"optimization":[{"n":58,"t":"sql-server"},{"n":26,"t":"performance"},{"n":16,"t":"index"},{"n":3,"t":"view"},{"n":10,"t":"execution-plan"},{"n":16,"t":"query-performance"},{"n":3,"t":"sql-server-2008"},{"n":4,"t":"t-sql"},{"n":5,"t":"sql-server-2008-r2"},{"n":2,"t":"stored-procedures"},{"n":10,"t":"mysql"},{"n":6,"t":"join"},{"n":20,"t":"postgresql"},{"n":2,"t":"query"},{"n":7,"t":"sql-server-2012"},{"n":5,"t":"cardinality-estimates"},{"n":3,"t":"explain"},{"n":2,"t":"count"},{"n":2,"t":"innodb"},{"n":2,"t":"cte"},{"n":4,"t":"postgresql-9.3"},{"n":2,"t":"postgresql-performance"},{"n":2,"t":"amazon-rds"},{"n":2,"t":"database-internals"},{"n":2,"t":"performance-tuning"},{"n":5,"t":"sql-server-2014"},{"n":5,"t":"sql-server-2016"}],"oracle":[{"n":2,"t":"tools"},{"n":12,"t":"sqlplus"},{"n":2,"t":"database-link"},{"n":3,"t":"stored-procedures"},{"n":17,"t":"oracle-11g-r2"},{"n":4,"t":"security"},{"n":7,"t":"database-design"},{"n":2,"t":"best-practices"},{"n":10,"t":"oracle-11g"},{"n":2,"t":"join"},{"n":3,"t":"syntax"},{"n":8,"t":"performance"},{"n":2,"t":"aggregate"},{"n":2,"t":"delete"},{"n":10,"t":"plsql"},{"n":10,"t":"oracle-10g"},{"n":2,"t":"backup"},{"n":2,"t":"datatypes"},{"n":4,"t":"export"},{"n":3,"t":"index"},{"n":3,"t":"null"},{"n":3,"t":"import"},{"n":2,"t":"transaction"},{"n":2,"t":"trigger"},{"n":2,"t":"greatest-n-per-group"},{"n":5,"t":"select"},{"n":2,"t":"oracle-sql-developer"},{"n":3,"t":"ddl"},{"n":7,"t":"sql-server"},{"n":2,"t":"permissions"},{"n":2,"t":"tablespaces"},{"n":2,"t":"functions"},{"n":7,"t":"mysql"},{"n":5,"t":"postgresql"},{"n":2,"t":"migration"},{"n":2,"t":"locking"},{"n":2,"t":"alter-table"},{"n":3,"t":"schema"},{"n":2,"t":"installation"},{"n":2,"t":"ubuntu"},{"n":2,"t":"startup"},{"n":2,"t":"windows"},{"n":3,"t":"oracle-12c"}],"oracle-10g":[{"n":10,"t":"oracle"},{"n":2,"t":"oracle-11g-r2"}],"oracle-11g":[{"n":10,"t":"oracle"},{"n":2,"t":"oracle-11g-r2"},{"n":2,"t":"listener"}],"oracle-11g-r2":[{"n":17,"t":"oracle"},{"n":2,"t":"security"},{"n":3,"t":"sqlplus"},{"n":2,"t":"plsql"},{"n":2,"t":"oracle-11g"},{"n":2,"t":"oracle-10g"},{"n":2,"t":"locking"}],"oracle-12c":[{"n":3,"t":"oracle"}],"oracle-sql-developer":[{"n":2,"t":"oracle"}],"order-by":[{"n":3,"t":"sql-server"},{"n":6,"t":"mysql"},{"n":4,"t":"index"},{"n":2,"t":"performance"},{"n":4,"t":"postgresql"}],"orm":[{"n":2,"t":"performance"}],"output-clause":[{"n":2,"t":"sql-server"},{"n":2,"t":"insert"}],"paging":[{"n":2,"t":"sql-server"}],"parallelism":[{"n":6,"t":"performance"},{"n":6,"t":"query-performance"},{"n":9,"t":"sql-server"},{"n":2,"t":"sql-server-2008"}],"parameter":[{"n":4,"t":"stored-procedures"},{"n":2,"t":"datatypes"},{"n":2,"t":"t-sql"},{"n":3,"t":"sql-server"}],"partitioning":[{"n":12,"t":"sql-server"},{"n":4,"t":"sql-server-2008"},{"n":2,"t":"sql-server-2005"},{"n":2,"t":"mysql"},{"n":6,"t":"database-design"},{"n":6,"t":"performance"},{"n":2,"t":"index"},{"n":5,"t":"sql-server-2008-r2"},{"n":10,"t":"postgresql"},{"n":2,"t":"postgresql-performance"},{"n":3,"t":"sql-server-2014"},{"n":2,"t":"query-performance"}],"password":[{"n":3,"t":"sql-server"},{"n":2,"t":"security"}],"password-recovery":[{"n":2,"t":"postgresql"},{"n":2,"t":"windows"}],"pattern-matching":[{"n":8,"t":"postgresql"},{"n":3,"t":"performance"},{"n":3,"t":"full-text-search"},{"n":3,"t":"index"},{"n":2,"t":"postgresql-9.1"}],"percona":[{"n":5,"t":"mysql"},{"n":2,"t":"performance"},{"n":2,"t":"mysql-5.5"}],"percona-server":[{"n":3,"t":"mysql"},{"n":3,"t":"innodb"},{"n":2,"t":"performance"}],"perfmon":[{"n":4,"t":"sql-server"}],"performance":[{"n":59,"t":"mysql"},{"n":18,"t":"innodb"},{"n":2,"t":"backup"},{"n":5,"t":"slow-log"},{"n":2,"t":"google-app-engine"},{"n":167,"t":"sql-server"},{"n":41,"t":"index"},{"n":26,"t":"optimization"},{"n":22,"t":"database-design"},{"n":10,"t":"performance-testing"},{"n":2,"t":"collation"},{"n":3,"t":"primary-key"},{"n":2,"t":"uniqueidentifier"},{"n":5,"t":"datatypes"},{"n":8,"t":"varchar"},{"n":2,"t":"orm"},{"n":5,"t":"query"},{"n":8,"t":"oracle"},{"n":20,"t":"sql-server-2008"},{"n":69,"t":"postgresql"},{"n":18,"t":"sql-server-2005"},{"n":6,"t":"delete"},{"n":2,"t":"full-text-search"},{"n":3,"t":"pattern-matching"},{"n":3,"t":"database-recommendation"},{"n":3,"t":"clustered-index"},{"n":5,"t":"view"},{"n":2,"t":"percona"},{"n":22,"t":"execution-plan"},{"n":114,"t":"query-performance"},{"n":5,"t":"stored-procedures"},{"n":3,"t":"trigger"},{"n":4,"t":"database-tuning"},{"n":2,"t":"testing"},{"n":14,"t":"join"},{"n":2,"t":"transaction"},{"n":9,"t":"index-tuning"},{"n":2,"t":"mysql-5.5"},{"n":2,"t":"tuning"},{"n":4,"t":"scalability"},{"n":7,"t":"myisam"},{"n":6,"t":"partitioning"},{"n":3,"t":"maintenance"},{"n":14,"t":"sql-server-2008-r2"},{"n":6,"t":"insert"},{"n":3,"t":"best-practices"},{"n":2,"t":"application-design"},{"n":2,"t":"order-by"},{"n":2,"t":"buffer-pool"},{"n":3,"t":"temporary-tables"},{"n":2,"t":"nosql"},{"n":2,"t":"aggregate"},{"n":6,"t":"parallelism"},{"n":2,"t":"percona-server"},{"n":4,"t":"configuration"},{"n":5,"t":"select"},{"n":2,"t":"statistics"},{"n":3,"t":"disk-space"},{"n":9,"t":"update"},{"n":2,"t":"vacuum"},{"n":17,"t":"performance-tuning"},{"n":3,"t":"count"},{"n":4,"t":"functions"},{"n":2,"t":"tempdb"},{"n":5,"t":"cache"},{"n":13,"t":"postgresql-performance"},{"n":4,"t":"postgresql-9.1"},{"n":19,"t":"sql-server-2012"},{"n":6,"t":"memory"},{"n":2,"t":"group-by"},{"n":2,"t":"filtered-index"},{"n":4,"t":"spatial"},{"n":7,"t":"t-sql"},{"n":2,"t":"subquery"},{"n":3,"t":"wait-types"},{"n":5,"t":"hardware"},{"n":2,"t":"transaction-log"},{"n":3,"t":"greatest-n-per-group"},{"n":2,"t":"except"},{"n":5,"t":"postgresql-9.3"},{"n":3,"t":"storage"},{"n":3,"t":"xml"},{"n":5,"t":"database-internals"},{"n":2,"t":"window-functions"},{"n":11,"t":"sql-server-2014"},{"n":5,"t":"cardinality-estimates"},{"n":2,"t":"exists"},{"n":2,"t":"blob"},{"n":10,"t":"sql-server-2016"},{"n":5,"t":"postgresql-9.6"},{"n":3,"t":"vmware"},{"n":2,"t":"azure-sql-database"},{"n":2,"t":"top"},{"n":2,"t":"cte"},{"n":2,"t":"sql-server-2017"}],"performance-testing":[{"n":10,"t":"performance"},{"n":3,"t":"mysql"},{"n":5,"t":"sql-server"},{"n":2,"t":"testing"}],"performance-tuning":[{"n":17,"t":"performance"},{"n":5,"t":"query-performance"},{"n":10,"t":"sql-server"},{"n":2,"t":"postgresql"},{"n":2,"t":"sql-server-2008-r2"},{"n":2,"t":"t-sql"},{"n":2,"t":"optimization"}],"permissions":[{"n":38,"t":"sql-server"},{"n":9,"t":"sql-server-2008"},{"n":2,"t":"backup"},{"n":22,"t":"postgresql"},{"n":3,"t":"psql"},{"n":6,"t":"sql-server-2008-r2"},{"n":7,"t":"mysql"},{"n":3,"t":"best-practices"},{"n":2,"t":"sql-server-2005"},{"n":9,"t":"security"},{"n":2,"t":"oracle"},{"n":5,"t":"role"},{"n":2,"t":"schema"},{"n":2,"t":"ssms"},{"n":3,"t":"windows"},{"n":2,"t":"postgresql-9.2"},{"n":2,"t":"active-directory"},{"n":2,"t":"tablespaces"},{"n":3,"t":"ssis"},{"n":2,"t":"trigger"},{"n":6,"t":"sql-server-2012"},{"n":3,"t":"logins"},{"n":2,"t":"t-sql"},{"n":2,"t":"sql-server-agent"},{"n":3,"t":"access-control"},{"n":2,"t":"database-design"},{"n":2,"t":"sql-server-2014"},{"n":2,"t":"view"}],"pg-dump":[{"n":8,"t":"postgresql"},{"n":2,"t":"backup"},{"n":2,"t":"postgresql-9.1"},{"n":2,"t":"postgresql-9.3"}],"pg-hba.conf":[{"n":4,"t":"postgresql"}],"pgadmin":[{"n":15,"t":"postgresql"},{"n":2,"t":"ubuntu"},{"n":2,"t":"pgadmin-4"}],"pgadmin-4":[{"n":2,"t":"pgadmin"}],"pgbouncer":[{"n":2,"t":"postgresql"}],"php":[{"n":3,"t":"mysql"}],"phpmyadmin":[{"n":5,"t":"mysql"}],"pivot":[{"n":5,"t":"sql-server"},{"n":2,"t":"sql-server-2008"}],"plan-cache":[{"n":5,"t":"sql-server"},{"n":3,"t":"execution-plan"},{"n":2,"t":"sql-server-2012"}],"plpgsql":[{"n":24,"t":"postgresql"},{"n":2,"t":"trigger"},{"n":3,"t":"stored-procedures"},{"n":3,"t":"error-handling"},{"n":2,"t":"upsert"},{"n":6,"t":"functions"},{"n":2,"t":"postgresql-9.3"}],"plpython":[{"n":2,"t":"postgresql"}],"plsql":[{"n":10,"t":"oracle"},{"n":2,"t":"oracle-11g-r2"}],"postgis":[{"n":4,"t":"postgresql"},{"n":2,"t":"spatial"}],"postgresql":[{"n":8,"t":"trigger"},{"n":24,"t":"plpgsql"},{"n":3,"t":"security"},{"n":2,"t":"sql-injection"},{"n":11,"t":"primary-key"},{"n":18,"t":"datatypes"},{"n":69,"t":"performance"},{"n":49,"t":"index"},{"n":3,"t":"query"},{"n":38,"t":"database-design"},{"n":11,"t":"schema"},{"n":15,"t":"pgadmin"},{"n":3,"t":"auto-increment"},{"n":4,"t":"tools"},{"n":21,"t":"psql"},{"n":3,"t":"command-line"},{"n":5,"t":"mac-os-x"},{"n":5,"t":"installation"},{"n":8,"t":"postgresql-8.4"},{"n":3,"t":"sql-standard"},{"n":4,"t":"memory"},{"n":2,"t":"cache"},{"n":6,"t":"count"},{"n":19,"t":"mysql"},{"n":6,"t":"full-text-search"},{"n":8,"t":"pattern-matching"},{"n":3,"t":"postgresql-9.0"},{"n":4,"t":"stored-procedures"},{"n":3,"t":"sqlite"},{"n":6,"t":"migration"},{"n":7,"t":"delete"},{"n":9,"t":"null"},{"n":10,"t":"timestamp"},{"n":2,"t":"date-format"},{"n":18,"t":"functions"},{"n":10,"t":"array"},{"n":10,"t":"aggregate"},{"n":7,"t":"select"},{"n":4,"t":"default-value"},{"n":6,"t":"insert"},{"n":3,"t":"benchmark"},{"n":5,"t":"sequence"},{"n":7,"t":"restore"},{"n":2,"t":"type-conversion"},{"n":2,"t":"truncate"},{"n":7,"t":"disk-space"},{"n":11,"t":"backup"},{"n":7,"t":"ubuntu"},{"n":22,"t":"permissions"},{"n":3,"t":"explain"},{"n":3,"t":"error-handling"},{"n":20,"t":"join"},{"n":5,"t":"best-practices"},{"n":2,"t":"failover"},{"n":6,"t":"ddl"},{"n":5,"t":"catalogs"},{"n":13,"t":"constraint"},{"n":10,"t":"unique-constraint"},{"n":2,"t":"mysqldump"},{"n":6,"t":"linux"},{"n":7,"t":"windows"},{"n":10,"t":"replication"},{"n":5,"t":"maintenance"},{"n":2,"t":"corruption"},{"n":2,"t":"regular-expression"},{"n":4,"t":"postgis"},{"n":2,"t":"data-warehouse"},{"n":2,"t":"etl"},{"n":3,"t":"monitoring"},{"n":7,"t":"upsert"},{"n":10,"t":"partitioning"},{"n":5,"t":"storage"},{"n":13,"t":"vacuum"},{"n":20,"t":"optimization"},{"n":2,"t":"connections"},{"n":8,"t":"alter-table"},{"n":3,"t":"database-size"},{"n":8,"t":"pg-dump"},{"n":24,"t":"query-performance"},{"n":5,"t":"oracle"},{"n":9,"t":"transaction"},{"n":3,"t":"random"},{"n":2,"t":"password-recovery"},{"n":13,"t":"update"},{"n":5,"t":"varchar"},{"n":3,"t":"dump"},{"n":5,"t":"role"},{"n":9,"t":"sql-server"},{"n":3,"t":"information-schema"},{"n":2,"t":"testing"},{"n":2,"t":"bytea"},{"n":12,"t":"foreign-key"},{"n":3,"t":"data-integrity"},{"n":6,"t":"view"},{"n":26,"t":"postgresql-9.1"},{"n":13,"t":"postgresql-performance"},{"n":3,"t":"scalability"},{"n":6,"t":"index-tuning"},{"n":3,"t":"sorting"},{"n":4,"t":"locking"},{"n":8,"t":"concurrency"},{"n":2,"t":"tablespaces"},{"n":2,"t":"log"},{"n":8,"t":"group-by"},{"n":5,"t":"collation"},{"n":2,"t":"high-availability"},{"n":3,"t":"duplication"},{"n":5,"t":"timezone"},{"n":9,"t":"postgresql-9.2"},{"n":2,"t":"bulk"},{"n":3,"t":"gaps-and-islands"},{"n":6,"t":"window-functions"},{"n":2,"t":"export"},{"n":2,"t":"csv"},{"n":5,"t":"execution-plan"},{"n":3,"t":"python"},{"n":3,"t":"exclusion-constraint"},{"n":2,"t":"mongodb"},{"n":3,"t":"metadata"},{"n":2,"t":"authentication"},{"n":28,"t":"postgresql-9.4"},{"n":2,"t":"clustered-index"},{"n":4,"t":"greatest-n-per-group"},{"n":3,"t":"upgrade"},{"n":9,"t":"postgresql-9.6"},{"n":38,"t":"postgresql-9.3"},{"n":2,"t":"encoding"},{"n":6,"t":"configuration"},{"n":13,"t":"json"},{"n":2,"t":"users"},{"n":2,"t":"access-control"},{"n":7,"t":"materialized-view"},{"n":2,"t":"pgbouncer"},{"n":5,"t":"referential-integrity"},{"n":11,"t":"amazon-rds"},{"n":2,"t":"amazon-ec2"},{"n":2,"t":"logs"},{"n":4,"t":"order-by"},{"n":6,"t":"cte"},{"n":3,"t":"recursive"},{"n":5,"t":"cast"},{"n":2,"t":"naming-convention"},{"n":2,"t":"max-connections"},{"n":3,"t":"queue"},{"n":2,"t":"row"},{"n":2,"t":"range-types"},{"n":2,"t":"check-constraints"},{"n":3,"t":"aws"},{"n":2,"t":"plpython"},{"n":4,"t":"pg-hba.conf"},{"n":2,"t":"syntax"},{"n":2,"t":"subquery"},{"n":5,"t":"uuid"},{"n":2,"t":"performance-tuning"},{"n":2,"t":"architecture"},{"n":4,"t":"postgresql-extensions"},{"n":2,"t":"table"},{"n":2,"t":"uniqueidentifier"},{"n":2,"t":"database-internals"},{"n":2,"t":"terminology"},{"n":16,"t":"postgresql-9.5"},{"n":2,"t":"datetime"},{"n":6,"t":"postgresql-10"},{"n":2,"t":"centos-7"}],"postgresql-10":[{"n":6,"t":"postgresql"},{"n":2,"t":"join"},{"n":2,"t":"execution-plan"}],"postgresql-8.4":[{"n":8,"t":"postgresql"},{"n":2,"t":"index"}],"postgresql-9.0":[{"n":3,"t":"postgresql"}],"postgresql-9.1":[{"n":26,"t":"postgresql"},{"n":4,"t":"performance"},{"n":3,"t":"database-design"},{"n":2,"t":"index"},{"n":2,"t":"vacuum"},{"n":2,"t":"query-performance"},{"n":2,"t":"pattern-matching"},{"n":3,"t":"backup"},{"n":2,"t":"pg-dump"}],"postgresql-9.2":[{"n":9,"t":"postgresql"},{"n":2,"t":"permissions"}],"postgresql-9.3":[{"n":38,"t":"postgresql"},{"n":2,"t":"installation"},{"n":3,"t":"array"},{"n":3,"t":"json"},{"n":4,"t":"optimization"},{"n":5,"t":"performance"},{"n":3,"t":"index"},{"n":4,"t":"query-performance"},{"n":2,"t":"plpgsql"},{"n":2,"t":"pg-dump"},{"n":2,"t":"amazon-rds"},{"n":2,"t":"join"}],"postgresql-9.4":[{"n":28,"t":"postgresql"},{"n":2,"t":"join"},{"n":3,"t":"json"},{"n":2,"t":"materialized-view"},{"n":2,"t":"index"},{"n":2,"t":"execution-plan"},{"n":3,"t":"array"}],"postgresql-9.5":[{"n":16,"t":"postgresql"},{"n":3,"t":"upsert"}],"postgresql-9.6":[{"n":9,"t":"postgresql"},{"n":5,"t":"performance"},{"n":5,"t":"query-performance"}],"postgresql-extensions":[{"n":4,"t":"postgresql"}],"postgresql-performance":[{"n":13,"t":"postgresql"},{"n":2,"t":"disk-space"},{"n":13,"t":"performance"},{"n":4,"t":"index"},{"n":2,"t":"partitioning"},{"n":2,"t":"optimization"},{"n":2,"t":"database-design"}],"powershell":[{"n":5,"t":"sql-server"},{"n":2,"t":"sql-server-2008"}],"prepared-statement":[{"n":2,"t":"mysql"}],"primary-key":[{"n":10,"t":"mysql"},{"n":3,"t":"performance"},{"n":14,"t":"sql-server"},{"n":3,"t":"uniqueidentifier"},{"n":11,"t":"postgresql"},{"n":2,"t":"sql-server-2005"},{"n":9,"t":"index"},{"n":2,"t":"clustered-index"},{"n":10,"t":"database-design"},{"n":2,"t":"surrogate-key"},{"n":5,"t":"unique-constraint"},{"n":4,"t":"foreign-key"},{"n":2,"t":"constraint"},{"n":3,"t":"identity"},{"n":3,"t":"auto-increment"}],"profiler":[{"n":3,"t":"sql-server-2008"},{"n":7,"t":"sql-server"},{"n":2,"t":"extended-events"},{"n":2,"t":"mysql"},{"n":2,"t":"sql-server-2012"}],"psql":[{"n":21,"t":"postgresql"},{"n":2,"t":"command-line"},{"n":3,"t":"mac-os-x"},{"n":3,"t":"permissions"}],"python":[{"n":3,"t":"postgresql"}],"query":[{"n":7,"t":"sql-server"},{"n":5,"t":"performance"},{"n":3,"t":"postgresql"},{"n":3,"t":"mysql"},{"n":2,"t":"sql-server-2008"},{"n":2,"t":"optimization"},{"n":2,"t":"sql-server-2014"}],"query-cache":[{"n":3,"t":"mysql"}],"query-performance":[{"n":74,"t":"sql-server"},{"n":114,"t":"performance"},{"n":16,"t":"optimization"},{"n":19,"t":"execution-plan"},{"n":2,"t":"sql-server-2008"},{"n":5,"t":"sql-server-2005"},{"n":2,"t":"stored-procedures"},{"n":6,"t":"parallelism"},{"n":2,"t":"view"},{"n":24,"t":"postgresql"},{"n":5,"t":"database-design"},{"n":11,"t":"index"},{"n":8,"t":"sql-server-2008-r2"},{"n":5,"t":"performance-tuning"},{"n":8,"t":"mysql"},{"n":2,"t":"filtered-index"},{"n":6,"t":"join"},{"n":2,"t":"scalability"},{"n":2,"t":"memory"},{"n":2,"t":"postgresql-9.1"},{"n":2,"t":"greatest-n-per-group"},{"n":2,"t":"except"},{"n":10,"t":"sql-server-2012"},{"n":2,"t":"spatial"},{"n":2,"t":"insert"},{"n":4,"t":"postgresql-9.3"},{"n":6,"t":"cardinality-estimates"},{"n":2,"t":"update"},{"n":3,"t":"t-sql"},{"n":2,"t":"window-functions"},{"n":2,"t":"partitioning"},{"n":10,"t":"sql-server-2014"},{"n":3,"t":"functions"},{"n":4,"t":"index-tuning"},{"n":7,"t":"sql-server-2016"},{"n":5,"t":"postgresql-9.6"},{"n":2,"t":"azure-sql-database"},{"n":3,"t":"database-internals"},{"n":2,"t":"select"},{"n":2,"t":"top"},{"n":2,"t":"cte"}],"query-store":[{"n":5,"t":"sql-server"},{"n":4,"t":"sql-server-2016"},{"n":3,"t":"execution-plan"},{"n":2,"t":"statistics"}],"queue":[{"n":3,"t":"postgresql"}],"random":[{"n":3,"t":"postgresql"}],"range-types":[{"n":2,"t":"postgresql"}],"rdbms":[{"n":3,"t":"nosql"},{"n":2,"t":"index"},{"n":2,"t":"database-design"},{"n":2,"t":"mongodb"}],"recovery":[{"n":9,"t":"sql-server"},{"n":2,"t":"sql-server-2008"},{"n":3,"t":"sql-server-2008-r2"}],"recovery-model":[{"n":2,"t":"sql-server"},{"n":2,"t":"transaction-log"}],"recursive":[{"n":7,"t":"sql-server"},{"n":3,"t":"postgresql"},{"n":6,"t":"cte"}],"redis":[{"n":2,"t":"nosql"}],"referential-integrity":[{"n":4,"t":"constraint"},{"n":4,"t":"database-design"},{"n":5,"t":"foreign-key"},{"n":5,"t":"postgresql"},{"n":2,"t":"ddl"}],"regular-expression":[{"n":2,"t":"postgresql"}],"relational-theory":[{"n":8,"t":"database-design"},{"n":3,"t":"mysql"},{"n":4,"t":"normalization"},{"n":2,"t":"foreign-key"}],"relations":[{"n":2,"t":"database-design"}],"remote":[{"n":2,"t":"sql-server-2008"}],"replication":[{"n":26,"t":"mysql"},{"n":5,"t":"mysql-5.5"},{"n":3,"t":"mysql-5.1"},{"n":12,"t":"sql-server"},{"n":3,"t":"mysql-5"},{"n":4,"t":"mongodb"},{"n":10,"t":"postgresql"},{"n":5,"t":"sql-server-2008-r2"},{"n":3,"t":"sql-server-2005"},{"n":2,"t":"backup"},{"n":2,"t":"sql-server-2012"},{"n":2,"t":"merge-replication"},{"n":3,"t":"transactional-replication"}],"restore":[{"n":28,"t":"sql-server"},{"n":6,"t":"sql-server-2008"},{"n":22,"t":"backup"},{"n":3,"t":"migration"},{"n":7,"t":"postgresql"},{"n":2,"t":"snapshot"},{"n":4,"t":"mysql"},{"n":3,"t":"mysqldump"},{"n":4,"t":"sql-server-2008-r2"},{"n":5,"t":"sql-server-2012"},{"n":2,"t":"mongodb"},{"n":2,"t":"t-sql"},{"n":5,"t":"sql-server-2014"},{"n":2,"t":"ssms"}],"role":[{"n":5,"t":"sql-server"},{"n":5,"t":"permissions"},{"n":5,"t":"postgresql"}],"rollback":[{"n":2,"t":"ddl"},{"n":4,"t":"transaction"},{"n":3,"t":"sql-server"},{"n":2,"t":"mysql"}],"row":[{"n":2,"t":"sql-server"},{"n":2,"t":"postgresql"},{"n":2,"t":"json"}],"san":[{"n":2,"t":"sql-server-2008-r2"}],"scalability":[{"n":3,"t":"nosql"},{"n":3,"t":"sql-server"},{"n":4,"t":"performance"},{"n":2,"t":"mysql"},{"n":3,"t":"postgresql"},{"n":2,"t":"query-performance"}],"scheduled-tasks":[{"n":2,"t":"sql-server"}],"schema":[{"n":4,"t":"mysql"},{"n":11,"t":"postgresql"},{"n":12,"t":"database-design"},{"n":2,"t":"tools"},{"n":10,"t":"sql-server"},{"n":4,"t":"sql-server-2008"},{"n":2,"t":"metadata"},{"n":2,"t":"best-practices"},{"n":2,"t":"migration"},{"n":2,"t":"eav"},{"n":2,"t":"sql-server-2012"},{"n":2,"t":"permissions"},{"n":3,"t":"oracle"},{"n":2,"t":"ssdt"}],"scripting":[{"n":6,"t":"sql-server"},{"n":2,"t":"dynamic-sql"}],"security":[{"n":4,"t":"mysql"},{"n":3,"t":"postgresql"},{"n":3,"t":"sql-injection"},{"n":4,"t":"oracle"},{"n":2,"t":"oracle-11g-r2"},{"n":4,"t":"database-design"},{"n":38,"t":"sql-server"},{"n":10,"t":"sql-server-2008"},{"n":9,"t":"permissions"},{"n":6,"t":"logins"},{"n":6,"t":"sql-server-2012"},{"n":3,"t":"sql-server-2008-r2"},{"n":3,"t":"backup"},{"n":2,"t":"t-sql"},{"n":2,"t":"password"},{"n":2,"t":"best-practices"}],"select":[{"n":7,"t":"postgresql"},{"n":14,"t":"mysql"},{"n":5,"t":"join"},{"n":5,"t":"oracle"},{"n":5,"t":"performance"},{"n":2,"t":"subquery"},{"n":3,"t":"count"},{"n":2,"t":"auto-increment"},{"n":4,"t":"sql-server"},{"n":2,"t":"top"},{"n":2,"t":"query-performance"}],"sequence":[{"n":4,"t":"sql-server"},{"n":4,"t":"sql-server-2012"},{"n":5,"t":"postgresql"}],"service-broker":[{"n":7,"t":"sql-server"}],"set-returning-functions":[{"n":2,"t":"sql-server"}],"shrink":[{"n":10,"t":"sql-server"},{"n":2,"t":"dbcc"},{"n":3,"t":"transaction-log"}],"slow-log":[{"n":5,"t":"mysql"},{"n":5,"t":"performance"}],"snapshot":[{"n":2,"t":"restore"},{"n":4,"t":"sql-server"}],"snapshot-isolation":[{"n":3,"t":"sql-server"}],"sort-operator":[{"n":2,"t":"sql-server"}],"sorting":[{"n":4,"t":"sql-server"},{"n":2,"t":"natural-sort"},{"n":2,"t":"mysql"},{"n":2,"t":"index"},{"n":3,"t":"postgresql"}],"source-control":[{"n":2,"t":"sql-server-2008"},{"n":2,"t":"sql-server"},{"n":2,"t":"version-control"}],"spatial":[{"n":3,"t":"mysql"},{"n":2,"t":"postgis"},{"n":4,"t":"performance"},{"n":5,"t":"sql-server"},{"n":2,"t":"query-performance"}],"sql-clr":[{"n":8,"t":"sql-server"},{"n":2,"t":"sql-server-2008"},{"n":2,"t":"c#"}],"sql-injection":[{"n":2,"t":"postgresql"},{"n":3,"t":"security"},{"n":3,"t":"sql-server"},{"n":2,"t":"dynamic-sql"}],"sql-server":[{"n":167,"t":"performance"},{"n":79,"t":"index"},{"n":58,"t":"optimization"},{"n":225,"t":"sql-server-2008"},{"n":22,"t":"deadlock"},{"n":22,"t":"best-practices"},{"n":15,"t":"constraint"},{"n":8,"t":"unique-constraint"},{"n":5,"t":"data-pages"},{"n":22,"t":"clustered-index"},{"n":17,"t":"collation"},{"n":14,"t":"primary-key"},{"n":7,"t":"uniqueidentifier"},{"n":127,"t":"t-sql"},{"n":10,"t":"shrink"},{"n":36,"t":"stored-procedures"},{"n":13,"t":"insert"},{"n":8,"t":"sql-server-2000"},{"n":4,"t":"database-tuning"},{"n":43,"t":"database-design"},{"n":10,"t":"metadata"},{"n":3,"t":"documentation"},{"n":7,"t":"query"},{"n":8,"t":"windows"},{"n":18,"t":"memory"},{"n":90,"t":"sql-server-2005"},{"n":52,"t":"ssms"},{"n":7,"t":"profiler"},{"n":9,"t":"recovery"},{"n":8,"t":"dbcc-checkdb"},{"n":16,"t":"identity"},{"n":2,"t":"management"},{"n":13,"t":"migration"},{"n":5,"t":"filegroups"},{"n":2,"t":"disk-structures"},{"n":15,"t":"view"},{"n":17,"t":"xml"},{"n":23,"t":"functions"},{"n":194,"t":"sql-server-2012"},{"n":4,"t":"sequence"},{"n":8,"t":"delete"},{"n":51,"t":"backup"},{"n":28,"t":"restore"},{"n":38,"t":"permissions"},{"n":74,"t":"execution-plan"},{"n":177,"t":"sql-server-2008-r2"},{"n":3,"t":"logs"},{"n":2,"t":"web-server"},{"n":6,"t":"scripting"},{"n":13,"t":"alter-table"},{"n":15,"t":"configuration"},{"n":3,"t":"compatibility-level"},{"n":5,"t":"ado.net"},{"n":38,"t":"security"},{"n":5,"t":"role"},{"n":2,"t":"active-directory"},{"n":4,"t":"perfmon"},{"n":9,"t":"extended-events"},{"n":25,"t":"locking"},{"n":3,"t":"nolock"},{"n":9,"t":"mysql"},{"n":15,"t":"varchar"},{"n":2,"t":"tools"},{"n":5,"t":"powershell"},{"n":4,"t":"sorting"},{"n":9,"t":"ddl"},{"n":2,"t":"default-value"},{"n":5,"t":"export"},{"n":3,"t":"order-by"},{"n":10,"t":"schema"},{"n":7,"t":"truncate"},{"n":16,"t":"transaction"},{"n":5,"t":"audit"},{"n":8,"t":"syntax"},{"n":5,"t":"index-maintenance"},{"n":74,"t":"query-performance"},{"n":11,"t":"maintenance"},{"n":12,"t":"partitioning"},{"n":5,"t":"heap"},{"n":3,"t":"monitoring"},{"n":2,"t":"testing"},{"n":5,"t":"performance-testing"},{"n":2,"t":"database-theory"},{"n":2,"t":"bcp"},{"n":21,"t":"join"},{"n":2,"t":"condition"},{"n":7,"t":"sqlcmd"},{"n":22,"t":"index-tuning"},{"n":6,"t":"aggregate"},{"n":11,"t":"materialized-view"},{"n":3,"t":"scalability"},{"n":12,"t":"replication"},{"n":2,"t":"intellisense"},{"n":9,"t":"errors"},{"n":2,"t":"terminology"},{"n":5,"t":"filtered-index"},{"n":8,"t":"ssrs"},{"n":16,"t":"datatypes"},{"n":7,"t":"type-conversion"},{"n":18,"t":"trigger"},{"n":7,"t":"encoding"},{"n":16,"t":"ssis"},{"n":11,"t":"azure-sql-database"},{"n":14,"t":"sql-server-agent"},{"n":4,"t":"full-text-search"},{"n":6,"t":"sql-server-express"},{"n":6,"t":"fragmentation"},{"n":2,"t":"surrogate-key"},{"n":3,"t":"version-control"},{"n":5,"t":"index-statistics"},{"n":7,"t":"recursive"},{"n":7,"t":"except"},{"n":7,"t":"oracle"},{"n":29,"t":"transaction-log"},{"n":6,"t":"mirroring"},{"n":11,"t":"columnstore"},{"n":10,"t":"linked-server"},{"n":2,"t":"dbcc"},{"n":8,"t":"sql-clr"},{"n":2,"t":"source-control"},{"n":3,"t":"architecture"},{"n":6,"t":"wait-types"},{"n":7,"t":"dynamic-sql"},{"n":4,"t":"c#"},{"n":31,"t":"statistics"},{"n":6,"t":"concurrency"},{"n":5,"t":"isolation-level"},{"n":11,"t":"null"},{"n":11,"t":"cte"},{"n":2,"t":"buffer-pool"},{"n":8,"t":"temporary-tables"},{"n":18,"t":"tempdb"},{"n":5,"t":"ssas"},{"n":9,"t":"window-functions"},{"n":3,"t":"date-format"},{"n":4,"t":"subquery"},{"n":2,"t":"alias"},{"n":4,"t":"etl"},{"n":7,"t":"disk-space"},{"n":4,"t":"hierarchy"},{"n":2,"t":"maintenance-plans"},{"n":6,"t":"datetime"},{"n":7,"t":"service-broker"},{"n":3,"t":"filestream"},{"n":32,"t":"database-internals"},{"n":3,"t":"log-shipping"},{"n":7,"t":"merge"},{"n":5,"t":"pivot"},{"n":9,"t":"parallelism"},{"n":13,"t":"dmv"},{"n":2,"t":"feature-comparison"},{"n":4,"t":"high-availability"},{"n":9,"t":"postgresql"},{"n":2,"t":"database-size"},{"n":4,"t":"jobs"},{"n":7,"t":"encryption"},{"n":4,"t":"transparent-data-encryption"},{"n":6,"t":"group-by"},{"n":20,"t":"availability-groups"},{"n":3,"t":"import"},{"n":5,"t":"troubleshooting"},{"n":10,"t":"update"},{"n":2,"t":"output-clause"},{"n":3,"t":"sql-injection"},{"n":2,"t":"database-recommendation"},{"n":4,"t":"network"},{"n":3,"t":"rollback"},{"n":4,"t":"snapshot"},{"n":2,"t":"information-schema"},{"n":5,"t":"corruption"},{"n":2,"t":"sqlite"},{"n":3,"t":"timezone"},{"n":5,"t":"upgrade"},{"n":9,"t":"logins"},{"n":2,"t":"instance"},{"n":4,"t":"merge-replication"},{"n":2,"t":"recovery-model"},{"n":3,"t":"sql-server-localdb"},{"n":5,"t":"data-warehouse"},{"n":2,"t":"table-valued-parameters"},{"n":4,"t":"windows-server"},{"n":2,"t":"scheduled-tasks"},{"n":11,"t":"foreign-key"},{"n":2,"t":"row"},{"n":8,"t":"hardware"},{"n":19,"t":"cardinality-estimates"},{"n":2,"t":"warning"},{"n":2,"t":"users"},{"n":2,"t":"hashing"},{"n":4,"t":"cache"},{"n":2,"t":"error-handling"},{"n":2,"t":"maxdop"},{"n":7,"t":"compression"},{"n":8,"t":"ssdt"},{"n":4,"t":"system-tables"},{"n":2,"t":"decimal"},{"n":2,"t":"failover"},{"n":3,"t":"clustering"},{"n":3,"t":"auto-increment"},{"n":6,"t":"bulk-insert"},{"n":6,"t":"authentication"},{"n":3,"t":"kerberos"},{"n":2,"t":"alter-database"},{"n":4,"t":"database-mail"},{"n":2,"t":"dynamic-ports"},{"n":6,"t":"connectivity"},{"n":3,"t":"ssis-2012"},{"n":3,"t":"date"},{"n":2,"t":"datetime2"},{"n":11,"t":"computed-column"},{"n":3,"t":"bookmark-lookup"},{"n":5,"t":"transactional-replication"},{"n":2,"t":"unpivot"},{"n":5,"t":"spatial"},{"n":3,"t":"snapshot-isolation"},{"n":2,"t":"crash"},{"n":105,"t":"sql-server-2014"},{"n":3,"t":"password"},{"n":2,"t":"change-data-capture"},{"n":2,"t":"data-synchronization"},{"n":4,"t":"select"},{"n":9,"t":"installation"},{"n":2,"t":"cross-apply"},{"n":3,"t":"memory-optimized-tables"},{"n":4,"t":"ssl"},{"n":4,"t":"blob"},{"n":2,"t":"table"},{"n":3,"t":"operator"},{"n":11,"t":"unicode"},{"n":2,"t":"memory-grant"},{"n":4,"t":"greatest-n-per-group"},{"n":2,"t":"paging"},{"n":5,"t":"plan-cache"},{"n":2,"t":"upsert"},{"n":10,"t":"performance-tuning"},{"n":6,"t":"nonclustered-index"},{"n":3,"t":"batch-mode"},{"n":2,"t":"multi-tenant"},{"n":4,"t":"blocking"},{"n":2,"t":"cursors"},{"n":2,"t":"microsoft-dynamics"},{"n":69,"t":"sql-server-2016"},{"n":4,"t":"gaps-and-islands"},{"n":3,"t":"xquery"},{"n":4,"t":"connections"},{"n":3,"t":"string"},{"n":2,"t":"ssis-2014"},{"n":3,"t":"parameter"},{"n":4,"t":"exists"},{"n":3,"t":"uuid"},{"n":2,"t":"concat"},{"n":3,"t":"ola-hallengren"},{"n":2,"t":"max"},{"n":2,"t":"set-returning-functions"},{"n":4,"t":"vmware"},{"n":2,"t":"archive"},{"n":2,"t":"trace-flags"},{"n":2,"t":"limits"},{"n":2,"t":"sort-operator"},{"n":2,"t":"certificate"},{"n":2,"t":"master-system-database"},{"n":4,"t":"storage"},{"n":5,"t":"query-store"},{"n":4,"t":"like"},{"n":4,"t":"linux"},{"n":2,"t":"ubuntu"},{"n":34,"t":"sql-server-2017"},{"n":2,"t":"utf-8"},{"n":2,"t":"azure-vm"},{"n":2,"t":"top"},{"n":2,"t":"amazon-rds"},{"n":2,"t":"check-constraints"},{"n":2,"t":"character-set"},{"n":2,"t":"distributed-availability-groups"},{"n":8,"t":"sql-server-2019"},{"n":2,"t":"access-control"}],"sql-server-2000":[{"n":8,"t":"sql-server"},{"n":3,"t":"migration"},{"n":2,"t":"sql-server-2005"},{"n":2,"t":"sql-server-2012"},{"n":2,"t":"sql-server-2008"}],"sql-server-2005":[{"n":26,"t":"sql-server-2008"},{"n":2,"t":"ssms"},{"n":90,"t":"sql-server"},{"n":2,"t":"primary-key"},{"n":4,"t":"index"},{"n":2,"t":"clustered-index"},{"n":3,"t":"identity"},{"n":18,"t":"performance"},{"n":5,"t":"stored-procedures"},{"n":2,"t":"best-practices"},{"n":2,"t":"maintenance"},{"n":5,"t":"backup"},{"n":2,"t":"partitioning"},{"n":2,"t":"dbcc"},{"n":2,"t":"collation"},{"n":5,"t":"query-performance"},{"n":2,"t":"permissions"},{"n":2,"t":"aggregate"},{"n":2,"t":"configuration"},{"n":2,"t":"etl"},{"n":3,"t":"transaction-log"},{"n":3,"t":"tempdb"},{"n":2,"t":"sql-server-2000"},{"n":4,"t":"t-sql"},{"n":3,"t":"mirroring"},{"n":3,"t":"sql-server-2008-r2"},{"n":3,"t":"replication"},{"n":2,"t":"dmv"},{"n":2,"t":"merge-replication"},{"n":2,"t":"linked-server"},{"n":2,"t":"insert"}],"sql-server-2008":[{"n":26,"t":"sql-server-2005"},{"n":2,"t":"source-control"},{"n":225,"t":"sql-server"},{"n":6,"t":"deadlock"},{"n":3,"t":"best-practices"},{"n":11,"t":"backup"},{"n":5,"t":"maintenance"},{"n":4,"t":"collation"},{"n":5,"t":"trigger"},{"n":16,"t":"database-design"},{"n":2,"t":"metadata"},{"n":3,"t":"profiler"},{"n":20,"t":"performance"},{"n":2,"t":"recovery"},{"n":2,"t":"migration"},{"n":2,"t":"query"},{"n":3,"t":"xml"},{"n":6,"t":"datatypes"},{"n":3,"t":"corruption"},{"n":6,"t":"restore"},{"n":9,"t":"permissions"},{"n":4,"t":"view"},{"n":2,"t":"mirroring"},{"n":10,"t":"security"},{"n":2,"t":"active-directory"},{"n":2,"t":"tools"},{"n":2,"t":"windows"},{"n":4,"t":"memory"},{"n":2,"t":"powershell"},{"n":3,"t":"ddl"},{"n":2,"t":"default-value"},{"n":4,"t":"schema"},{"n":7,"t":"stored-procedures"},{"n":3,"t":"transaction"},{"n":4,"t":"partitioning"},{"n":17,"t":"t-sql"},{"n":3,"t":"optimization"},{"n":22,"t":"sql-server-2008-r2"},{"n":11,"t":"index"},{"n":2,"t":"fragmentation"},{"n":3,"t":"disk-space"},{"n":2,"t":"aggregate"},{"n":2,"t":"materialized-view"},{"n":2,"t":"type-conversion"},{"n":10,"t":"ssms"},{"n":5,"t":"sql-server-agent"},{"n":9,"t":"execution-plan"},{"n":2,"t":"except"},{"n":2,"t":"query-performance"},{"n":4,"t":"transaction-log"},{"n":2,"t":"sql-clr"},{"n":3,"t":"varchar"},{"n":14,"t":"sql-server-2012"},{"n":2,"t":"c#"},{"n":3,"t":"index-tuning"},{"n":2,"t":"tempdb"},{"n":3,"t":"null"},{"n":4,"t":"database-internals"},{"n":2,"t":"alter-table"},{"n":2,"t":"window-functions"},{"n":3,"t":"statistics"},{"n":2,"t":"remote"},{"n":2,"t":"hierarchy"},{"n":2,"t":"datetime"},{"n":2,"t":"pivot"},{"n":2,"t":"parallelism"},{"n":2,"t":"group-by"},{"n":2,"t":"update"},{"n":2,"t":"logins"},{"n":2,"t":"locking"},{"n":2,"t":"sql-server-2000"},{"n":2,"t":"linked-server"},{"n":5,"t":"sql-server-2014"}],"sql-server-2008-r2":[{"n":177,"t":"sql-server"},{"n":5,"t":"execution-plan"},{"n":5,"t":"ssms"},{"n":6,"t":"backup"},{"n":3,"t":"locking"},{"n":3,"t":"alter-table"},{"n":22,"t":"sql-server-2008"},{"n":4,"t":"database-design"},{"n":3,"t":"memory"},{"n":6,"t":"permissions"},{"n":14,"t":"performance"},{"n":2,"t":"trigger"},{"n":2,"t":"delete"},{"n":4,"t":"stored-procedures"},{"n":5,"t":"optimization"},{"n":2,"t":"ssis"},{"n":2,"t":"full-text-search"},{"n":2,"t":"sql-server-express"},{"n":3,"t":"recovery"},{"n":2,"t":"linked-server"},{"n":4,"t":"except"},{"n":2,"t":"network"},{"n":2,"t":"san"},{"n":12,"t":"index"},{"n":4,"t":"restore"},{"n":5,"t":"replication"},{"n":5,"t":"partitioning"},{"n":11,"t":"sql-server-2012"},{"n":7,"t":"transaction-log"},{"n":2,"t":"hierarchy"},{"n":9,"t":"t-sql"},{"n":3,"t":"functions"},{"n":3,"t":"statistics"},{"n":8,"t":"query-performance"},{"n":2,"t":"tempdb"},{"n":2,"t":"sql-server-agent"},{"n":3,"t":"deadlock"},{"n":3,"t":"sql-server-2005"},{"n":2,"t":"information-schema"},{"n":2,"t":"filtered-index"},{"n":2,"t":"jobs"},{"n":2,"t":"disk-space"},{"n":2,"t":"errors"},{"n":3,"t":"hardware"},{"n":2,"t":"sqlcmd"},{"n":2,"t":"ssrs"},{"n":2,"t":"index-statistics"},{"n":2,"t":"index-tuning"},{"n":2,"t":"encryption"},{"n":2,"t":"dmv"},{"n":3,"t":"security"},{"n":4,"t":"sql-server-2014"},{"n":3,"t":"database-internals"},{"n":2,"t":"installation"},{"n":3,"t":"xml"},{"n":3,"t":"gaps-and-islands"},{"n":2,"t":"collation"},{"n":2,"t":"unicode"},{"n":2,"t":"performance-tuning"},{"n":2,"t":"identity"}],"sql-server-2012":[{"n":194,"t":"sql-server"},{"n":4,"t":"sequence"},{"n":12,"t":"index"},{"n":2,"t":"columnstore"},{"n":14,"t":"sql-server-2008"},{"n":11,"t":"sql-server-2008-r2"},{"n":7,"t":"database-design"},{"n":15,"t":"ssms"},{"n":5,"t":"availability-groups"},{"n":2,"t":"schema"},{"n":2,"t":"high-availability"},{"n":18,"t":"t-sql"},{"n":2,"t":"sql-server-2000"},{"n":4,"t":"stored-procedures"},{"n":2,"t":"trigger"},{"n":19,"t":"performance"},{"n":2,"t":"delete"},{"n":3,"t":"truncate"},{"n":2,"t":"migration"},{"n":2,"t":"profiler"},{"n":2,"t":"logins"},{"n":14,"t":"execution-plan"},{"n":7,"t":"optimization"},{"n":4,"t":"xml"},{"n":4,"t":"database-internals"},{"n":2,"t":"replication"},{"n":2,"t":"memory"},{"n":4,"t":"cardinality-estimates"},{"n":6,"t":"security"},{"n":3,"t":"ssis"},{"n":2,"t":"data-warehouse"},{"n":2,"t":"tempdb"},{"n":2,"t":"wait-types"},{"n":8,"t":"backup"},{"n":3,"t":"transaction-log"},{"n":2,"t":"window-functions"},{"n":5,"t":"restore"},{"n":2,"t":"index-tuning"},{"n":5,"t":"statistics"},{"n":2,"t":"datetime"},{"n":3,"t":"join"},{"n":2,"t":"syntax"},{"n":6,"t":"permissions"},{"n":2,"t":"deadlock"},{"n":10,"t":"query-performance"},{"n":3,"t":"installation"},{"n":3,"t":"insert"},{"n":3,"t":"locking"},{"n":2,"t":"change-tracking"},{"n":2,"t":"varchar"},{"n":2,"t":"authentication"},{"n":3,"t":"dmv"},{"n":2,"t":"audit"},{"n":2,"t":"functions"},{"n":5,"t":"sql-server-2014"},{"n":2,"t":"nonclustered-index"},{"n":2,"t":"connectivity"},{"n":2,"t":"identity"},{"n":3,"t":"computed-column"},{"n":2,"t":"errors"},{"n":2,"t":"plan-cache"},{"n":3,"t":"transaction"},{"n":2,"t":"date"},{"n":2,"t":"linked-server"},{"n":2,"t":"connections"},{"n":2,"t":"troubleshooting"}],"sql-server-2014":[{"n":105,"t":"sql-server"},{"n":4,"t":"sql-server-2008-r2"},{"n":3,"t":"index"},{"n":2,"t":"memory-optimized-tables"},{"n":3,"t":"partitioning"},{"n":5,"t":"ssis"},{"n":3,"t":"compression"},{"n":3,"t":"foreign-key"},{"n":4,"t":"columnstore"},{"n":3,"t":"linked-server"},{"n":5,"t":"sql-server-2012"},{"n":2,"t":"database-internals"},{"n":4,"t":"transaction-log"},{"n":2,"t":"batch-mode"},{"n":3,"t":"ssms"},{"n":4,"t":"availability-groups"},{"n":10,"t":"t-sql"},{"n":3,"t":"statistics"},{"n":2,"t":"bulk-insert"},{"n":4,"t":"backup"},{"n":5,"t":"restore"},{"n":2,"t":"computed-column"},{"n":11,"t":"performance"},{"n":2,"t":"insert"},{"n":2,"t":"functions"},{"n":7,"t":"cardinality-estimates"},{"n":10,"t":"query-performance"},{"n":2,"t":"connectivity"},{"n":2,"t":"ssis-2014"},{"n":2,"t":"permissions"},{"n":2,"t":"sql-server-2016"},{"n":2,"t":"tempdb"},{"n":5,"t":"optimization"},{"n":2,"t":"index-tuning"},{"n":2,"t":"identity"},{"n":2,"t":"memory"},{"n":2,"t":"join"},{"n":2,"t":"ssrs"},{"n":2,"t":"merge"},{"n":4,"t":"execution-plan"},{"n":5,"t":"sql-server-2008"},{"n":2,"t":"database-design"},{"n":2,"t":"constraint"},{"n":2,"t":"query"}],"sql-server-2016":[{"n":69,"t":"sql-server"},{"n":2,"t":"sql-server-2014"},{"n":4,"t":"columnstore"},{"n":2,"t":"availability-groups"},{"n":2,"t":"upgrade"},{"n":5,"t":"execution-plan"},{"n":5,"t":"optimization"},{"n":4,"t":"cardinality-estimates"},{"n":2,"t":"database-design"},{"n":10,"t":"performance"},{"n":2,"t":"window-functions"},{"n":7,"t":"query-performance"},{"n":2,"t":"database-internals"},{"n":2,"t":"authentication"},{"n":4,"t":"query-store"},{"n":2,"t":"statistics"},{"n":2,"t":"foreign-key"},{"n":2,"t":"like"},{"n":3,"t":"extended-events"},{"n":3,"t":"memory"},{"n":2,"t":"index"},{"n":2,"t":"tempdb"},{"n":2,"t":"temporary-tables"}],"sql-server-2017":[{"n":3,"t":"ubuntu"},{"n":34,"t":"sql-server"},{"n":2,"t":"linux"},{"n":2,"t":"installation"},{"n":2,"t":"aggregate"},{"n":2,"t":"availability-groups"},{"n":2,"t":"distributed-availability-groups"},{"n":3,"t":"database-internals"},{"n":3,"t":"execution-plan"},{"n":3,"t":"cardinality-estimates"},{"n":2,"t":"performance"},{"n":2,"t":"backup"},{"n":2,"t":"alter-table"},{"n":2,"t":"storage"}],"sql-server-2019":[{"n":8,"t":"sql-server"},{"n":3,"t":"functions"}],"sql-server-agent":[{"n":14,"t":"sql-server"},{"n":5,"t":"sql-server-2008"},{"n":2,"t":"sql-server-2008-r2"},{"n":2,"t":"permissions"}],"sql-server-express":[{"n":6,"t":"sql-server"},{"n":2,"t":"sql-server-2008-r2"},{"n":2,"t":"ssms"},{"n":2,"t":"memory"}],"sql-server-localdb":[{"n":3,"t":"sql-server"}],"sql-standard":[{"n":3,"t":"postgresql"},{"n":2,"t":"aggregate"}],"sqlcmd":[{"n":2,"t":"ssms"},{"n":7,"t":"sql-server"},{"n":2,"t":"sql-server-2008-r2"}],"sqlite":[{"n":3,"t":"postgresql"},{"n":2,"t":"sql-server"},{"n":2,"t":"mysql"}],"sqlplus":[{"n":12,"t":"oracle"},{"n":3,"t":"oracle-11g-r2"}],"ssas":[{"n":5,"t":"sql-server"},{"n":2,"t":"business-intelligence"}],"ssdt":[{"n":8,"t":"sql-server"},{"n":2,"t":"schema"},{"n":2,"t":"deployment"}],"ssis":[{"n":16,"t":"sql-server"},{"n":2,"t":"sql-server-2008-r2"},{"n":3,"t":"sql-server-2012"},{"n":3,"t":"permissions"},{"n":3,"t":"ssis-2012"},{"n":5,"t":"sql-server-2014"},{"n":2,"t":"ssis-2014"}],"ssis-2012":[{"n":3,"t":"sql-server"},{"n":3,"t":"ssis"}],"ssis-2014":[{"n":2,"t":"sql-server"},{"n":2,"t":"sql-server-2014"},{"n":2,"t":"ssis"}],"ssl":[{"n":2,"t":"mysql"},{"n":4,"t":"sql-server"},{"n":2,"t":"encryption"}],"ssms":[{"n":2,"t":"sql-server-2005"},{"n":2,"t":"sqlcmd"},{"n":52,"t":"sql-server"},{"n":5,"t":"sql-server-2008-r2"},{"n":10,"t":"sql-server-2008"},{"n":2,"t":"tools"},{"n":15,"t":"sql-server-2012"},{"n":3,"t":"t-sql"},{"n":2,"t":"configuration"},{"n":2,"t":"stored-procedures"},{"n":2,"t":"permissions"},{"n":2,"t":"sql-server-express"},{"n":2,"t":"execution-plan"},{"n":2,"t":"installation"},{"n":3,"t":"sql-server-2014"},{"n":2,"t":"connectivity"},{"n":2,"t":"restore"}],"ssrs":[{"n":8,"t":"sql-server"},{"n":2,"t":"sql-server-2008-r2"},{"n":2,"t":"sql-server-2014"}],"startup":[{"n":2,"t":"oracle"},{"n":2,"t":"mysql"}],"statistics":[{"n":31,"t":"sql-server"},{"n":4,"t":"index"},{"n":2,"t":"maintenance"},{"n":3,"t":"sql-server-2008"},{"n":2,"t":"performance"},{"n":3,"t":"sql-server-2008-r2"},{"n":2,"t":"database-internals"},{"n":5,"t":"sql-server-2012"},{"n":3,"t":"index-statistics"},{"n":4,"t":"execution-plan"},{"n":3,"t":"sql-server-2014"},{"n":2,"t":"cardinality-estimates"},{"n":2,"t":"sql-server-2016"},{"n":2,"t":"query-store"}],"storage":[{"n":2,"t":"architecture"},{"n":5,"t":"postgresql"},{"n":3,"t":"performance"},{"n":4,"t":"sql-server"},{"n":2,"t":"sql-server-2017"}],"storage-engine":[{"n":4,"t":"mysql"},{"n":2,"t":"innodb"},{"n":2,"t":"myisam"}],"stored-procedures":[{"n":3,"t":"oracle"},{"n":12,"t":"mysql"},{"n":6,"t":"trigger"},{"n":36,"t":"sql-server"},{"n":5,"t":"sql-server-2005"},{"n":2,"t":"best-practices"},{"n":4,"t":"postgresql"},{"n":3,"t":"plpgsql"},{"n":2,"t":"backup"},{"n":2,"t":"mysqldump"},{"n":7,"t":"sql-server-2008"},{"n":5,"t":"performance"},{"n":2,"t":"datatypes"},{"n":4,"t":"parameter"},{"n":4,"t":"sql-server-2008-r2"},{"n":2,"t":"optimization"},{"n":11,"t":"t-sql"},{"n":2,"t":"query-performance"},{"n":2,"t":"functions"},{"n":2,"t":"ssms"},{"n":4,"t":"sql-server-2012"},{"n":3,"t":"temporary-tables"},{"n":2,"t":"transaction"},{"n":2,"t":"xml"},{"n":2,"t":"dmv"}],"string":[{"n":3,"t":"sql-server"}],"subquery":[{"n":4,"t":"sql-server"},{"n":2,"t":"alias"},{"n":2,"t":"performance"},{"n":2,"t":"select"},{"n":2,"t":"postgresql"}],"subtypes":[{"n":7,"t":"database-design"},{"n":2,"t":"mysql"}],"surrogate-key":[{"n":2,"t":"database-design"},{"n":2,"t":"primary-key"},{"n":2,"t":"sql-server"},{"n":2,"t":"natural-key"}],"syntax":[{"n":3,"t":"oracle"},{"n":3,"t":"join"},{"n":8,"t":"sql-server"},{"n":2,"t":"mysql"},{"n":2,"t":"t-sql"},{"n":2,"t":"sql-server-2012"},{"n":2,"t":"postgresql"}],"system-tables":[{"n":4,"t":"sql-server"}],"t-sql":[{"n":127,"t":"sql-server"},{"n":2,"t":"ado.net"},{"n":17,"t":"sql-server-2008"},{"n":4,"t":"optimization"},{"n":4,"t":"datatypes"},{"n":4,"t":"type-conversion"},{"n":11,"t":"stored-procedures"},{"n":2,"t":"parameter"},{"n":4,"t":"window-functions"},{"n":2,"t":"temporary-tables"},{"n":3,"t":"datetime"},{"n":9,"t":"sql-server-2008-r2"},{"n":4,"t":"functions"},{"n":3,"t":"jobs"},{"n":4,"t":"trigger"},{"n":4,"t":"sql-server-2005"},{"n":18,"t":"sql-server-2012"},{"n":3,"t":"ssms"},{"n":3,"t":"cte"},{"n":2,"t":"syntax"},{"n":5,"t":"transaction"},{"n":2,"t":"execution-plan"},{"n":2,"t":"merge"},{"n":2,"t":"null"},{"n":7,"t":"performance"},{"n":2,"t":"best-practices"},{"n":4,"t":"join"},{"n":2,"t":"dynamic-sql"},{"n":2,"t":"permissions"},{"n":3,"t":"database-design"},{"n":2,"t":"restore"},{"n":2,"t":"errors"},{"n":2,"t":"xml"},{"n":2,"t":"security"},{"n":2,"t":"ddl"},{"n":10,"t":"sql-server-2014"},{"n":2,"t":"index"},{"n":3,"t":"query-performance"},{"n":2,"t":"performance-tuning"},{"n":3,"t":"collation"},{"n":3,"t":"unicode"}],"table":[{"n":2,"t":"mysql"},{"n":2,"t":"sql-server"},{"n":2,"t":"postgresql"}],"table-valued-parameters":[{"n":2,"t":"sql-server"}],"tablespaces":[{"n":2,"t":"oracle"},{"n":2,"t":"postgresql"},{"n":2,"t":"permissions"}],"tempdb":[{"n":18,"t":"sql-server"},{"n":2,"t":"sql-server-2008"},{"n":3,"t":"sql-server-2005"},{"n":2,"t":"transaction-log"},{"n":2,"t":"sql-server-2008-r2"},{"n":2,"t":"performance"},{"n":2,"t":"sql-server-2012"},{"n":2,"t":"sql-server-2014"},{"n":2,"t":"temporary-tables"},{"n":2,"t":"sql-server-2016"},{"n":2,"t":"memory"}],"temporary-tables":[{"n":3,"t":"mysql"},{"n":8,"t":"sql-server"},{"n":3,"t":"performance"},{"n":2,"t":"t-sql"},{"n":3,"t":"stored-procedures"},{"n":2,"t":"memory"},{"n":2,"t":"tempdb"},{"n":2,"t":"sql-server-2016"}],"terminology":[{"n":2,"t":"sql-server"},{"n":2,"t":"database-theory"},{"n":2,"t":"postgresql"}],"testing":[{"n":2,"t":"mysql"},{"n":2,"t":"sql-server"},{"n":2,"t":"performance"},{"n":2,"t":"performance-testing"},{"n":2,"t":"postgresql"}],"timestamp":[{"n":10,"t":"postgresql"},{"n":2,"t":"utc-time"},{"n":5,"t":"timezone"},{"n":2,"t":"date"}],"timezone":[{"n":3,"t":"sql-server"},{"n":2,"t":"utc-time"},{"n":5,"t":"postgresql"},{"n":5,"t":"timestamp"},{"n":2,"t":"datetime"}],"tools":[{"n":2,"t":"oracle"},{"n":4,"t":"mysql"},{"n":4,"t":"postgresql"},{"n":2,"t":"database-design"},{"n":2,"t":"schema"},{"n":2,"t":"migration"},{"n":2,"t":"sql-server"},{"n":2,"t":"sql-server-2008"},{"n":2,"t":"ssms"}],"top":[{"n":2,"t":"sql-server"},{"n":2,"t":"performance"},{"n":2,"t":"select"},{"n":2,"t":"query-performance"}],"trace-flags":[{"n":2,"t":"sql-server"}],"transaction":[{"n":2,"t":"oracle"},{"n":16,"t":"sql-server"},{"n":3,"t":"sql-server-2008"},{"n":2,"t":"ddl"},{"n":2,"t":"performance"},{"n":4,"t":"rollback"},{"n":2,"t":"ado.net"},{"n":3,"t":"locking"},{"n":8,"t":"mysql"},{"n":9,"t":"postgresql"},{"n":4,"t":"innodb"},{"n":5,"t":"t-sql"},{"n":3,"t":"trigger"},{"n":2,"t":"stored-procedures"},{"n":2,"t":"unique-constraint"},{"n":3,"t":"sql-server-2012"},{"n":2,"t":"index"}],"transaction-log":[{"n":29,"t":"sql-server"},{"n":4,"t":"sql-server-2008"},{"n":7,"t":"sql-server-2008-r2"},{"n":3,"t":"sql-server-2005"},{"n":2,"t":"tempdb"},{"n":2,"t":"alter-table"},{"n":3,"t":"shrink"},{"n":2,"t":"recovery-model"},{"n":5,"t":"backup"},{"n":3,"t":"sql-server-2012"},{"n":2,"t":"performance"},{"n":4,"t":"sql-server-2014"}],"transactional-replication":[{"n":5,"t":"sql-server"},{"n":3,"t":"replication"}],"transparent-data-encryption":[{"n":4,"t":"sql-server"},{"n":2,"t":"encryption"}],"trigger":[{"n":8,"t":"postgresql"},{"n":2,"t":"plpgsql"},{"n":6,"t":"mysql"},{"n":6,"t":"stored-procedures"},{"n":5,"t":"sql-server-2008"},{"n":2,"t":"backup"},{"n":2,"t":"delete"},{"n":3,"t":"performance"},{"n":2,"t":"oracle"},{"n":18,"t":"sql-server"},{"n":2,"t":"sql-server-2008-r2"},{"n":3,"t":"update"},{"n":4,"t":"t-sql"},{"n":2,"t":"sql-server-2012"},{"n":3,"t":"transaction"},{"n":2,"t":"permissions"}],"troubleshooting":[{"n":5,"t":"sql-server"},{"n":2,"t":"sql-server-2012"}],"truncate":[{"n":2,"t":"postgresql"},{"n":2,"t":"disk-space"},{"n":7,"t":"sql-server"},{"n":3,"t":"sql-server-2012"},{"n":2,"t":"delete"}],"tuning":[{"n":2,"t":"mysql"},{"n":2,"t":"performance"}],"type-conversion":[{"n":2,"t":"postgresql"},{"n":4,"t":"datatypes"},{"n":7,"t":"sql-server"},{"n":2,"t":"sql-server-2008"},{"n":4,"t":"t-sql"},{"n":2,"t":"execution-plan"},{"n":2,"t":"cardinality-estimates"}],"ubuntu":[{"n":7,"t":"postgresql"},{"n":5,"t":"linux"},{"n":2,"t":"memory"},{"n":2,"t":"pgadmin"},{"n":2,"t":"oracle"},{"n":2,"t":"installation"},{"n":3,"t":"sql-server-2017"},{"n":2,"t":"sql-server"}],"unicode":[{"n":11,"t":"sql-server"},{"n":5,"t":"collation"},{"n":3,"t":"encoding"},{"n":2,"t":"sql-server-2008-r2"},{"n":3,"t":"t-sql"},{"n":3,"t":"datatypes"},{"n":2,"t":"utf-8"}],"unique-constraint":[{"n":8,"t":"sql-server"},{"n":5,"t":"index"},{"n":7,"t":"constraint"},{"n":10,"t":"postgresql"},{"n":3,"t":"null"},{"n":5,"t":"primary-key"},{"n":3,"t":"database-design"},{"n":2,"t":"transaction"},{"n":2,"t":"update"}],"uniqueidentifier":[{"n":2,"t":"performance"},{"n":7,"t":"sql-server"},{"n":3,"t":"primary-key"},{"n":2,"t":"mysql"},{"n":2,"t":"postgresql"},{"n":2,"t":"database-design"},{"n":2,"t":"datatypes"}],"unpivot":[{"n":2,"t":"sql-server"}],"update":[{"n":7,"t":"mysql"},{"n":3,"t":"trigger"},{"n":13,"t":"postgresql"},{"n":9,"t":"performance"},{"n":10,"t":"sql-server"},{"n":2,"t":"sql-server-2008"},{"n":2,"t":"join"},{"n":2,"t":"concurrency"},{"n":2,"t":"query-performance"},{"n":2,"t":"unique-constraint"},{"n":2,"t":"index"}],"upgrade":[{"n":5,"t":"sql-server"},{"n":3,"t":"postgresql"},{"n":2,"t":"availability-groups"},{"n":2,"t":"sql-server-2016"}],"upsert":[{"n":7,"t":"postgresql"},{"n":2,"t":"plpgsql"},{"n":2,"t":"sql-server"},{"n":3,"t":"postgresql-9.5"}],"users":[{"n":2,"t":"mysql"},{"n":2,"t":"sql-server"},{"n":2,"t":"postgresql"}],"utc-time":[{"n":2,"t":"timestamp"},{"n":2,"t":"timezone"}],"utf-8":[{"n":3,"t":"mysql"},{"n":2,"t":"collation"},{"n":2,"t":"unicode"},{"n":2,"t":"sql-server"}],"uuid":[{"n":5,"t":"postgresql"},{"n":2,"t":"index"},{"n":3,"t":"sql-server"}],"vacuum":[{"n":13,"t":"postgresql"},{"n":2,"t":"delete"},{"n":2,"t":"performance"},{"n":3,"t":"maintenance"},{"n":2,"t":"postgresql-9.1"}],"varchar":[{"n":4,"t":"mysql"},{"n":8,"t":"performance"},{"n":3,"t":"datatypes"},{"n":15,"t":"sql-server"},{"n":3,"t":"sql-server-2008"},{"n":5,"t":"postgresql"},{"n":2,"t":"index"},{"n":2,"t":"sql-server-2012"},{"n":3,"t":"database-design"}],"version-control":[{"n":3,"t":"sql-server"},{"n":2,"t":"source-control"}],"view":[{"n":15,"t":"sql-server"},{"n":2,"t":"index"},{"n":3,"t":"optimization"},{"n":4,"t":"sql-server-2008"},{"n":5,"t":"performance"},{"n":4,"t":"mysql"},{"n":2,"t":"query-performance"},{"n":6,"t":"postgresql"},{"n":3,"t":"materialized-view"},{"n":2,"t":"computed-column"},{"n":2,"t":"permissions"}],"vmware":[{"n":4,"t":"sql-server"},{"n":3,"t":"performance"}],"wait-types":[{"n":6,"t":"sql-server"},{"n":2,"t":"sql-server-2012"},{"n":3,"t":"performance"}],"warning":[{"n":2,"t":"sql-server"},{"n":2,"t":"execution-plan"}],"web-server":[{"n":2,"t":"sql-server"}],"window-functions":[{"n":9,"t":"sql-server"},{"n":2,"t":"sql-server-2008"},{"n":4,"t":"t-sql"},{"n":6,"t":"postgresql"},{"n":3,"t":"gaps-and-islands"},{"n":2,"t":"group-by"},{"n":2,"t":"sql-server-2012"},{"n":2,"t":"aggregate"},{"n":2,"t":"join"},{"n":2,"t":"performance"},{"n":2,"t":"query-performance"},{"n":2,"t":"sql-server-2016"}],"windows":[{"n":8,"t":"sql-server"},{"n":2,"t":"memory"},{"n":8,"t":"mysql"},{"n":2,"t":"installation"},{"n":2,"t":"sql-server-2008"},{"n":7,"t":"postgresql"},{"n":2,"t":"password-recovery"},{"n":3,"t":"permissions"},{"n":2,"t":"innodb"},{"n":2,"t":"oracle"}],"windows-server":[{"n":4,"t":"sql-server"}],"xml":[{"n":17,"t":"sql-server"},{"n":3,"t":"sql-server-2008"},{"n":2,"t":"database-design"},{"n":2,"t":"datatypes"},{"n":4,"t":"sql-server-2012"},{"n":3,"t":"execution-plan"},{"n":2,"t":"t-sql"},{"n":2,"t":"stored-procedures"},{"n":3,"t":"performance"},{"n":3,"t":"sql-server-2008-r2"},{"n":3,"t":"xquery"}],"xquery":[{"n":3,"t":"sql-server"},{"n":3,"t":"xml"}]}