{"adiabatic-model":[{"n":3,"t":"annealing"}],"algorithm":[{"n":6,"t":"speedup"},{"n":11,"t":"complexity-theory"},{"n":4,"t":"circuit-construction"},{"n":3,"t":"classical-computing"},{"n":3,"t":"cryptography"},{"n":2,"t":"cryptocurrency"},{"n":2,"t":"quantum-money"},{"n":4,"t":"grovers-algorithm"},{"n":4,"t":"machine-learning"},{"n":4,"t":"quantum-enhanced-machine-learning"},{"n":2,"t":"programming"},{"n":3,"t":"resource-request"},{"n":2,"t":"simulation"},{"n":3,"t":"bqp"},{"n":3,"t":"hamiltonian-simulation"},{"n":2,"t":"qiskit"},{"n":3,"t":"hhl-algorithm"},{"n":2,"t":"phase-estimation"},{"n":3,"t":"applications"},{"n":2,"t":"research"},{"n":2,"t":"quantum-state"},{"n":2,"t":"quantum-advantage"}],"annealing":[{"n":2,"t":"d-wave"},{"n":2,"t":"models"},{"n":2,"t":"speedup"},{"n":3,"t":"adiabatic-model"}],"anyons":[{"n":2,"t":"topological-quantum-computing"}],"applications":[{"n":3,"t":"algorithm"},{"n":2,"t":"technologies"}],"architecture":[{"n":12,"t":"physical-realization"},{"n":4,"t":"physical-qubit"},{"n":4,"t":"superconducting-quantum-computing"},{"n":5,"t":"experiment"},{"n":3,"t":"quantum-gate"},{"n":2,"t":"ion-trap-quantum-computing"},{"n":2,"t":"scalability"},{"n":3,"t":"decoherence"}],"biology":[{"n":2,"t":"decoherence"}],"bloch-sphere":[{"n":2,"t":"quantum-gate"}],"bqp":[{"n":4,"t":"complexity-theory"},{"n":3,"t":"algorithm"}],"circuit-construction":[{"n":4,"t":"algorithm"},{"n":7,"t":"quantum-gate"},{"n":2,"t":"universal-gates"},{"n":2,"t":"gate-synthesis"},{"n":2,"t":"measurement"},{"n":2,"t":"quantum-state"}],"classical-computing":[{"n":2,"t":"performance"},{"n":3,"t":"algorithm"},{"n":2,"t":"history"},{"n":2,"t":"programming"}],"complexity-theory":[{"n":2,"t":"cryptography"},{"n":4,"t":"bqp"},{"n":6,"t":"speedup"},{"n":2,"t":"quantum-advantage"},{"n":11,"t":"algorithm"},{"n":2,"t":"grovers-algorithm"}],"cryptocurrency":[{"n":2,"t":"algorithm"},{"n":2,"t":"cryptography"},{"n":2,"t":"quantum-money"}],"cryptography":[{"n":2,"t":"complexity-theory"},{"n":3,"t":"algorithm"},{"n":2,"t":"cryptocurrency"},{"n":2,"t":"quantum-money"}],"d-wave":[{"n":2,"t":"annealing"},{"n":2,"t":"performance"},{"n":3,"t":"physical-realization"}],"decoherence":[{"n":3,"t":"architecture"},{"n":2,"t":"experiment"},{"n":2,"t":"biology"}],"entanglement":[{"n":3,"t":"quantum-state"}],"error-correction":[{"n":6,"t":"fault-tolerance"},{"n":2,"t":"noise"},{"n":2,"t":"terminology"},{"n":2,"t":"stabilizer-code"},{"n":2,"t":"nielsen-and-chuang"}],"experiment":[{"n":3,"t":"physical-realization"},{"n":5,"t":"architecture"},{"n":2,"t":"ion-trap-quantum-computing"},{"n":2,"t":"decoherence"},{"n":2,"t":"quantum-gate"}],"fault-tolerance":[{"n":6,"t":"error-correction"},{"n":2,"t":"noise"}],"gate-synthesis":[{"n":5,"t":"universal-gates"},{"n":2,"t":"solovay-kitaev-algorithm"},{"n":11,"t":"quantum-gate"},{"n":2,"t":"circuit-construction"},{"n":2,"t":"programming"},{"n":2,"t":"mathematics"}],"google-sycamore":[{"n":2,"t":"quantum-advantage"}],"grovers-algorithm":[{"n":4,"t":"algorithm"},{"n":2,"t":"complexity-theory"}],"hamiltonian-simulation":[{"n":2,"t":"quantum-gate"},{"n":3,"t":"simulation"},{"n":2,"t":"pauli-gates"},{"n":3,"t":"algorithm"}],"hhl-algorithm":[{"n":3,"t":"algorithm"},{"n":2,"t":"phase-estimation"}],"history":[{"n":2,"t":"classical-computing"}],"ion-trap-quantum-computing":[{"n":2,"t":"physical-realization"},{"n":2,"t":"architecture"},{"n":2,"t":"experiment"}],"machine-learning":[{"n":6,"t":"quantum-enhanced-machine-learning"},{"n":4,"t":"algorithm"},{"n":2,"t":"quantum-state"}],"mathematics":[{"n":3,"t":"quantum-gate"},{"n":2,"t":"quantum-state"},{"n":2,"t":"gate-synthesis"}],"measurement":[{"n":3,"t":"quantum-gate"},{"n":4,"t":"quantum-state"},{"n":2,"t":"circuit-construction"}],"models":[{"n":2,"t":"annealing"}],"nielsen-and-chuang":[{"n":2,"t":"error-correction"},{"n":2,"t":"stabilizer-code"}],"noise":[{"n":2,"t":"error-correction"},{"n":2,"t":"fault-tolerance"}],"pauli-gates":[{"n":2,"t":"hamiltonian-simulation"}],"performance":[{"n":2,"t":"simulation"},{"n":2,"t":"d-wave"},{"n":2,"t":"classical-computing"},{"n":2,"t":"physical-realization"}],"phase-estimation":[{"n":2,"t":"algorithm"},{"n":2,"t":"hhl-algorithm"}],"physical-qubit":[{"n":3,"t":"physical-realization"},{"n":4,"t":"architecture"},{"n":2,"t":"superconducting-quantum-computing"}],"physical-realization":[{"n":12,"t":"architecture"},{"n":3,"t":"physical-qubit"},{"n":3,"t":"superconducting-quantum-computing"},{"n":3,"t":"experiment"},{"n":3,"t":"quantum-gate"},{"n":2,"t":"ion-trap-quantum-computing"},{"n":2,"t":"scalability"},{"n":2,"t":"performance"},{"n":3,"t":"d-wave"}],"programming":[{"n":3,"t":"resource-request"},{"n":2,"t":"simulation"},{"n":2,"t":"algorithm"},{"n":3,"t":"quantum-gate"},{"n":3,"t":"qiskit"},{"n":2,"t":"classical-computing"},{"n":2,"t":"gate-synthesis"}],"qiskit":[{"n":2,"t":"quantum-gate"},{"n":3,"t":"programming"},{"n":2,"t":"algorithm"}],"quantum-advantage":[{"n":3,"t":"speedup"},{"n":2,"t":"complexity-theory"},{"n":2,"t":"algorithm"},{"n":2,"t":"google-sycamore"}],"quantum-enhanced-machine-learning":[{"n":6,"t":"machine-learning"},{"n":4,"t":"algorithm"},{"n":2,"t":"quantum-state"}],"quantum-gate":[{"n":5,"t":"quantum-state"},{"n":4,"t":"unitarity"},{"n":3,"t":"measurement"},{"n":2,"t":"quantum-operation"},{"n":7,"t":"circuit-construction"},{"n":3,"t":"architecture"},{"n":3,"t":"physical-realization"},{"n":2,"t":"hamiltonian-simulation"},{"n":6,"t":"universal-gates"},{"n":11,"t":"gate-synthesis"},{"n":3,"t":"mathematics"},{"n":3,"t":"programming"},{"n":2,"t":"qiskit"},{"n":2,"t":"bloch-sphere"},{"n":2,"t":"experiment"}],"quantum-money":[{"n":2,"t":"algorithm"},{"n":2,"t":"cryptography"},{"n":2,"t":"cryptocurrency"}],"quantum-operation":[{"n":2,"t":"quantum-gate"},{"n":2,"t":"quantum-state"}],"quantum-state":[{"n":5,"t":"quantum-gate"},{"n":4,"t":"measurement"},{"n":2,"t":"terminology"},{"n":2,"t":"superposition"},{"n":2,"t":"quantum-operation"},{"n":3,"t":"entanglement"},{"n":2,"t":"mathematics"},{"n":2,"t":"machine-learning"},{"n":2,"t":"quantum-enhanced-machine-learning"},{"n":2,"t":"circuit-construction"},{"n":2,"t":"algorithm"}],"research":[{"n":2,"t":"algorithm"}],"resource-request":[{"n":3,"t":"programming"},{"n":3,"t":"algorithm"}],"scalability":[{"n":2,"t":"physical-realization"},{"n":2,"t":"architecture"}],"simulation":[{"n":2,"t":"performance"},{"n":2,"t":"programming"},{"n":3,"t":"hamiltonian-simulation"},{"n":2,"t":"algorithm"}],"solovay-kitaev-algorithm":[{"n":2,"t":"gate-synthesis"}],"speedup":[{"n":3,"t":"quantum-advantage"},{"n":2,"t":"annealing"},{"n":6,"t":"algorithm"},{"n":6,"t":"complexity-theory"}],"stabilizer-code":[{"n":2,"t":"error-correction"},{"n":2,"t":"nielsen-and-chuang"}],"superconducting-quantum-computing":[{"n":3,"t":"physical-realization"},{"n":4,"t":"architecture"},{"n":2,"t":"physical-qubit"}],"superposition":[{"n":2,"t":"quantum-state"}],"technologies":[{"n":2,"t":"applications"}],"terminology":[{"n":2,"t":"quantum-state"},{"n":2,"t":"error-correction"}],"topological-quantum-computing":[{"n":2,"t":"anyons"}],"unitarity":[{"n":4,"t":"quantum-gate"}],"universal-gates":[{"n":5,"t":"gate-synthesis"},{"n":6,"t":"quantum-gate"},{"n":2,"t":"circuit-construction"}]}